Workbook

Sheet MOVI
A1: No. | B1: ID | C1: Mã nhân viên mới | D1: Full Name | E1: Department | F1: Business Unit | G1: Internal Job Band | H1: Current Job Title | I1: Region | J1: Company | K1: Type of Employee | L1: Employment Status | M1: Joining Date | N1: Matenity Leaving Date | O1: Unpaid | P1: Effective Leaving Date | Q1: Type of contract | U1: Contract salary | X1: ALLOWANCE | AE1: Time Attendance | AL1: Over times | AR1: Actual Gross Salary | AU1: Total Actual Gross Salary | AV1: Actual Allowance | BF1: Total Actual Allowance | BG1: INCENTIVE/BONUS | BT1: Total Bonus/ Incentive | BU1: TOTAL INCOME | BV1: Tax relief | CB1: 0.08 | CC1: 0.01 | CD1: 0.015 | CE1: 0.045 | CF1: Total SMU | CG1: Total Tax Relief | CH1: PIT | CL1: Severance Allow Payment/Net adjustments | CM1: Net Deduction | CR1: Total Net Deduction | CS1: INCOME | CV1: 0.17 | CW1: 0 | CX1: 0.03 | CY1: 0 | CZ1: 0.045 | DA1: 21.0% by ER | DB1: 0.305 | DC1: 0.02
Q2: JO/ LC/ SC | R2: TYPE OF PIT | S2: E/L | T2: Count days for Expat | U2: Basic Salary | V2: KPI salary | W2: Total Contract Salary | X2: Laptop | Y2: Transportation | Z2: Position | AA2: Phone | AB2: Housing | AC2: Meal Allowance | AD2: Total Allowance | AE2: Standard weekly | AF2: Standard WK Days | AG2: Actual WK Days | AH2: Annual Leave days | AI2: Public Holidays | AJ2: Other Paid leave | AK2: Total Actual WK Days | AL2: Standard Nomal day | AM2: Weekend | AN2: Public Holiday | AO2: Total OT hours | AP2: Total OT hours x rating OT | AQ2: Nontaxable - Total OT hous x rating OT | AR2: Actual Gross Salary | AS2: Other adjustment (+/-) | AT2: OT Payment | AV2: Laptop | AW2: Transportation | AX2: Position | AY2: Phone | AZ2: Gasoline | BA2: Housing | BB2: Training | BC2: Public Holiday | BD2: Special Allowance | BE2: Meal Allowance | BG2: Incentive for FL & TLS | BH2: Bonus for FL & TLS | BI2: Candidate referral bonus | BJ2: Debt collection | BK2: MKT Bonus | BL2: MA/MD Bonus | BM2: Delivery Bonus | BN2: B2B Bonus | BO2: CS Bonus | BP2: Logistics Bonus | BQ2: 13th Bonus | BR2: Bonus paid by region/ Benefit - in -kind or pay out cash | BS2: Engagement Program Bonus | BV2: OT-nontaxable | BW2: Phone | BX2: Meal - Non tax | BY2: Personal Deduction | BZ2: No.of Dedendants | CA2: Deduction of Dependants | CB2: SI | CC2: UI | CD2: HI | CE2: Special case | CH2: Taxed Income | CI2: PIT in month | CJ2: PIT Finalization/ Adjusment (-return/+collect) 2020 | CK2: PIT payable | CM2: Trade Union Fee | CN2: Cash advance | CO2: Mobilephone | CP2: MCA Amount | CQ2: Other Deduction | CS2: NET INCOME | CT2: PAID | CU2: BANK TRANSFER TO EE (NTH>0) | CV2: SI | CW2: UI | CX2: HI | CY2: ADI | CZ2: Special case | DA2: SI+HI+UI+ADI | DB2: Total SMU | DC2: Trade Union (2%) | DD2: GRAND TOTAL COMPANY COST | DE2: NOTE | DF2: for C&B Report | DG2: 13rd Bonus Budget | DH2: Area | DI2: Total WD 1st - 25th | DJ2: For SMU | DK2: Total Unpaid Leave for SHUI | DL2: List of union staff | DM2: Laptop | DN2: Trade Union Fee (employee) | DO2: Days of Phone Allowance | DP2: Area for report (Revenue South) | DQ2: Maternity from | DR2: Maternity to | DS2: Group | DT2: for Expense Report (Group)
A3: # | B3: 1 | C3: 1 | D3: 2 | E3: 3 | F3: =+E3+1 -> 4 | G3: =+F3+1 -> 5 | H3: =+G3+1 -> 6 | I3: =+H3+1 -> 7 | J3: =+I3+1 -> 8 | K3: =+J3+1 -> 9 | L3: =+K3+1 -> 10 | M3: =+L3+1 -> 11 | ... CA3: =+BZ3+1 -> 77 | CB3: 78 | CC3: 79 | CD3: 80 | CE3: 81 | CF3: 82 | CG3: 83 | CH3: 84 | CI3: 85 | CJ3: 86 | CK3: 87 | CL3: =+CK3+1 -> 88 | CM3: =+CL3+1 -> 89 | CN3: =+CM3+1 -> 90 | CO3: =+CN3+1 -> 91 | CP3: 92 | CQ3: =+CP3+1 -> 93 | CR3: =+CQ3+1 -> 94 | CS3: =+CR3+1 -> 95 | CT3: =+CS3+1 -> 96 | CU3: =+CT3+1 -> 97 | CV3: 98 | CW3: 99 | CX3: 100 | CY3: 101 | CZ3: 102 | DA3: 103 | DB3: 104 | DC3: =+DB3+1 -> 105 | DD3: =+DC3+1 -> 106 | DE3: =+DD3+1 -> 107 | DF3: =+DE3+1 -> 108 | DG3: =+DF3+1 -> 109 | DH3: =+DG3+1 -> 110 | DI3: =+DH3+1 -> 111 | DJ3: =+DI3+1 -> 112 | ... DT3: =+DS3+1 -> 122
A4: 1 | B4: 5031 | C4: VP005031 | D4: Trần Quốc Huy | E4: Finance | F4: Accounting & Tax | G4: Manager | H4: Chief Accountant | I4: South | J4: Việt Phú | K4: Full-time | L4: Permanent | M4: 43591 | Q4: LC | R4: LTTP | S4: L | U4: 40000000 | W4: 40000000 | X4: 0 | Y4: 0 | AA4: 0 | AC4: 0 | AD4: 0 | AE4: TB, CN | AF4: 21 | AG4: 21 | AH4: 0 | AI4: 0 | AJ4: 0 | AK4: 21 | AL4: 0 | AM4: 0 | AN4: 0 | AO4: 0 | AP4: 0 | AQ4: 0 | AR4: 40000000 | AS4: 0 | AT4: 0 | AU4: 40000000 | AV4: 0 | AW4: 0 | AX4: 0 | AY4: 0 | AZ4: 0 | BA4: 0 | BE4: 0 | BF4: 0 | BG4: 0 | BH4: 0 | BI4: 0 | BJ4: 0 | BL4: 0 | BO4: 0 | BT4: 0 | BU4: 40000000 | BV4: 0 | BW4: 0 | BX4: 0 | BY4: 11000000 | BZ4: 2 | CA4: 8800000 | CB4: 2384000 | CC4: 400000 | CD4: 447000 | CE4: 0 | CF4: 3231000 | CG4: 23031000 | CH4: 16969000 | CI4: 1795350 | CK4: 1795350 | CL4: 0 | CM4: 0 | CN4: 0 | CP4: 0 | CQ4: 0 | CR4: 0 | CS4: 34973650 | CU4: 34973650 | CV4: 5066000 | CW4: 0 | CX4: 894000 | CY4: 0 | DA4: 5960000 | DB4: 9191000 | DC4: 596000 | DD4: 46556000 | DF4: Việt PhúSouthFinance | DG4: 3333333.3 | DH4: HO | DI4: =IFERROR(VLOOKUP($B4,[1]Timesheet!$D:$BK,51,0),0) -> 18 | DJ4: =IFERROR(VLOOKUP($B4,[1]Timesheet!$D:$BK,52,0),0) -> 0 | DK4: =IFERROR(VLOOKUP($B4,[1]Timesheet!$D:$BK,55,0),0) -> 0 | DL4: 0 | DM4: =IFERROR(VLOOKUP($B4,[1]Timesheet!$D:$BK,57,0),0) -> 0 | DN4: =IF(AND(DL4="x",CB4>0),MIN(ROUND(W4*1%,0),149000),0) -> 0 | DP4: =IF(E4="Sales",IF(F4="Logistics",F4,IF(F4="Marketing",F4,DH4)),"") | DQ4: 0 | DR4: 0 | DS4: =IFERROR(VLOOKUP(E4&H4,[1]Group!$D$3:$G$40,4,0),"") | DT4: =J4&I4&DS4 -> Việt PhúSouth
A5: 2 | B5: 2210 | C5: VP002210 | D5: Dương Thị Kim Phố | E5: Finance | F5: Accounting & Tax | G5: Senior Associate | H5: General Accountant | I5: South | J5: Việt Phú | K5: Full-time | L5: Permanent | M5: 41939 | Q5: LC | R5: LTTP | S5: L | U5: 10000000 | W5: 10000000 | X5: 0 | Y5: 0 | AA5: 0 | AC5: 0 | AD5: 0 | AE5: TB, CN | AF5: 21 | AG5: 21 | AH5: 0 | AI5: 0 | AJ5: 0 | AK5: 21 | AL5: 0 | AM5: 0 | AN5: 0 | AO5: 0 | AP5: 0 | AQ5: 0 | AR5: 10000000 | AS5: 0 | AT5: 0 | AU5: 10000000 | AV5: 0 | AW5: 0 | AX5: 0 | AY5: 0 | AZ5: 0 | BA5: 0 | BE5: 0 | BF5: 0 | BG5: 0 | BH5: 0 | BI5: 0 | BJ5: 0 | BL5: 0 | BO5: 0 | BT5: 0 | BU5: 10000000 | BV5: 0 | BW5: 0 | BX5: 0 | BY5: 11000000 | BZ5: 2 | CA5: 8800000 | CB5: 800000 | CC5: 100000 | CD5: 150000 | CE5: 0 | CF5: 1050000 | CG5: 20850000 | CH5: 0 | CI5: 0 | CK5: 0 | CL5: 0 | CM5: 100000 | CN5: 0 | CP5: 310000 | CQ5: 0 | CR5: 410000 | CS5: 8540000 | CU5: 8540000 | CV5: 1700000 | CW5: 0 | CX5: 300000 | CY5: 0 | DA5: 2000000 | DB5: 3050000 | DC5: 200000 | DD5: 12200000 | DF5: Việt PhúSouthFinance | DG5: 833333.33 | DH5: HO | DI5: =IFERROR(VLOOKUP($B5,[1]Timesheet!$D:$BK,51,0),0) -> 18 | DJ5: =IFERROR(VLOOKUP($B5,[1]Timesheet!$D:$BK,52,0),0) -> 0 | DK5: =IFERROR(VLOOKUP($B5,[1]Timesheet!$D:$BK,55,0),0) -> 0 | DL5: x | DM5: =IFERROR(VLOOKUP($B5,[1]Timesheet!$D:$BK,57,0),0) -> 0 | DN5: =IF(AND(DL5="x",CB5>0),MIN(ROUND(W5*1%,0),149000),0) -> 100000 | DP5: =IF(E5="Sales",IF(F5="Logistics",F5,IF(F5="Marketing",F5,DH5)),"") | DQ5: 43595 | DR5: 43777 | DS5: =IFERROR(VLOOKUP(E5&H5,[1]Group!$D$3:$G$40,4,0),"") | DT5: =J5&I5&DS5 -> Việt PhúSouth
A6: 3 | B6: 5162 | C6: VP005162 | D6: Lưu Nguyễn Phương Uyên | E6: Finance | F6: Accounting & Tax | G6: Senior Associate | H6: General Accountant | I6: South | J6: Việt Phú | K6: Full-time | L6: Permanent | M6: 43668 | Q6: LC | R6: LTTP | S6: L | U6: 10000000 | W6: 10000000 | X6: 0 | Y6: 0 | AA6: 0 | AC6: 0 | AD6: 0 | AE6: TB, CN | AF6: 21 | AG6: 21 | AH6: 0 | AI6: 0 | AJ6: 0 | AK6: 21 | AL6: 0 | AM6: 0 | AN6: 0 | AO6: 0 | AP6: 0 | AQ6: 0 | AR6: 10000000 | AS6: 0 | AT6: 0 | AU6: 10000000 | AV6: 0 | AW6: 0 | AX6: 0 | AY6: 0 | AZ6: 0 | BA6: 0 | BE6: 0 | BF6: 0 | BG6: 0 | BH6: 0 | BI6: 0 | BJ6: 0 | BL6: 0 | BO6: 0 | BT6: 0 | BU6: 10000000 | BV6: 0 | BW6: 0 | BX6: 0 | BY6: 11000000 | BZ6: 0 | CA6: 0 | CB6: 800000 | CC6: 100000 | CD6: 150000 | CE6: 0 | CF6: 1050000 | CG6: 12050000 | CH6: 0 | CI6: 0 | CK6: 0 | CL6: 0 | CM6: 0 | CN6: 0 | CP6: 5500 | CQ6: 0 | CR6: 5500 | CS6: 8944500 | CU6: 8944500 | CV6: 1700000 | CW6: 0 | CX6: 300000 | CY6: 0 | DA6: 2000000 | DB6: 3050000 | DC6: 200000 | DD6: 12200000 | DF6: Việt PhúSouthFinance | DG6: 833333.33 | DH6: HO | DI6: =IFERROR(VLOOKUP($B6,[1]Timesheet!$D:$BK,51,0),0) -> 18 | DJ6: =IFERROR(VLOOKUP($B6,[1]Timesheet!$D:$BK,52,0),0) -> 0 | DK6: =IFERROR(VLOOKUP($B6,[1]Timesheet!$D:$BK,55,0),0) -> 0 | DL6: 0 | DM6: =IFERROR(VLOOKUP($B6,[1]Timesheet!$D:$BK,57,0),0) -> 0 | DN6: =IF(AND(DL6="x",CB6>0),MIN(ROUND(W6*1%,0),149000),0) -> 0 | DP6: =IF(E6="Sales",IF(F6="Logistics",F6,IF(F6="Marketing",F6,DH6)),"") | DQ6: 0 | DR6: 0 | DS6: =IFERROR(VLOOKUP(E6&H6,[1]Group!$D$3:$G$40,4,0),"") | DT6: =J6&I6&DS6 -> Việt PhúSouth
A7: 4 | B7: 5368 | C7: VP005368 | D7: Phan Thị Hải | E7: Finance | F7: Accounting & Tax | G7: Senior Associate | H7: General Accountant | I7: South | J7: Việt Phú | K7: Full-time | L7: Permanent | M7: 43739 | Q7: LC | R7: LTTP | S7: L | U7: 10000000 | W7: 10000000 | X7: 0 | Y7: 0 | AA7: 0 | AC7: 0 | AD7: 0 | AE7: TB, CN | AF7: 21 | AG7: 21 | AH7: 0 | AI7: 0 | AJ7: 0 | AK7: 21 | AL7: 0 | AM7: 0 | AN7: 0 | AO7: 0 | AP7: 0 | AQ7: 0 | AR7: 10000000 | AS7: 0 | AT7: 0 | AU7: 10000000 | AV7: 0 | AW7: 0 | AX7: 0 | AY7: 0 | AZ7: 0 | BA7: 0 | BE7: 0 | BF7: 0 | BG7: 0 | BH7: 0 | BI7: 0 | BJ7: 0 | BL7: 0 | BO7: 0 | BT7: 0 | BU7: 10000000 | BV7: 0 | BW7: 0 | BX7: 0 | BY7: 11000000 | BZ7: 1 | CA7: 4400000 | CB7: 800000 | CC7: 100000 | CD7: 150000 | CE7: 0 | CF7: 1050000 | CG7: 16450000 | CH7: 0 | CI7: 0 | CK7: 0 | CL7: 0 | CM7: 100000 | CN7: 0 | CP7: 0 | CQ7: 0 | CR7: 100000 | CS7: 8850000 | CU7: 8850000 | CV7: 1700000 | CW7: 0 | CX7: 300000 | CY7: 0 | DA7: 2000000 | DB7: 3050000 | DC7: 200000 | DD7: 12200000 | DF7: Việt PhúSouthFinance | DG7: 833333.33 | DH7: HO | DI7: =IFERROR(VLOOKUP($B7,[1]Timesheet!$D:$BK,51,0),0) -> 18 | DJ7: =IFERROR(VLOOKUP($B7,[1]Timesheet!$D:$BK,52,0),0) -> 0 | DK7: =IFERROR(VLOOKUP($B7,[1]Timesheet!$D:$BK,55,0),0) -> 0 | DL7: x | DM7: =IFERROR(VLOOKUP($B7,[1]Timesheet!$D:$BK,57,0),0) -> 0 | DN7: =IF(AND(DL7="x",CB7>0),MIN(ROUND(W7*1%,0),149000),0) -> 100000 | DP7: =IF(E7="Sales",IF(F7="Logistics",F7,IF(F7="Marketing",F7,DH7)),"") | DQ7: 0 | DR7: 0 | DS7: =IFERROR(VLOOKUP(E7&H7,[1]Group!$D$3:$G$40,4,0),"") | DT7: =J7&I7&DS7 -> Việt PhúSouth
A8: 5 | B8: 1464 | C8: VP001464 | D8: Lê Thị Cẩm Nhung | E8: Finance | F8: Funding | G8: Senior Associate | H8: Funding - Banking Relationship | I8: South | J8: Việt Phú | K8: Full-time | L8: Permanent | M8: 41680 | Q8: LC | R8: LTTP | S8: L | U8: 10000000 | W8: 10000000 | X8: 0 | Y8: 0 | AA8: 0 | AC8: 0 | AD8: 0 | AE8: TB, CN | AF8: 21 | AG8: 21 | AH8: 0 | AI8: 0 | AJ8: 0 | AK8: 21 | AL8: 0 | AM8: 0 | AN8: 0 | AO8: 0 | AP8: 0 | AQ8: 0 | AR8: 10000000 | AS8: 0 | AT8: 0 | AU8: 10000000 | AV8: 0 | AW8: 0 | AX8: 0 | AY8: 0 | AZ8: 0 | BA8: 0 | BE8: 0 | BF8: 0 | BG8: 0 | BH8: 0 | BI8: 0 | BJ8: 0 | BL8: 0 | BO8: 0 | BT8: 0 | BU8: 10000000 | BV8: 0 | BW8: 0 | BX8: 0 | BY8: 11000000 | BZ8: 1 | CA8: 4400000 | CB8: 800000 | CC8: 100000 | CD8: 150000 | CE8: 0 | CF8: 1050000 | CG8: 16450000 | CH8: 0 | CI8: 0 | CK8: 0 | CL8: 0 | CM8: 100000 | CN8: 0 | CP8: 174000 | CQ8: 0 | CR8: 274000 | CS8: 8676000 | CU8: 8676000 | CV8: 1700000 | CW8: 0 | CX8: 300000 | CY8: 0 | DA8: 2000000 | DB8: 3050000 | DC8: 200000 | DD8: 12200000 | DF8: Việt PhúSouthFinance | DG8: 833333.33 | DH8: HO | DI8: =IFERROR(VLOOKUP($B8,[1]Timesheet!$D:$BK,51,0),0) -> 18 | DJ8: =IFERROR(VLOOKUP($B8,[1]Timesheet!$D:$BK,52,0),0) -> 0 | DK8: =IFERROR(VLOOKUP($B8,[1]Timesheet!$D:$BK,55,0),0) -> 0 | DL8: x | DM8: =IFERROR(VLOOKUP($B8,[1]Timesheet!$D:$BK,57,0),0) -> 0 | DN8: =IF(AND(DL8="x",CB8>0),MIN(ROUND(W8*1%,0),149000),0) -> 100000 | DP8: =IF(E8="Sales",IF(F8="Logistics",F8,IF(F8="Marketing",F8,DH8)),"") | DQ8: 0 | DR8: 0 | DS8: =IFERROR(VLOOKUP(E8&H8,[1]Group!$D$3:$G$40,4,0),"") | DT8: =J8&I8&DS8 -> Việt PhúSouth
A9: 6 | B9: 4767 | C9: VP004767 | D9: Hoàng Thị Minh Châu | E9: Finance | F9: Planning & Analysis | G9: HOD | H9: Head of Finance | I9: South | J9: Việt Phú | K9: Full-time | L9: Maternity | M9: 43314 | N9: 15/09/2021 - 14/03/2022 | Q9: LC | R9: LTTP | S9: L | U9: 80000000 | W9: 80000000 | X9: 0 | Y9: 0 | AA9: 0 | AC9: 0 | AD9: 0 | AE9: TB, CN | AF9: 21 | AG9: 0 | AH9: 0 | AI9: 0 | AJ9: 0 | AK9: 0 | AL9: 0 | AM9: 0 | AN9: 0 | AO9: 0 | AP9: 0 | AQ9: 0 | AR9: 0 | AS9: 0 | AT9: 0 | AU9: 0 | AV9: 0 | AW9: 0 | AX9: 0 | AY9: 0 | AZ9: 0 | BA9: 0 | BE9: 0 | BF9: 0 | BG9: 0 | BH9: 0 | BI9: 0 | BJ9: 0 | BL9: 0 | BO9: 0 | BT9: 0 | BU9: 0 | BV9: 0 | BW9: 0 | BX9: 0 | BY9: 11000000 | BZ9: 0 | CA9: 0 | CB9: 0 | CC9: 0 | CD9: 0 | CE9: 0 | CF9: 0 | CG9: 11000000 | CH9: 0 | CI9: 0 | CK9: 0 | CL9: 0 | CM9: 0 | CN9: 0 | CP9: 0 | CQ9: 0 | CR9: 0 | CS9: 0 | CU9: 0 | CV9: 0 | CW9: 0 | CX9: 0 | CY9: 0 | DA9: 0 | DB9: 0 | DC9: 0 | DD9: 0 | DF9: Việt PhúSouthFinance | DG9: 6666666.7 | DH9: HO | DI9: =IFERROR(VLOOKUP($B9,[1]Timesheet!$D:$BK,51,0),0) -> 0 | DJ9: =IFERROR(VLOOKUP($B9,[1]Timesheet!$D:$BK,52,0),0) -> 0 | DK9: =IFERROR(VLOOKUP($B9,[1]Timesheet!$D:$BK,55,0),0) -> 0 | DL9: 0 | DM9: =IFERROR(VLOOKUP($B9,[1]Timesheet!$D:$BK,57,0),0) -> 0 | DN9: =IF(AND(DL9="x",CB9>0),MIN(ROUND(W9*1%,0),149000),0) -> 0 | DP9: =IF(E9="Sales",IF(F9="Logistics",F9,IF(F9="Marketing",F9,DH9)),"") | DQ9: 44454 | DR9: 44634 | DS9: =IFERROR(VLOOKUP(E9&H9,[1]Group!$D$3:$G$40,4,0),"") | DT9: =J9&I9&DS9 -> Việt PhúSouth
A10: 7 | B10: 6176 | C10: VP006176 | D10: Nguyễn Hải Hà | E10: Finance | F10: Planning & Analysis | G10: Associate | H10: Finance Analyst | I10: South | J10: Việt Phú | K10: Full-time | L10: Permanent | M10: 44382 | Q10: LC | R10: LTTP | S10: L | U10: 5000000 | W10: 5000000 | X10: 0 | Y10: 0 | AA10: 0 | AC10: 0 | AD10: 0 | AE10: TB, CN | AF10: 21 | AG10: 21 | AH10: 0 | AI10: 0 | AJ10: 0 | AK10: 21 | AL10: 0 | AM10: 0 | AN10: 0 | AO10: 0 | AP10: 0 | AQ10: 0 | AR10: 5000000 | AS10: 0 | AT10: 0 | AU10: 5000000 | AV10: 0 | AW10: 0 | AX10: 0 | AY10: 0 | AZ10: 0 | BA10: 0 | BE10: 0 | BF10: 0 | BG10: 0 | BH10: 0 | BI10: 0 | BJ10: 0 | BL10: 0 | BO10: 0 | BT10: 0 | BU10: 5000000 | BV10: 0 | BW10: 0 | BX10: 0 | BY10: 11000000 | BZ10: 0 | CA10: 0 | CB10: 400000 | CC10: 50000 | CD10: 75000 | CE10: 0 | CF10: 525000 | CG10: 11525000 | CH10: 0 | CI10: 0 | CK10: 0 | CL10: 0 | CM10: 0 | CN10: 0 | CP10: 0 | CQ10: 0 | CR10: 0 | CS10: 4475000 | CU10: 4475000 | CV10: 850000 | CW10: 0 | CX10: 150000 | CY10: 0 | DA10: 1000000 | DB10: 1525000 | DC10: 100000 | DD10: 6100000 | DF10: Việt PhúSouthFinance | DG10: 416666.67 | DH10: HO | DI10: =IFERROR(VLOOKUP($B10,[1]Timesheet!$D:$BK,51,0),0) -> 18 | DJ10: =IFERROR(VLOOKUP($B10,[1]Timesheet!$D:$BK,52,0),0) -> 0 | DK10: =IFERROR(VLOOKUP($B10,[1]Timesheet!$D:$BK,55,0),0) -> 0 | DL10: 0 | DM10: =IFERROR(VLOOKUP($B10,[1]Timesheet!$D:$BK,57,0),0) -> 0 | DN10: =IF(AND(DL10="x",CB10>0),MIN(ROUND(W10*1%,0),149000),0) -> 0 | DP10: =IF(E10="Sales",IF(F10="Logistics",F10,IF(F10="Marketing",F10,DH10)),"") | DQ10: 0 | DR10: 0 | DS10: =IFERROR(VLOOKUP(E10&H10,[1]Group!$D$3:$G$40,4,0),"") | DT10: =J10&I10&DS10 -> Việt PhúSouth
A11: 8 | B11: 6197 | C11: VP006197 | D11: Trần Minh Tâm | E11: Finance | F11: Bank Partnership | G11: Manager | H11: Bank Partnership Manager | I11: South | J11: Việt Phú | K11: Full-time | L11: Permanent | M11: 44445 | Q11: LC | R11: LTTP | S11: L | U11: 40000000 | W11: 40000000 | X11: 0 | Y11: 0 | AA11: 0 | AC11: 0 | AD11: 0 | AE11: TB, CN | AF11: 21 | AG11: 19 | AH11: 2 | AI11: 0 | AJ11: 0 | AK11: 21 | AL11: 0 | AM11: 0 | AN11: 0 | AO11: 0 | AP11: 0 | AQ11: 0 | AR11: 40000000 | AS11: 0 | AT11: 0 | AU11: 40000000 | AV11: 0 | AW11: 0 | AX11: 0 | AY11: 0 | AZ11: 0 | BA11: 0 | BE11: 0 | BF11: 0 | BG11: 0 | BH11: 0 | BI11: 0 | BJ11: 0 | BL11: 0 | BO11: 0 | BT11: 0 | BU11: 40000000 | BV11: 0 | BW11: 0 | BX11: 0 | BY11: 11000000 | BZ11: 0 | CA11: 0 | CB11: 2384000 | CC11: 400000 | CD11: 447000 | CE11: 0 | CF11: 3231000 | CG11: 14231000 | CH11: 25769000 | CI11: 3503800 | CK11: 3503800 | CL11: 0 | CM11: 149000 | CN11: 0 | CP11: 0 | CQ11: 0 | CR11: 149000 | CS11: 33116200 | CU11: 33116200 | CV11: 5066000 | CW11: 0 | CX11: 894000 | CY11: 0 | DA11: 5960000 | DB11: 9191000 | DC11: 596000 | DD11: 46556000 | DF11: Việt PhúSouthFinance | DG11: 3333333.3 | DH11: HO | DI11: =IFERROR(VLOOKUP($B11,[1]Timesheet!$D:$BK,51,0),0) -> 18 | DJ11: =IFERROR(VLOOKUP($B11,[1]Timesheet!$D:$BK,52,0),0) -> 0 | DK11: =IFERROR(VLOOKUP($B11,[1]Timesheet!$D:$BK,55,0),0) -> 0 | DL11: x | DM11: =IFERROR(VLOOKUP($B11,[1]Timesheet!$D:$BK,57,0),0) -> 0 | DN11: =IF(AND(DL11="x",CB11>0),MIN(ROUND(W11*1%,0),149000),0) -> 149000 | DP11: =IF(E11="Sales",IF(F11="Logistics",F11,IF(F11="Marketing",F11,DH11)),"") | DQ11: 0 | DR11: 0 | DS11: =IFERROR(VLOOKUP(E11&H11,[1]Group!$D$3:$G$40,4,0),"") | DT11: =J11&I11&DS11 -> Việt PhúSouth
A12: 9 | B12: 5456 | C12: VP005456 | D12: Nguyễn Thị Hồng Đào | E12: Finance | F12: Accounting & Tax | G12: Associate | H12: Accounting Officer | I12: South | J12: Việt Phú | K12: Full-time | L12: Permanent | M12: 43759 | Q12: LC | R12: LTTP | S12: L | U12: 5000000 | W12: 5000000 | X12: 0 | Y12: 0 | AA12: 0 | AC12: 0 | AD12: 0 | AE12: TB, CN | AF12: 21 | AG12: 21 | AH12: 0 | AI12: 0 | AJ12: 0 | AK12: 21 | AL12: 0 | AM12: 0 | AN12: 0 | AO12: 0 | AP12: 0 | AQ12: 0 | AR12: 5000000 | AS12: 0 | AT12: 0 | AU12: 5000000 | AV12: 0 | AW12: 0 | AX12: 0 | AY12: 0 | AZ12: 0 | BA12: 0 | BE12: 0 | BF12: 0 | BG12: 0 | BH12: 0 | BI12: 0 | BJ12: 0 | BL12: 0 | BO12: 0 | BT12: 0 | BU12: 5000000 | BV12: 0 | BW12: 0 | BX12: 0 | BY12: 11000000 | BZ12: 0 | CA12: 0 | CB12: 400000 | CC12: 50000 | CD12: 75000 | CE12: 0 | CF12: 525000 | CG12: 11525000 | CH12: 0 | CI12: 0 | CK12: 0 | CL12: 0 | CM12: 0 | CN12: 0 | CP12: 0 | CQ12: 0 | CR12: 0 | CS12: 4475000 | CU12: 4475000 | CV12: 850000 | CW12: 0 | CX12: 150000 | CY12: 0 | DA12: 1000000 | DB12: 1525000 | DC12: 100000 | DD12: 6100000 | DF12: Việt PhúSouthFinance | DG12: 416666.67 | DH12: HO | DI12: =IFERROR(VLOOKUP($B12,[1]Timesheet!$D:$BK,51,0),0) -> 18 | DJ12: =IFERROR(VLOOKUP($B12,[1]Timesheet!$D:$BK,52,0),0) -> 0 | DK12: =IFERROR(VLOOKUP($B12,[1]Timesheet!$D:$BK,55,0),0) -> 0 | DL12: 0 | DM12: =IFERROR(VLOOKUP($B12,[1]Timesheet!$D:$BK,57,0),0) -> 0 | DN12: =IF(AND(DL12="x",CB12>0),MIN(ROUND(W12*1%,0),149000),0) -> 0 | DP12: =IF(E12="Sales",IF(F12="Logistics",F12,IF(F12="Marketing",F12,DH12)),"") | DQ12: 0 | DR12: 0 | DS12: =IFERROR(VLOOKUP(E12&H12,[1]Group!$D$3:$G$40,4,0),"") | DT12: =J12&I12&DS12 -> Việt PhúSouth
A13: 10 | B13: 5679 | C13: VP005679 | D13: Quách Thị Phượng | E13: Finance | F13: Facilities & Workplace support | G13: Manager | H13: Manager, Work Place Support | I13: South | J13: Việt Phú | K13: Full-time | L13: Permanent | M13: 43964 | Q13: LC | R13: LTTP | S13: L | U13: 40000000 | W13: 40000000 | X13: 0 | Y13: 0 | AA13: 0 | AC13: 0 | AD13: 0 | AE13: TB, CN | AF13: 21 | AG13: 15 | AH13: 6 | AI13: 0 | AJ13: 0 | AK13: 21 | AL13: 0 | AM13: 0 | AN13: 0 | AO13: 0 | AP13: 0 | AQ13: 0 | AR13: 40000000 | AS13: 0 | AT13: 0 | AU13: 40000000 | AV13: 0 | AW13: 0 | AX13: 0 | AY13: 0 | AZ13: 0 | BA13: 0 | BE13: 0 | BF13: 0 | BG13: 0 | BH13: 0 | BI13: 0 | BJ13: 0 | BL13: 0 | BO13: 0 | BT13: 0 | BU13: 40000000 | BV13: 0 | BW13: 0 | BX13: 0 | BY13: 11000000 | BZ13: 3 | CA13: 13200000 | CB13: 2384000 | CC13: 400000 | CD13: 447000 | CE13: 0 | CF13: 3231000 | CG13: 27431000 | CH13: 12569000 | CI13: 1135350 | CK13: 1135350 | CL13: 0 | CM13: 149000 | CN13: 0 | CP13: 0 | CQ13: 0 | CR13: 149000 | CS13: 35484650 | CU13: 35484650 | CV13: 5066000 | CW13: 0 | CX13: 894000 | CY13: 0 | DA13: 5960000 | DB13: 9191000 | DC13: 596000 | DD13: 46556000 | DF13: Việt PhúSouthFinance | DG13: 3333333.3 | DH13: HO | DI13: =IFERROR(VLOOKUP($B13,[1]Timesheet!$D:$BK,51,0),0) -> 18 | DJ13: =IFERROR(VLOOKUP($B13,[1]Timesheet!$D:$BK,52,0),0) -> 0 | DK13: =IFERROR(VLOOKUP($B13,[1]Timesheet!$D:$BK,55,0),0) -> 0 | DL13: x | DM13: =IFERROR(VLOOKUP($B13,[1]Timesheet!$D:$BK,57,0),0) -> 0 | DN13: =IF(AND(DL13="x",CB13>0),MIN(ROUND(W13*1%,0),149000),0) -> 149000 | DP13: =IF(E13="Sales",IF(F13="Logistics",F13,IF(F13="Marketing",F13,DH13)),"") | DQ13: 0 | DR13: 0 | DS13: =IFERROR(VLOOKUP(E13&H13,[1]Group!$D$3:$G$40,4,0),"") | DT13: =J13&I13&DS13 -> Việt PhúSouth
A14: 11 | B14: 4962 | C14: VP004962 | D14: Lê Thị Bạch Kim | E14: Finance | F14: Facilities & Workplace support | G14: Associate | H14: Personal Assistant cum Admin | I14: South | J14: Việt Phú | K14: Full-time | L14: Permanent | M14: 43530 | Q14: LC | R14: LTTP | S14: L | U14: 5000000 | W14: 5000000 | X14: 0 | Y14: 0 | AA14: 0 | AC14: 0 | AD14: 0 | AE14: TB, CN | AF14: 21 | AG14: 16 | AH14: 5 | AI14: 0 | AJ14: 0 | AK14: 21 | AL14: 0 | AM14: 0 | AN14: 0 | AO14: 0 | AP14: 0 | AQ14: 0 | AR14: 5000000 | AS14: 0 | AT14: 0 | AU14: 5000000 | AV14: 0 | AW14: 0 | AX14: 0 | AY14: 0 | AZ14: 0 | BA14: 0 | BE14: 0 | BF14: 0 | BG14: 0 | BH14: 0 | BI14: 0 | BJ14: 0 | BL14: 0 | BO14: 0 | BT14: 0 | BU14: 5000000 | BV14: 0 | BW14: 0 | BX14: 0 | BY14: 11000000 | BZ14: 0 | CA14: 0 | CB14: 400000 | CC14: 50000 | CD14: 75000 | CE14: 0 | CF14: 525000 | CG14: 11525000 | CH14: 0 | CI14: 0 | CK14: 0 | CL14: 0 | CM14: 50000 | CN14: 0 | CP14: 137000 | CQ14: 0 | CR14: 187000 | CS14: 4288000 | CU14: 4288000 | CV14: 850000 | CW14: 0 | CX14: 150000 | CY14: 0 | DA14: 1000000 | DB14: 1525000 | DC14: 100000 | DD14: 6100000 | DF14: Việt PhúSouthFinance | DG14: 416666.67 | DH14: HO | DI14: =IFERROR(VLOOKUP($B14,[1]Timesheet!$D:$BK,51,0),0) -> 18 | DJ14: =IFERROR(VLOOKUP($B14,[1]Timesheet!$D:$BK,52,0),0) -> 0 | DK14: =IFERROR(VLOOKUP($B14,[1]Timesheet!$D:$BK,55,0),0) -> 0 | DL14: x | DM14: =IFERROR(VLOOKUP($B14,[1]Timesheet!$D:$BK,57,0),0) -> 0 | DN14: =IF(AND(DL14="x",CB14>0),MIN(ROUND(W14*1%,0),149000),0) -> 50000 | DP14: =IF(E14="Sales",IF(F14="Logistics",F14,IF(F14="Marketing",F14,DH14)),"") | DQ14: 44161 | DR14: 44341 | DS14: =IFERROR(VLOOKUP(E14&H14,[1]Group!$D$3:$G$40,4,0),"") | DT14: =J14&I14&DS14 -> Việt PhúSouth
A15: 12 | B15: 5688 | C15: VP005688 | D15: Nguyễn Thụy Thanh Xuân | E15: Finance | F15: Facilities & Workplace support | G15: Associate | H15: Administration Officer | I15: South | J15: Việt Phú | K15: Full-time | L15: Permanent | M15: 43977 | Q15: LC | R15: LTTP | S15: L | U15: 5000000 | W15: 5000000 | X15: 0 | Y15: 0 | AA15: 0 | AC15: 0 | AD15: 0 | AE15: TB, CN | AF15: 21 | AG15: 16 | AH15: 5 | AI15: 0 | AJ15: 0 | AK15: 21 | AL15: 0 | AM15: 0 | AN15: 0 | AO15: 0 | AP15: 0 | AQ15: 0 | AR15: 5000000 | AS15: 0 | AT15: 0 | AU15: 5000000 | AV15: 0 | AW15: 0 | AX15: 0 | AY15: 0 | AZ15: 0 | BA15: 0 | BE15: 0 | BF15: 0 | BG15: 0 | BH15: 0 | BI15: 0 | BJ15: 0 | BL15: 0 | BO15: 0 | BT15: 0 | BU15: 5000000 | BV15: 0 | BW15: 0 | BX15: 0 | BY15: 11000000 | BZ15: 0 | CA15: 0 | CB15: 400000 | CC15: 50000 | CD15: 75000 | CE15: 0 | CF15: 525000 | CG15: 11525000 | CH15: 0 | CI15: 0 | CK15: 0 | CL15: 0 | CM15: 50000 | CN15: 0 | CP15: 0 | CQ15: 0 | CR15: 50000 | CS15: 4425000 | CU15: 4425000 | CV15: 850000 | CW15: 0 | CX15: 150000 | CY15: 0 | DA15: 1000000 | DB15: 1525000 | DC15: 100000 | DD15: 6100000 | DF15: Việt PhúSouthFinance | DG15: 416666.67 | DH15: HO | DI15: =IFERROR(VLOOKUP($B15,[1]Timesheet!$D:$BK,51,0),0) -> 18 | DJ15: =IFERROR(VLOOKUP($B15,[1]Timesheet!$D:$BK,52,0),0) -> 0 | DK15: =IFERROR(VLOOKUP($B15,[1]Timesheet!$D:$BK,55,0),0) -> 0 | DL15: x | DM15: =IFERROR(VLOOKUP($B15,[1]Timesheet!$D:$BK,57,0),0) -> 0 | DN15: =IF(AND(DL15="x",CB15>0),MIN(ROUND(W15*1%,0),149000),0) -> 50000 | DP15: =IF(E15="Sales",IF(F15="Logistics",F15,IF(F15="Marketing",F15,DH15)),"") | DQ15: 0 | DR15: 0 | DS15: =IFERROR(VLOOKUP(E15&H15,[1]Group!$D$3:$G$40,4,0),"") | DT15: =J15&I15&DS15 -> Việt PhúSouth
A16: 13 | B16: 6037 | C16: VP006037 | D16: Châu Hùng Minh | E16: Finance | F16: Facilities & Workplace support | G16: Associate | H16: Work Place Technician | I16: South | J16: Việt Phú | K16: Full-time | L16: Permanent | M16: 44167 | Q16: LC | R16: LTTP | S16: L | U16: 5000000 | W16: 5000000 | X16: 0 | Y16: 0 | AA16: 0 | AC16: 0 | AD16: 0 | AE16: TB, CN | AF16: 21 | AG16: 16 | AH16: 5 | AI16: 0 | AJ16: 0 | AK16: 21 | AL16: 0 | AM16: 0 | AN16: 0 | AO16: 0 | AP16: 0 | AQ16: 0 | AR16: 5000000 | AS16: 0 | AT16: 0 | AU16: 5000000 | AV16: 0 | AW16: 0 | AX16: 0 | AY16: 0 | AZ16: 0 | BA16: 0 | BE16: 0 | BF16: 0 | BG16: 0 | BH16: 0 | BI16: 0 | BJ16: 0 | BL16: 0 | BO16: 0 | BT16: 0 | BU16: 5000000 | BV16: 0 | BW16: 0 | BX16: 0 | BY16: 11000000 | BZ16: 0 | CA16: 0 | CB16: 400000 | CC16: 50000 | CD16: 75000 | CE16: 0 | CF16: 525000 | CG16: 11525000 | CH16: 0 | CI16: 0 | CK16: 0 | CL16: 0 | CM16: 50000 | CN16: 0 | CP16: 0 | CQ16: 0 | CR16: 50000 | CS16: 4425000 | CU16: 4425000 | CV16: 850000 | CW16: 0 | CX16: 150000 | CY16: 0 | DA16: 1000000 | DB16: 1525000 | DC16: 100000 | DD16: 6100000 | DF16: Việt PhúSouthFinance | DG16: 416666.67 | DH16: HO | DI16: =IFERROR(VLOOKUP($B16,[1]Timesheet!$D:$BK,51,0),0) -> 18 | DJ16: =IFERROR(VLOOKUP($B16,[1]Timesheet!$D:$BK,52,0),0) -> 0 | DK16: =IFERROR(VLOOKUP($B16,[1]Timesheet!$D:$BK,55,0),0) -> 0 | DL16: x | DM16: =IFERROR(VLOOKUP($B16,[1]Timesheet!$D:$BK,57,0),0) -> 0 | DN16: =IF(AND(DL16="x",CB16>0),MIN(ROUND(W16*1%,0),149000),0) -> 50000 | DP16: =IF(E16="Sales",IF(F16="Logistics",F16,IF(F16="Marketing",F16,DH16)),"") | DQ16: 0 | DR16: 0 | DS16: =IFERROR(VLOOKUP(E16&H16,[1]Group!$D$3:$G$40,4,0),"") | DT16: =J16&I16&DS16 -> Việt PhúSouth
A17: 14 | B17: 5701 | C17: VP005701 | D17: Nguyễn Thị Xây | E17: Finance | F17: Facilities & Workplace support | G17: Associate | H17: Cleaner (HN Office) | I17: North | J17: Việt Phú | K17: Contractor | L17: Contractor | M17: 43977 | Q17: SC | R17: 0.1 | S17: L | U17: 5000000 | W17: 5000000 | X17: 0 | Y17: 0 | AA17: 0 | AC17: 0 | AD17: 0 | AE17: CN | AF17: 26 | AG17: 26 | AH17: 0 | AI17: 0 | AJ17: 0 | AK17: 26 | AL17: 0 | AM17: 0 | AN17: 0 | AO17: 0 | AP17: 0 | AQ17: 0 | AR17: 5000000 | AS17: 0 | AT17: 0 | AU17: 5000000 | AV17: 0 | AW17: 0 | AX17: 0 | AY17: 0 | AZ17: 0 | BA17: 0 | BE17: 0 | BF17: 0 | BG17: 0 | BH17: 0 | BI17: 0 | BJ17: 0 | BL17: 0 | BO17: 0 | BT17: 0 | BU17: 5000000 | BV17: 0 | BW17: 0 | BX17: 0 | BY17: 0 | BZ17: 0 | CA17: 0 | CB17: 0 | CC17: 0 | CD17: 0 | CE17: 0 | CF17: 0 | CG17: 0 | CH17: 5000000 | CI17: 500000 | CK17: 500000 | CL17: 0 | CM17: 0 | CN17: 0 | CP17: 0 | CQ17: 0 | CR17: 0 | CS17: 4500000 | CU17: 4500000 | CV17: 0 | CW17: 0 | CX17: 0 | CY17: 0 | DA17: 0 | DB17: 0 | DC17: 0 | DD17: 5000000 | DF17: Việt PhúNorthFinance | DG17: 416666.67 | DH17: HNI | DI17: =IFERROR(VLOOKUP($B17,[1]Timesheet!$D:$BK,51,0),0) -> 22 | DJ17: =IFERROR(VLOOKUP($B17,[1]Timesheet!$D:$BK,52,0),0) -> 0 | DK17: =IFERROR(VLOOKUP($B17,[1]Timesheet!$D:$BK,55,0),0) -> 0 | DL17: 0 | DM17: =IFERROR(VLOOKUP($B17,[1]Timesheet!$D:$BK,57,0),0) -> 0 | DN17: =IF(AND(DL17="x",CB17>0),MIN(ROUND(W17*1%,0),149000),0) -> 0 | DP17: =IF(E17="Sales",IF(F17="Logistics",F17,IF(F17="Marketing",F17,DH17)),"") | DQ17: 0 | DR17: 0 | DS17: =IFERROR(VLOOKUP(E17&H17,[1]Group!$D$3:$G$40,4,0),"") | DT17: =J17&I17&DS17 -> Việt PhúNorth
A18: 15 | B18: 6109 | C18: VP006109 | D18: Lê Thị Kiều Diễm | E18: Finance | F18: Facilities & Workplace support | G18: Associate | H18: Work Place Procurement Officer | I18: South | J18: Việt Phú | K18: Full-time | L18: Permanent | M18: 44300 | Q18: LC | R18: LTTP | S18: L | U18: 5000000 | W18: 5000000 | X18: 0 | Y18: 0 | AA18: 0 | AC18: 0 | AD18: 0 | AE18: TB, CN | AF18: 21 | AG18: 17.5 | AH18: 3.5 | AI18: 0 | AJ18: 0 | AK18: 21 | AL18: 0 | AM18: 0 | AN18: 0 | AO18: 0 | AP18: 0 | AQ18: 0 | AR18: 5000000 | AS18: 0 | AT18: 0 | AU18: 5000000 | AV18: 0 | AW18: 0 | AX18: 0 | AY18: 0 | AZ18: 0 | BA18: 0 | BE18: 0 | BF18: 0 | BG18: 0 | BH18: 0 | BI18: 0 | BJ18: 0 | BL18: 0 | BO18: 0 | BT18: 0 | BU18: 5000000 | BV18: 0 | BW18: 0 | BX18: 0 | BY18: 11000000 | BZ18: 0 | CA18: 0 | CB18: 400000 | CC18: 50000 | CD18: 75000 | CE18: 0 | CF18: 525000 | CG18: 11525000 | CH18: 0 | CI18: 0 | CK18: 0 | CL18: 0 | CM18: 50000 | CN18: 0 | CP18: 0 | CQ18: 0 | CR18: 50000 | CS18: 4425000 | CU18: 4425000 | CV18: 850000 | CW18: 0 | CX18: 150000 | CY18: 0 | DA18: 1000000 | DB18: 1525000 | DC18: 100000 | DD18: 6100000 | DF18: Việt PhúSouthFinance | DG18: 416666.67 | DH18: HO | DI18: =IFERROR(VLOOKUP($B18,[1]Timesheet!$D:$BK,51,0),0) -> 18 | DJ18: =IFERROR(VLOOKUP($B18,[1]Timesheet!$D:$BK,52,0),0) -> 0 | DK18: =IFERROR(VLOOKUP($B18,[1]Timesheet!$D:$BK,55,0),0) -> 0 | DL18: x | DM18: =IFERROR(VLOOKUP($B18,[1]Timesheet!$D:$BK,57,0),0) -> 0 | DN18: =IF(AND(DL18="x",CB18>0),MIN(ROUND(W18*1%,0),149000),0) -> 50000 | DP18: =IF(E18="Sales",IF(F18="Logistics",F18,IF(F18="Marketing",F18,DH18)),"") | DQ18: 0 | DR18: 0 | DS18: =IFERROR(VLOOKUP(E18&H18,[1]Group!$D$3:$G$40,4,0),"") | DT18: =J18&I18&DS18 -> Việt PhúSouth
A19: 16 | B19: 5693 | C19: MV005693 | D19: Lê Trọng Đoan | E19: Supply Chain Management | F19: Logistics | G19: HOD | H19: Head of Logistics and Supply Chain Management | I19: South | J19: Movi | K19: Full-time | L19: Permanent | M19: 43983 | Q19: LC | R19: LTTP | S19: L | U19: 80000000 | W19: 80000000 | X19: 0 | Y19: 0 | AA19: 200000 | AC19: 0 | AD19: 200000 | AE19: TB, CN | AF19: 21 | AG19: 18 | AH19: 3 | AI19: 0 | AJ19: 0 | AK19: 21 | AL19: 0 | AM19: 0 | AN19: 0 | AO19: 0 | AP19: 0 | AQ19: 0 | AR19: 80000000 | AS19: 0 | AT19: 0 | AU19: 80000000 | AV19: 0 | AW19: 0 | AX19: 0 | AY19: 200000 | AZ19: 0 | BA19: 0 | BE19: 0 | BF19: 200000 | BG19: 0 | BH19: 0 | BI19: 0 | BJ19: 0 | BL19: 0 | BO19: 0 | BT19: 0 | BU19: 80200000 | BV19: 0 | BW19: 200000 | BX19: 0 | BY19: 11000000 | BZ19: 1 | CA19: 4400000 | CB19: 2384000 | CC19: 800000 | CD19: 447000 | CE19: 0 | CF19: 3631000 | CG19: 19231000 | CH19: 60969000 | CI19: 12440700 | CK19: 12440700 | CL19: 0 | CM19: 149000 | CN19: 0 | CP19: 9238000 | CQ19: 0 | CR19: 9387000 | CS19: 54741300 | CU19: 54741300 | CV19: 5066000 | CW19: 0 | CX19: 894000 | CY19: 0 | DA19: 5960000 | DB19: 9591000 | DC19: 596000 | DD19: 86756000 | DF19: MoviSouthSupply Chain Management | DG19: 6666666.7 | DH19: HO | DI19: =IFERROR(VLOOKUP($B19,[1]Timesheet!$D:$BK,51,0),0) -> 18 | DJ19: =IFERROR(VLOOKUP($B19,[1]Timesheet!$D:$BK,52,0),0) -> 0 | DK19: =IFERROR(VLOOKUP($B19,[1]Timesheet!$D:$BK,55,0),0) -> 0 | DL19: x | DM19: =IFERROR(VLOOKUP($B19,[1]Timesheet!$D:$BK,57,0),0) -> 0 | DN19: =IF(AND(DL19="x",CB19>0),MIN(ROUND(W19*1%,0),149000),0) -> 149000 | DP19: =IF(E19="Sales",IF(F19="Logistics",F19,IF(F19="Marketing",F19,DH19)),"") | DQ19: 0 | DR19: 0 | DS19: =IFERROR(VLOOKUP(E19&H19,[1]Group!$D$3:$G$40,4,0),"") | DT19: =J19&I19&DS19 -> MoviSouth
A20: 17 | B20: 1909 | C20: MV001909 | D20: Trần Thị Bích | E20: Supply Chain Management | F20: Logistics | G20: Supervisor | H20: Logistics Supervisor | I20: Central | J20: Movi | K20: Full-time | L20: Permanent | M20: 42181 | Q20: LC | R20: LTTP | S20: L | U20: 20000000 | W20: 20000000 | X20: 0 | Y20: 0 | AA20: 100000 | AC20: 0 | AD20: 100000 | AE20: CN | AF20: 26 | AG20: 26 | AH20: 0 | AI20: 0 | AJ20: 0 | AK20: 26 | AL20: 0 | AM20: 0 | AN20: 0 | AO20: 0 | AP20: 0 | AQ20: 0 | AR20: 20000000 | AS20: 0 | AT20: 0 | AU20: 20000000 | AV20: 0 | AW20: 0 | AX20: 0 | AY20: 100000 | AZ20: 0 | BA20: 0 | BE20: 0 | BF20: 100000 | BG20: 0 | BH20: 0 | BI20: 0 | BJ20: 0 | BL20: 0 | BO20: 0 | BT20: 0 | BU20: 20100000 | BV20: 0 | BW20: 100000 | BX20: 0 | BY20: 11000000 | BZ20: 0 | CA20: 0 | CB20: 1600000 | CC20: 200000 | CD20: 300000 | CE20: 0 | CF20: 2100000 | CG20: 13200000 | CH20: 6900000 | CI20: 440000 | CK20: 440000 | CL20: 0 | CM20: 149000 | CN20: 0 | CP20: 833000 | CQ20: 0 | CR20: 982000 | CS20: 16578000 | CU20: 16578000 | CV20: 3400000 | CW20: 0 | CX20: 600000 | CY20: 0 | DA20: 4000000 | DB20: 6100000 | DC20: 400000 | DD20: 24500000 | DF20: MoviCentralSupply Chain Management | DG20: 1666666.7 | DH20: DNG | DI20: =IFERROR(VLOOKUP($B20,[1]Timesheet!$D:$BK,51,0),0) -> 22 | DJ20: =IFERROR(VLOOKUP($B20,[1]Timesheet!$D:$BK,52,0),0) -> 0 | DK20: =IFERROR(VLOOKUP($B20,[1]Timesheet!$D:$BK,55,0),0) -> 0 | DL20: x | DM20: =IFERROR(VLOOKUP($B20,[1]Timesheet!$D:$BK,57,0),0) -> 0 | DN20: =IF(AND(DL20="x",CB20>0),MIN(ROUND(W20*1%,0),149000),0) -> 149000 | DP20: =IF(E20="Sales",IF(F20="Logistics",F20,IF(F20="Marketing",F20,DH20)),"") | DQ20: 0 | DR20: 0 | DS20: =IFERROR(VLOOKUP(E20&H20,[1]Group!$D$3:$G$40,4,0),"") -> Group 4 | DT20: =J20&I20&DS20 -> MoviCentralGroup 4
A21: 18 | B21: 3338 | C21: MV003338 | D21: Nguyễn Thanh Nhàn | E21: Supply Chain Management | F21: Logistics | G21: Assistant Manager | H21: Assistant to Supply Chain Manager | I21: South | J21: Movi | K21: Full-time | L21: Permanent | M21: 42650 | Q21: LC | R21: LTTP | S21: L | U21: 30000000 | W21: 30000000 | X21: 0 | Y21: 0 | AA21: 200000 | AC21: 0 | AD21: 200000 | AE21: CN | AF21: 26 | AG21: 26 | AH21: 0 | AI21: 0 | AJ21: 0 | AK21: 26 | AL21: 0 | AM21: 0 | AN21: 0 | AO21: 0 | AP21: 0 | AQ21: 0 | AR21: 30000000 | AS21: 0 | AT21: 0 | AU21: 30000000 | AV21: 0 | AW21: 0 | AX21: 0 | AY21: 200000 | AZ21: 0 | BA21: 0 | BE21: 0 | BF21: 200000 | BG21: 0 | BH21: 0 | BI21: 0 | BJ21: 0 | BL21: 0 | BO21: 0 | BT21: 0 | BU21: 30200000 | BV21: 0 | BW21: 200000 | BX21: 0 | BY21: 11000000 | BZ21: 0 | CA21: 0 | CB21: 2384000 | CC21: 300000 | CD21: 447000 | CE21: 0 | CF21: 3131000 | CG21: 14331000 | CH21: 15869000 | CI21: 1630350 | CK21: 1630350 | CL21: 0 | CM21: 149000 | CN21: 0 | CP21: 0 | CQ21: 0 | CR21: 149000 | CS21: 25289650 | CU21: 25289650 | CV21: 5066000 | CW21: 0 | CX21: 894000 | CY21: 0 | DA21: 5960000 | DB21: 9091000 | DC21: 596000 | DD21: 36756000 | DF21: MoviSouthSupply Chain Management | DG21: 2500000 | DH21: MKD | DI21: =IFERROR(VLOOKUP($B21,[1]Timesheet!$D:$BK,51,0),0) -> 22 | DJ21: =IFERROR(VLOOKUP($B21,[1]Timesheet!$D:$BK,52,0),0) -> 0 | DK21: =IFERROR(VLOOKUP($B21,[1]Timesheet!$D:$BK,55,0),0) -> 0 | DL21: x | DM21: =IFERROR(VLOOKUP($B21,[1]Timesheet!$D:$BK,57,0),0) -> 0 | DN21: =IF(AND(DL21="x",CB21>0),MIN(ROUND(W21*1%,0),149000),0) -> 149000 | DP21: =IF(E21="Sales",IF(F21="Logistics",F21,IF(F21="Marketing",F21,DH21)),"") | DQ21: 0 | DR21: 0 | DS21: =IFERROR(VLOOKUP(E21&H21,[1]Group!$D$3:$G$40,4,0),"") | DT21: =J21&I21&DS21 -> MoviSouth
A22: 19 | B22: 1853 | C22: MV001853 | D22: Trần Thị Trang | E22: Supply Chain Management | F22: Logistics | G22: Supervisor | H22: Logistics Supervisor | I22: North | J22: Movi | K22: Full-time | L22: Permanent | M22: 42137 | Q22: LC | R22: LTTP | S22: L | U22: 20000000 | W22: 20000000 | X22: 0 | Y22: 0 | AA22: 200000 | AC22: 0 | AD22: 200000 | AE22: CN | AF22: 26 | AG22: 26 | AH22: 0 | AI22: 0 | AJ22: 0 | AK22: 26 | AL22: 0 | AM22: 0 | AN22: 0 | AO22: 0 | AP22: 0 | AQ22: 0 | AR22: 20000000 | AS22: 0 | AT22: 0 | AU22: 20000000 | AV22: 0 | AW22: 0 | AX22: 0 | AY22: 200000 | AZ22: 0 | BA22: 0 | BE22: 0 | BF22: 200000 | BG22: 0 | BH22: 0 | BI22: 0 | BJ22: 0 | BL22: 0 | BO22: 0 | BT22: 0 | BU22: 20200000 | BV22: 0 | BW22: 200000 | BX22: 0 | BY22: 11000000 | BZ22: 1 | CA22: 4400000 | CB22: 1600000 | CC22: 200000 | CD22: 300000 | CE22: 0 | CF22: 2100000 | CG22: 17700000 | CH22: 2500000 | CI22: 125000 | CK22: 125000 | CL22: 0 | CM22: 149000 | CN22: 0 | CP22: 1459000 | CQ22: 0 | CR22: 1608000 | CS22: 16367000 | CU22: 16367000 | CV22: 3400000 | CW22: 0 | CX22: 600000 | CY22: 0 | DA22: 4000000 | DB22: 6100000 | DC22: 400000 | DD22: 24600000 | DF22: MoviNorthSupply Chain Management | DG22: 1666666.7 | DH22: HNI | DI22: =IFERROR(VLOOKUP($B22,[1]Timesheet!$D:$BK,51,0),0) -> 22 | DJ22: =IFERROR(VLOOKUP($B22,[1]Timesheet!$D:$BK,52,0),0) -> 0 | DK22: =IFERROR(VLOOKUP($B22,[1]Timesheet!$D:$BK,55,0),0) -> 0 | DL22: x | DM22: =IFERROR(VLOOKUP($B22,[1]Timesheet!$D:$BK,57,0),0) -> 0 | DN22: =IF(AND(DL22="x",CB22>0),MIN(ROUND(W22*1%,0),149000),0) -> 149000 | DP22: =IF(E22="Sales",IF(F22="Logistics",F22,IF(F22="Marketing",F22,DH22)),"") | DQ22: 0 | DR22: 0 | DS22: =IFERROR(VLOOKUP(E22&H22,[1]Group!$D$3:$G$40,4,0),"") -> Group 4 | DT22: =J22&I22&DS22 -> MoviNorthGroup 4
A23: 20 | B23: 4065 | C23: MV004065 | D23: Nguyễn Thị Ngọc Yến | E23: Supply Chain Management | F23: Logistics | G23: Supervisor | H23: Logistics Supervisor | I23: South | J23: Movi | K23: Full-time | L23: Permanent | M23: 43054 | Q23: LC | R23: LTTP | S23: L | U23: 20000000 | W23: 20000000 | X23: 0 | Y23: 0 | AA23: 200000 | AC23: 0 | AD23: 200000 | AE23: CN | AF23: 26 | AG23: 26 | AH23: 0 | AI23: 0 | AJ23: 0 | AK23: 26 | AL23: 0 | AM23: 0 | AN23: 0 | AO23: 0 | AP23: 0 | AQ23: 0 | AR23: 20000000 | AS23: 0 | AT23: 0 | AU23: 20000000 | AV23: 0 | AW23: 0 | AX23: 0 | AY23: 200000 | AZ23: 0 | BA23: 0 | BE23: 0 | BF23: 200000 | BG23: 0 | BH23: 0 | BI23: 0 | BJ23: 0 | BL23: 0 | BO23: 0 | BT23: 0 | BU23: 20200000 | BV23: 0 | BW23: 200000 | BX23: 0 | BY23: 11000000 | BZ23: 0 | CA23: 0 | CB23: 1600000 | CC23: 200000 | CD23: 300000 | CE23: 0 | CF23: 2100000 | CG23: 13300000 | CH23: 6900000 | CI23: 440000 | CK23: 440000 | CL23: 0 | CM23: 149000 | CN23: 0 | CP23: 0 | CQ23: 0 | CR23: 149000 | CS23: 17511000 | CU23: 17511000 | CV23: 3400000 | CW23: 0 | CX23: 600000 | CY23: 0 | DA23: 4000000 | DB23: 6100000 | DC23: 400000 | DD23: 24600000 | DF23: MoviSouthSupply Chain Management | DG23: 1666666.7 | DH23: MKD | DI23: =IFERROR(VLOOKUP($B23,[1]Timesheet!$D:$BK,51,0),0) -> 22 | DJ23: =IFERROR(VLOOKUP($B23,[1]Timesheet!$D:$BK,52,0),0) -> 0 | DK23: =IFERROR(VLOOKUP($B23,[1]Timesheet!$D:$BK,55,0),0) -> 0 | DL23: x | DM23: =IFERROR(VLOOKUP($B23,[1]Timesheet!$D:$BK,57,0),0) -> 0 | DN23: =IF(AND(DL23="x",CB23>0),MIN(ROUND(W23*1%,0),149000),0) -> 149000 | DP23: =IF(E23="Sales",IF(F23="Logistics",F23,IF(F23="Marketing",F23,DH23)),"") | DQ23: 0 | DR23: 0 | DS23: =IFERROR(VLOOKUP(E23&H23,[1]Group!$D$3:$G$40,4,0),"") -> Group 4 | DT23: =J23&I23&DS23 -> MoviSouthGroup 4
A24: 21 | B24: 2503 | C24: MV002503 | D24: Ngô Thị Phương Thảo | E24: Sales | F24: Field Sales | G24: Associate | H24: Field sales | I24: South | J24: Movi | K24: Full-time | L24: Permanent | M24: 42191 | Q24: LC | R24: LTTP | S24: L | U24: 5000000 | W24: 5000000 | X24: 0 | Y24: 0 | AA24: 200000 | AC24: 730000 | AD24: 930000 | AE24: CN | AF24: 26 | AG24: 24.5 | AH24: 1.5 | AI24: 0 | AJ24: 0 | AK24: 26 | AL24: 0 | AM24: 0 | AN24: 0 | AO24: 0 | AP24: 0 | AQ24: 0 | AR24: 5000000 | AS24: 0 | AT24: 0 | AU24: 5000000 | AV24: 0 | AW24: 0 | AX24: 0 | AY24: 200000 | AZ24: 0 | BA24: 0 | BE24: 687885 | BF24: 887885 | BG24: 0 | BH24: 0 | BI24: 0 | BJ24: 0 | BL24: 0 | BO24: 0 | BT24: 0 | BU24: 5887885 | BV24: 0 | BW24: 200000 | BX24: 687885 | BY24: 11000000 | BZ24: 0 | CA24: 0 | CB24: 400000 | CC24: 50000 | CD24: 75000 | CE24: 0 | CF24: 525000 | CG24: 12412885 | CH24: 0 | CI24: 0 | CK24: 0 | CL24: 0 | CM24: 50000 | CN24: 0 | CP24: 594000 | CQ24: 0 | CR24: 644000 | CS24: 4718885 | CU24: 4718885 | CV24: 850000 | CW24: 0 | CX24: 150000 | CY24: 0 | DA24: 1000000 | DB24: 1525000 | DC24: 100000 | DD24: 6987885 | DF24: MoviSouthSales | DG24: 416666.67 | DH24: DNI | DI24: =IFERROR(VLOOKUP($B24,[1]Timesheet!$D:$BK,51,0),0) -> 22 | DJ24: =IFERROR(VLOOKUP($B24,[1]Timesheet!$D:$BK,52,0),0) -> 0 | DK24: =IFERROR(VLOOKUP($B24,[1]Timesheet!$D:$BK,55,0),0) -> 0 | DL24: x | DM24: =IFERROR(VLOOKUP($B24,[1]Timesheet!$D:$BK,57,0),0) -> 0 | DN24: =IF(AND(DL24="x",CB24>0),MIN(ROUND(W24*1%,0),149000),0) -> 50000 | DP24: =IF(E24="Sales",IF(F24="Logistics",F24,IF(F24="Marketing",F24,DH24)),"") -> DNI | DQ24: 0 | DR24: 0 | DS24: =IFERROR(VLOOKUP(E24&H24,[1]Group!$D$3:$G$40,4,0),"") -> Group 1 | DT24: =J24&I24&DS24 -> MoviSouthGroup 1
A25: 22 | B25: 3633 | C25: MV003633 | D25: Nguyễn Minh Kha | E25: Supply Chain Management | F25: Logistics | G25: Associate | H25: Logistics Officer | I25: South | J25: Movi | K25: Full-time | L25: Leaving | M25: 42898 | P25: 44532 | Q25: LC | R25: LTTP | S25: L | U25: 5000000 | W25: 5000000 | X25: 0 | Y25: 0 | AA25: 100000 | AC25: 0 | AD25: 100000 | AE25: CN | AF25: 26 | AG25: 5 | AH25: 0 | AI25: 0 | AJ25: 0 | AK25: 5 | AL25: 0 | AM25: 0 | AN25: 0 | AO25: 0 | AP25: 0 | AQ25: 0 | AR25: 961538 | AS25: 1076923 | AT25: 0 | AU25: 2038461 | AV25: 0 | AW25: 0 | AX25: 0 | AY25: 50000 | AZ25: 0 | BA25: 0 | BE25: 0 | BF25: 50000 | BG25: 0 | BH25: 0 | BI25: 0 | BJ25: 0 | BL25: 0 | BO25: 0 | BT25: 0 | BU25: 2088461 | BV25: 0 | BW25: 50000 | BX25: 0 | BY25: 11000000 | BZ25: 0 | CA25: 0 | CB25: 0 | CC25: 0 | CD25: 0 | CE25: 0 | CF25: 0 | CG25: 11050000 | CH25: 0 | CI25: 0 | CK25: 0 | CL25: 0 | CM25: 0 | CN25: 0 | CP25: 0 | CQ25: 0 | CR25: 0 | CS25: 2088461 | CU25: 2088461 | CV25: 0 | CW25: 0 | CX25: 0 | CY25: 0 | DA25: 0 | DB25: 0 | DC25: 0 | DD25: 2088461 | DF25: MoviSouthSupply Chain Management | DG25: 416666.67 | DH25: DNI | DI25: =IFERROR(VLOOKUP($B25,[1]Timesheet!$D:$BK,51,0),0) -> 1 | DJ25: =IFERROR(VLOOKUP($B25,[1]Timesheet!$D:$BK,52,0),0) -> 0 | DK25: =IFERROR(VLOOKUP($B25,[1]Timesheet!$D:$BK,55,0),0) -> 0 | DL25: 0 | DM25: =IFERROR(VLOOKUP($B25,[1]Timesheet!$D:$BK,57,0),0) -> 0 | DN25: =IF(AND(DL25="x",CB25>0),MIN(ROUND(W25*1%,0),149000),0) -> 0 | DP25: =IF(E25="Sales",IF(F25="Logistics",F25,IF(F25="Marketing",F25,DH25)),"") | DQ25: 0 | DR25: 0 | DS25: =IFERROR(VLOOKUP(E25&H25,[1]Group!$D$3:$G$40,4,0),"") -> Group 4 | DT25: =J25&I25&DS25 -> MoviSouthGroup 4
A26: 23 | B26: 2745 | C26: MV002745 | D26: Lê Đăng Hiệu | E26: Supply Chain Management | F26: Logistics | G26: Associate | H26: Logistics Officer | I26: South | J26: Movi | K26: Full-time | L26: Permanent | M26: 42338 | Q26: LC | R26: LTTP | S26: L | U26: 5000000 | W26: 5000000 | X26: 0 | Y26: 0 | AA26: 200000 | AC26: 0 | AD26: 200000 | AE26: CN | AF26: 26 | AG26: 26 | AH26: 0 | AI26: 0 | AJ26: 0 | AK26: 26 | AL26: 0 | AM26: 0 | AN26: 0 | AO26: 0 | AP26: 0 | AQ26: 0 | AR26: 5000000 | AS26: 0 | AT26: 0 | AU26: 5000000 | AV26: 0 | AW26: 0 | AX26: 0 | AY26: 200000 | AZ26: 0 | BA26: 0 | BE26: 0 | BF26: 200000 | BG26: 0 | BH26: 0 | BI26: 0 | BJ26: 0 | BL26: 0 | BO26: 0 | BT26: 0 | BU26: 5200000 | BV26: 0 | BW26: 200000 | BX26: 0 | BY26: 11000000 | BZ26: 0 | CA26: 0 | CB26: 400000 | CC26: 50000 | CD26: 75000 | CE26: 0 | CF26: 525000 | CG26: 11725000 | CH26: 0 | CI26: 0 | CK26: 0 | CL26: 0 | CM26: 50000 | CN26: 0 | CP26: 3179000 | CQ26: 0 | CR26: 3229000 | CS26: 1446000 | CU26: 1446000 | CV26: 850000 | CW26: 0 | CX26: 150000 | CY26: 0 | DA26: 1000000 | DB26: 1525000 | DC26: 100000 | DD26: 6300000 | DF26: MoviSouthSupply Chain Management | DG26: 416666.67 | DH26: HCM | DI26: =IFERROR(VLOOKUP($B26,[1]Timesheet!$D:$BK,51,0),0) -> 22 | DJ26: =IFERROR(VLOOKUP($B26,[1]Timesheet!$D:$BK,52,0),0) -> 0 | DK26: =IFERROR(VLOOKUP($B26,[1]Timesheet!$D:$BK,55,0),0) -> 0 | DL26: x | DM26: =IFERROR(VLOOKUP($B26,[1]Timesheet!$D:$BK,57,0),0) -> 0 | DN26: =IF(AND(DL26="x",CB26>0),MIN(ROUND(W26*1%,0),149000),0) -> 50000 | DP26: =IF(E26="Sales",IF(F26="Logistics",F26,IF(F26="Marketing",F26,DH26)),"") | DQ26: 0 | DR26: 0 | DS26: =IFERROR(VLOOKUP(E26&H26,[1]Group!$D$3:$G$40,4,0),"") -> Group 4 | DT26: =J26&I26&DS26 -> MoviSouthGroup 4
A27: 24 | B27: 5056 | C27: MV005056 | D27: Nguyễn Văn Việt | E27: Supply Chain Management | F27: Logistics | G27: Associate | H27: Logistics Officer | I27: South | J27: Movi | K27: Full-time | L27: Permanent | M27: 43616 | Q27: LC | R27: LTTP | S27: L | U27: 5000000 | W27: 5000000 | X27: 0 | Y27: 0 | AA27: 0 | AC27: 0 | AD27: 0 | AE27: CN | AF27: 26 | AG27: 26 | AH27: 0 | AI27: 0 | AJ27: 0 | AK27: 26 | AL27: 0 | AM27: 0 | AN27: 0 | AO27: 0 | AP27: 0 | AQ27: 0 | AR27: 5000000 | AS27: 0 | AT27: 0 | AU27: 5000000 | AV27: 0 | AW27: 0 | AX27: 0 | AY27: 0 | AZ27: 0 | BA27: 0 | BE27: 0 | BF27: 0 | BG27: 0 | BH27: 0 | BI27: 0 | BJ27: 0 | BL27: 0 | BO27: 0 | BT27: 0 | BU27: 5000000 | BV27: 0 | BW27: 0 | BX27: 0 | BY27: 11000000 | BZ27: 0 | CA27: 0 | CB27: 400000 | CC27: 50000 | CD27: 75000 | CE27: 0 | CF27: 525000 | CG27: 11525000 | CH27: 0 | CI27: 0 | CK27: 0 | CL27: 0 | CM27: 0 | CN27: 0 | CP27: 0 | CQ27: 0 | CR27: 0 | CS27: 4475000 | CU27: 4475000 | CV27: 850000 | CW27: 0 | CX27: 150000 | CY27: 0 | DA27: 1000000 | DB27: 1525000 | DC27: 100000 | DD27: 6100000 | DF27: MoviSouthSupply Chain Management | DG27: 416666.67 | DH27: MKD | DI27: =IFERROR(VLOOKUP($B27,[1]Timesheet!$D:$BK,51,0),0) -> 22 | DJ27: =IFERROR(VLOOKUP($B27,[1]Timesheet!$D:$BK,52,0),0) -> 0 | DK27: =IFERROR(VLOOKUP($B27,[1]Timesheet!$D:$BK,55,0),0) -> 0 | DL27: 0 | DM27: =IFERROR(VLOOKUP($B27,[1]Timesheet!$D:$BK,57,0),0) -> 0 | DN27: =IF(AND(DL27="x",CB27>0),MIN(ROUND(W27*1%,0),149000),0) -> 0 | DP27: =IF(E27="Sales",IF(F27="Logistics",F27,IF(F27="Marketing",F27,DH27)),"") | DQ27: 0 | DR27: 0 | DS27: =IFERROR(VLOOKUP(E27&H27,[1]Group!$D$3:$G$40,4,0),"") -> Group 4 | DT27: =J27&I27&DS27 -> MoviSouthGroup 4
A28: 25 | B28: 5107 | C28: MV005107 | D28: Hồ Trung Tín | E28: Supply Chain Management | F28: Logistics | G28: Supervisor | H28: Logistics Supervisor | I28: South | J28: Movi | K28: Full-time | L28: Permanent | M28: 43642 | Q28: LC | R28: LTTP | S28: L | U28: 20000000 | W28: 20000000 | X28: 0 | Y28: 0 | AA28: 200000 | AC28: 0 | AD28: 200000 | AE28: CN | AF28: 26 | AG28: 26 | AH28: 0 | AI28: 0 | AJ28: 0 | AK28: 26 | AL28: 0 | AM28: 0 | AN28: 0 | AO28: 0 | AP28: 0 | AQ28: 0 | AR28: 20000000 | AS28: 0 | AT28: 0 | AU28: 20000000 | AV28: 0 | AW28: 0 | AX28: 0 | AY28: 200000 | AZ28: 0 | BA28: 0 | BE28: 0 | BF28: 200000 | BG28: 0 | BH28: 0 | BI28: 0 | BJ28: 0 | BL28: 0 | BO28: 0 | BT28: 0 | BU28: 20200000 | BV28: 0 | BW28: 200000 | BX28: 0 | BY28: 11000000 | BZ28: 0 | CA28: 0 | CB28: 1600000 | CC28: 200000 | CD28: 300000 | CE28: 0 | CF28: 2100000 | CG28: 13300000 | CH28: 6900000 | CI28: 440000 | CK28: 440000 | CL28: 0 | CM28: 0 | CN28: 0 | CP28: 0 | CQ28: 0 | CR28: 0 | CS28: 17660000 | CU28: 17660000 | CV28: 3400000 | CW28: 0 | CX28: 600000 | CY28: 0 | DA28: 4000000 | DB28: 6100000 | DC28: 400000 | DD28: 24600000 | DF28: MoviSouthSupply Chain Management | DG28: 1666666.7 | DH28: BDG | DI28: =IFERROR(VLOOKUP($B28,[1]Timesheet!$D:$BK,51,0),0) -> 22 | DJ28: =IFERROR(VLOOKUP($B28,[1]Timesheet!$D:$BK,52,0),0) -> 0 | DK28: =IFERROR(VLOOKUP($B28,[1]Timesheet!$D:$BK,55,0),0) -> 0 | DL28: 0 | DM28: =IFERROR(VLOOKUP($B28,[1]Timesheet!$D:$BK,57,0),0) -> 0 | DN28: =IF(AND(DL28="x",CB28>0),MIN(ROUND(W28*1%,0),149000),0) -> 0 | DP28: =IF(E28="Sales",IF(F28="Logistics",F28,IF(F28="Marketing",F28,DH28)),"") | DQ28: 0 | DR28: 0 | DS28: =IFERROR(VLOOKUP(E28&H28,[1]Group!$D$3:$G$40,4,0),"") -> Group 4 | DT28: =J28&I28&DS28 -> MoviSouthGroup 4
A29: 26 | B29: 2536 | C29: MV002536 | D29: Đào Tuấn Anh | E29: Supply Chain Management | F29: Logistics | G29: Associate | H29: Delivery Man | I29: North | J29: Movi | K29: Full-time | L29: Permanent | M29: 42255 | Q29: LC | R29: LTTP | S29: L | U29: 5000000 | W29: 5000000 | X29: 0 | Y29: 0 | AA29: 100000 | AC29: 0 | AD29: 100000 | AE29: CN | AF29: 26 | AG29: 26 | AH29: 0 | AI29: 0 | AJ29: 0 | AK29: 26 | AL29: 0 | AM29: 0 | AN29: 0 | AO29: 0 | AP29: 0 | AQ29: 0 | AR29: 5000000 | AS29: 0 | AT29: 0 | AU29: 5000000 | AV29: 0 | AW29: 0 | AX29: 0 | AY29: 100000 | AZ29: 0 | BA29: 0 | BE29: 0 | BF29: 100000 | BG29: 0 | BH29: 0 | BI29: 0 | BJ29: 0 | BL29: 0 | BO29: 0 | BT29: 0 | BU29: 5100000 | BV29: 0 | BW29: 100000 | BX29: 0 | BY29: 11000000 | BZ29: 2 | CA29: 8800000 | CB29: 400000 | CC29: 50000 | CD29: 75000 | CE29: 0 | CF29: 525000 | CG29: 20425000 | CH29: 0 | CI29: 0 | CK29: 0 | CL29: 0 | CM29: 50000 | CN29: 0 | CP29: 0 | CQ29: 0 | CR29: 50000 | CS29: 4525000 | CU29: 4525000 | CV29: 850000 | CW29: 0 | CX29: 150000 | CY29: 0 | DA29: 1000000 | DB29: 1525000 | DC29: 100000 | DD29: 6200000 | DF29: MoviNorthSupply Chain Management | DG29: 416666.67 | DH29: THA | DI29: =IFERROR(VLOOKUP($B29,[1]Timesheet!$D:$BK,51,0),0) -> 22 | DJ29: =IFERROR(VLOOKUP($B29,[1]Timesheet!$D:$BK,52,0),0) -> 0 | DK29: =IFERROR(VLOOKUP($B29,[1]Timesheet!$D:$BK,55,0),0) -> 0 | DL29: x | DM29: =IFERROR(VLOOKUP($B29,[1]Timesheet!$D:$BK,57,0),0) -> 0 | DN29: =IF(AND(DL29="x",CB29>0),MIN(ROUND(W29*1%,0),149000),0) -> 50000 | DP29: =IF(E29="Sales",IF(F29="Logistics",F29,IF(F29="Marketing",F29,DH29)),"") | DQ29: 0 | DR29: 0 | DS29: =IFERROR(VLOOKUP(E29&H29,[1]Group!$D$3:$G$40,4,0),"") -> Group 4 | DT29: =J29&I29&DS29 -> MoviNorthGroup 4
A30: 27 | B30: 2482 | C30: MV002482 | D30: Nguyễn Văn Bình | E30: Supply Chain Management | F30: Logistics | G30: Associate | H30: Delivery man | I30: South | J30: Movi | K30: Full-time | L30: Permanent | M30: 42177 | Q30: LC | R30: LTTP | S30: L | U30: 5000000 | W30: 5000000 | X30: 0 | Y30: 0 | AA30: 100000 | AC30: 0 | AD30: 100000 | AE30: CN | AF30: 26 | AG30: 25 | AH30: 1 | AI30: 0 | AJ30: 0 | AK30: 26 | AL30: 0 | AM30: 0 | AN30: 0 | AO30: 0 | AP30: 0 | AQ30: 0 | AR30: 5000000 | AS30: 0 | AT30: 0 | AU30: 5000000 | AV30: 0 | AW30: 0 | AX30: 0 | AY30: 100000 | AZ30: 0 | BA30: 0 | BE30: 0 | BF30: 100000 | BG30: 0 | BH30: 0 | BI30: 0 | BJ30: 0 | BL30: 0 | BO30: 0 | BT30: 0 | BU30: 5100000 | BV30: 0 | BW30: 100000 | BX30: 0 | BY30: 11000000 | BZ30: 0 | CA30: 0 | CB30: 400000 | CC30: 50000 | CD30: 75000 | CE30: 0 | CF30: 525000 | CG30: 11625000 | CH30: 0 | CI30: 0 | CK30: 0 | CL30: 0 | CM30: 50000 | CN30: 0 | CP30: 1185000 | CQ30: 0 | CR30: 1235000 | CS30: 3340000 | CU30: 3340000 | CV30: 850000 | CW30: 0 | CX30: 150000 | CY30: 0 | DA30: 1000000 | DB30: 1525000 | DC30: 100000 | DD30: 6200000 | DF30: MoviSouthSupply Chain Management | DG30: 416666.67 | DH30: MKD | DI30: =IFERROR(VLOOKUP($B30,[1]Timesheet!$D:$BK,51,0),0) -> 22 | DJ30: =IFERROR(VLOOKUP($B30,[1]Timesheet!$D:$BK,52,0),0) -> 0 | DK30: =IFERROR(VLOOKUP($B30,[1]Timesheet!$D:$BK,55,0),0) -> 0 | DL30: x | DM30: =IFERROR(VLOOKUP($B30,[1]Timesheet!$D:$BK,57,0),0) -> 0 | DN30: =IF(AND(DL30="x",CB30>0),MIN(ROUND(W30*1%,0),149000),0) -> 50000 | DP30: =IF(E30="Sales",IF(F30="Logistics",F30,IF(F30="Marketing",F30,DH30)),"") | DQ30: 0 | DR30: 0 | DS30: =IFERROR(VLOOKUP(E30&H30,[1]Group!$D$3:$G$40,4,0),"") -> Group 4 | DT30: =J30&I30&DS30 -> MoviSouthGroup 4
A31: 28 | B31: 2754 | C31: MV002754 | D31: Huỳnh Tấn Vũ | E31: Supply Chain Management | F31: Logistics | G31: Associate | H31: Delivery man | I31: South | J31: Movi | K31: Full-time | L31: Permanent | M31: 42340 | Q31: LC | R31: LTTP | S31: L | U31: 5000000 | W31: 5000000 | X31: 0 | Y31: 0 | AA31: 100000 | AC31: 0 | AD31: 100000 | AE31: CN | AF31: 26 | AG31: 26 | AH31: 0 | AI31: 0 | AJ31: 0 | AK31: 26 | AL31: 0 | AM31: 0 | AN31: 0 | AO31: 0 | AP31: 0 | AQ31: 0 | AR31: 5000000 | AS31: 0 | AT31: 0 | AU31: 5000000 | AV31: 0 | AW31: 0 | AX31: 0 | AY31: 100000 | AZ31: 0 | BA31: 0 | BE31: 0 | BF31: 100000 | BG31: 0 | BH31: 0 | BI31: 0 | BJ31: 0 | BL31: 0 | BO31: 0 | BT31: 0 | BU31: 5100000 | BV31: 0 | BW31: 100000 | BX31: 0 | BY31: 11000000 | BZ31: 0 | CA31: 0 | CB31: 400000 | CC31: 50000 | CD31: 75000 | CE31: 0 | CF31: 525000 | CG31: 11625000 | CH31: 0 | CI31: 0 | CK31: 0 | CL31: 0 | CM31: 50000 | CN31: 0 | CP31: 1442900 | CQ31: 0 | CR31: 1492900 | CS31: 3082100 | CU31: 3082100 | CV31: 850000 | CW31: 0 | CX31: 150000 | CY31: 0 | DA31: 1000000 | DB31: 1525000 | DC31: 100000 | DD31: 6200000 | DF31: MoviSouthSupply Chain Management | DG31: 416666.67 | DH31: TNH | DI31: =IFERROR(VLOOKUP($B31,[1]Timesheet!$D:$BK,51,0),0) -> 22 | DJ31: =IFERROR(VLOOKUP($B31,[1]Timesheet!$D:$BK,52,0),0) -> 0 | DK31: =IFERROR(VLOOKUP($B31,[1]Timesheet!$D:$BK,55,0),0) -> 0 | DL31: x | DM31: =IFERROR(VLOOKUP($B31,[1]Timesheet!$D:$BK,57,0),0) -> 0 | DN31: =IF(AND(DL31="x",CB31>0),MIN(ROUND(W31*1%,0),149000),0) -> 50000 | DP31: =IF(E31="Sales",IF(F31="Logistics",F31,IF(F31="Marketing",F31,DH31)),"") | DQ31: 0 | DR31: 0 | DS31: =IFERROR(VLOOKUP(E31&H31,[1]Group!$D$3:$G$40,4,0),"") -> Group 4 | DT31: =J31&I31&DS31 -> MoviSouthGroup 4
A32: 29 | B32: 2766 | C32: MV002766 | D32: Nguyễn Thanh Hải | E32: Supply Chain Management | F32: Logistics | G32: Associate | H32: Delivery Man | I32: North | J32: Movi | K32: Full-time | L32: Permanent | M32: 42346 | Q32: LC | R32: LTTP | S32: L | U32: 5000000 | W32: 5000000 | X32: 0 | Y32: 0 | AA32: 100000 | AC32: 0 | AD32: 100000 | AE32: CN | AF32: 26 | AG32: 26 | AH32: 0 | AI32: 0 | AJ32: 0 | AK32: 26 | AL32: 0 | AM32: 0 | AN32: 0 | AO32: 0 | AP32: 0 | AQ32: 0 | AR32: 5000000 | AS32: 0 | AT32: 0 | AU32: 5000000 | AV32: 0 | AW32: 0 | AX32: 0 | AY32: 100000 | AZ32: 0 | BA32: 0 | BE32: 0 | BF32: 100000 | BG32: 0 | BH32: 0 | BI32: 0 | BJ32: 0 | BL32: 0 | BO32: 0 | BT32: 0 | BU32: 5100000 | BV32: 0 | BW32: 100000 | BX32: 0 | BY32: 11000000 | BZ32: 0 | CA32: 0 | CB32: 400000 | CC32: 50000 | CD32: 75000 | CE32: 0 | CF32: 525000 | CG32: 11625000 | CH32: 0 | CI32: 0 | CK32: 0 | CL32: 0 | CM32: 0 | CN32: 0 | CP32: 0 | CQ32: 0 | CR32: 0 | CS32: 4575000 | CU32: 4575000 | CV32: 850000 | CW32: 0 | CX32: 150000 | CY32: 0 | DA32: 1000000 | DB32: 1525000 | DC32: 100000 | DD32: 6200000 | DF32: MoviNorthSupply Chain Management | DG32: 416666.67 | DH32: HPG | DI32: =IFERROR(VLOOKUP($B32,[1]Timesheet!$D:$BK,51,0),0) -> 22 | DJ32: =IFERROR(VLOOKUP($B32,[1]Timesheet!$D:$BK,52,0),0) -> 0 | DK32: =IFERROR(VLOOKUP($B32,[1]Timesheet!$D:$BK,55,0),0) -> 0 | DL32: 0 | DM32: =IFERROR(VLOOKUP($B32,[1]Timesheet!$D:$BK,57,0),0) -> 0 | DN32: =IF(AND(DL32="x",CB32>0),MIN(ROUND(W32*1%,0),149000),0) -> 0 | DP32: =IF(E32="Sales",IF(F32="Logistics",F32,IF(F32="Marketing",F32,DH32)),"") | DQ32: 0 | DR32: 0 | DS32: =IFERROR(VLOOKUP(E32&H32,[1]Group!$D$3:$G$40,4,0),"") -> Group 4 | DT32: =J32&I32&DS32 -> MoviNorthGroup 4
A33: 30 | B33: 4610 | C33: MV004610 | D33: Ngô Công Tuấn Phong | E33: Supply Chain Management | F33: Logistics | G33: Associate | H33: Delivery man | I33: South | J33: Movi | K33: Full-time | L33: Permanent | M33: 43236 | Q33: LC | R33: LTTP | S33: L | U33: 5000000 | W33: 5000000 | X33: 0 | Y33: 0 | AA33: 100000 | AC33: 0 | AD33: 100000 | AE33: CN | AF33: 26 | AG33: 26 | AH33: 0 | AI33: 0 | AJ33: 0 | AK33: 26 | AL33: 0 | AM33: 0 | AN33: 0 | AO33: 0 | AP33: 0 | AQ33: 0 | AR33: 5000000 | AS33: 0 | AT33: 0 | AU33: 5000000 | AV33: 0 | AW33: 0 | AX33: 0 | AY33: 100000 | AZ33: 0 | BA33: 0 | BE33: 0 | BF33: 100000 | BG33: 0 | BH33: 0 | BI33: 0 | BJ33: 0 | BL33: 0 | BO33: 0 | BT33: 0 | BU33: 5100000 | BV33: 0 | BW33: 100000 | BX33: 0 | BY33: 11000000 | BZ33: 0 | CA33: 0 | CB33: 400000 | CC33: 50000 | CD33: 75000 | CE33: 0 | CF33: 525000 | CG33: 11625000 | CH33: 0 | CI33: 0 | CK33: 0 | CL33: 0 | CM33: 0 | CN33: 0 | CP33: 0 | CQ33: 0 | CR33: 0 | CS33: 4575000 | CU33: 4575000 | CV33: 850000 | CW33: 0 | CX33: 150000 | CY33: 0 | DA33: 1000000 | DB33: 1525000 | DC33: 100000 | DD33: 6200000 | DF33: MoviSouthSupply Chain Management | DG33: 416666.67 | DH33: MKD | DI33: =IFERROR(VLOOKUP($B33,[1]Timesheet!$D:$BK,51,0),0) -> 22 | DJ33: =IFERROR(VLOOKUP($B33,[1]Timesheet!$D:$BK,52,0),0) -> 0 | DK33: =IFERROR(VLOOKUP($B33,[1]Timesheet!$D:$BK,55,0),0) -> 0 | DL33: 0 | DM33: =IFERROR(VLOOKUP($B33,[1]Timesheet!$D:$BK,57,0),0) -> 0 | DN33: =IF(AND(DL33="x",CB33>0),MIN(ROUND(W33*1%,0),149000),0) -> 0 | DP33: =IF(E33="Sales",IF(F33="Logistics",F33,IF(F33="Marketing",F33,DH33)),"") | DQ33: 0 | DR33: 0 | DS33: =IFERROR(VLOOKUP(E33&H33,[1]Group!$D$3:$G$40,4,0),"") -> Group 4 | DT33: =J33&I33&DS33 -> MoviSouthGroup 4
A34: 31 | B34: 5373 | C34: MV005373 | D34: Hồ Hữu Đại | E34: Supply Chain Management | F34: Logistics | G34: Associate | H34: Delivery Man | I34: North | J34: Movi | K34: Full-time | L34: Permanent | M34: 43732 | Q34: LC | R34: LTTP | S34: L | U34: 5000000 | W34: 5000000 | X34: 0 | Y34: 0 | AA34: 100000 | AC34: 0 | AD34: 100000 | AE34: CN | AF34: 26 | AG34: 26 | AH34: 0 | AI34: 0 | AJ34: 0 | AK34: 26 | AL34: 0 | AM34: 0 | AN34: 0 | AO34: 0 | AP34: 0 | AQ34: 0 | AR34: 5000000 | AS34: 0 | AT34: 0 | AU34: 5000000 | AV34: 0 | AW34: 0 | AX34: 0 | AY34: 100000 | AZ34: 0 | BA34: 0 | BE34: 0 | BF34: 100000 | BG34: 0 | BH34: 0 | BI34: 0 | BJ34: 0 | BL34: 0 | BO34: 0 | BT34: 0 | BU34: 5100000 | BV34: 0 | BW34: 100000 | BX34: 0 | BY34: 11000000 | BZ34: 0 | CA34: 0 | CB34: 400000 | CC34: 50000 | CD34: 75000 | CE34: 0 | CF34: 525000 | CG34: 11625000 | CH34: 0 | CI34: 0 | CK34: 0 | CL34: 0 | CM34: 0 | CN34: 0 | CP34: 0 | CQ34: 0 | CR34: 0 | CS34: 4575000 | CU34: 4575000 | CV34: 850000 | CW34: 0 | CX34: 150000 | CY34: 0 | DA34: 1000000 | DB34: 1525000 | DC34: 100000 | DD34: 6200000 | DF34: MoviNorthSupply Chain Management | DG34: 416666.67 | DH34: HPG | DI34: =IFERROR(VLOOKUP($B34,[1]Timesheet!$D:$BK,51,0),0) -> 22 | DJ34: =IFERROR(VLOOKUP($B34,[1]Timesheet!$D:$BK,52,0),0) -> 0 | DK34: =IFERROR(VLOOKUP($B34,[1]Timesheet!$D:$BK,55,0),0) -> 0 | DL34: 0 | DM34: =IFERROR(VLOOKUP($B34,[1]Timesheet!$D:$BK,57,0),0) -> 0 | DN34: =IF(AND(DL34="x",CB34>0),MIN(ROUND(W34*1%,0),149000),0) -> 0 | DP34: =IF(E34="Sales",IF(F34="Logistics",F34,IF(F34="Marketing",F34,DH34)),"") | DQ34: 0 | DR34: 0 | DS34: =IFERROR(VLOOKUP(E34&H34,[1]Group!$D$3:$G$40,4,0),"") -> Group 4 | DT34: =J34&I34&DS34 -> MoviNorthGroup 4
A35: 32 | B35: 6106 | C35: MV006106 | D35: Bùi Thị Minh Nguyệt | E35: Supply Chain Management | F35: Logistics | G35: Supervisor | H35: Logistics Supervisor | I35: South | J35: Movi | K35: Full-time | L35: Permanent | M35: 44295 | Q35: LC | R35: LTTP | S35: L | U35: 20000000 | W35: 20000000 | X35: 0 | Y35: 0 | AA35: 200000 | AC35: 0 | AD35: 200000 | AE35: CN | AF35: 26 | AG35: 26 | AH35: 0 | AI35: 0 | AJ35: 0 | AK35: 26 | AL35: 0 | AM35: 0 | AN35: 0 | AO35: 0 | AP35: 0 | AQ35: 0 | AR35: 20000000 | AS35: 0 | AT35: 0 | AU35: 20000000 | AV35: 0 | AW35: 0 | AX35: 0 | AY35: 200000 | AZ35: 0 | BA35: 0 | BE35: 0 | BF35: 200000 | BG35: 0 | BH35: 0 | BI35: 0 | BJ35: 0 | BL35: 0 | BO35: 0 | BT35: 0 | BU35: 20200000 | BV35: 0 | BW35: 200000 | BX35: 0 | BY35: 11000000 | BZ35: 1 | CA35: 4400000 | CB35: 1600000 | CC35: 200000 | CD35: 300000 | CE35: 0 | CF35: 2100000 | CG35: 17700000 | CH35: 2500000 | CI35: 125000 | CK35: 125000 | CL35: 0 | CM35: 149000 | CN35: 0 | CP35: 2982900 | CQ35: 0 | CR35: 3131900 | CS35: 14843100 | CU35: 14843100 | CV35: 3400000 | CW35: 0 | CX35: 600000 | CY35: 0 | DA35: 4000000 | DB35: 6100000 | DC35: 400000 | DD35: 24600000 | DF35: MoviSouthSupply Chain Management | DG35: 1666666.7 | DH35: HCM | DI35: =IFERROR(VLOOKUP($B35,[1]Timesheet!$D:$BK,51,0),0) -> 22 | DJ35: =IFERROR(VLOOKUP($B35,[1]Timesheet!$D:$BK,52,0),0) -> 0 | DK35: =IFERROR(VLOOKUP($B35,[1]Timesheet!$D:$BK,55,0),0) -> 0 | DL35: x | DM35: =IFERROR(VLOOKUP($B35,[1]Timesheet!$D:$BK,57,0),0) -> 0 | DN35: =IF(AND(DL35="x",CB35>0),MIN(ROUND(W35*1%,0),149000),0) -> 149000 | DP35: =IF(E35="Sales",IF(F35="Logistics",F35,IF(F35="Marketing",F35,DH35)),"") | DQ35: 0 | DR35: 0 | DS35: =IFERROR(VLOOKUP(E35&H35,[1]Group!$D$3:$G$40,4,0),"") -> Group 4 | DT35: =J35&I35&DS35 -> MoviSouthGroup 4
A36: 33 | B36: 1250 | C36: MV001250 | D36: Lê Xuân Hoàng Minh | E36: Supply Chain Management | F36: Merchandise | G36: Manager | H36: Manager, Merchandise | I36: South | J36: Movi | K36: Full-time | L36: Permanent | M36: 40735 | Q36: LC | R36: LTTP | S36: L | U36: 40000000 | W36: 40000000 | X36: 0 | Y36: 0 | AA36: 0 | AC36: 0 | AD36: 0 | AE36: TB, CN | AF36: 21 | AG36: 21 | AH36: 0 | AI36: 0 | AJ36: 0 | AK36: 21 | AL36: 0 | AM36: 0 | AN36: 0 | AO36: 0 | AP36: 0 | AQ36: 0 | AR36: 40000000 | AS36: 0 | AT36: 0 | AU36: 40000000 | AV36: 0 | AW36: 0 | AX36: 0 | AY36: 0 | AZ36: 0 | BA36: 0 | BE36: 0 | BF36: 0 | BG36: 0 | BH36: 0 | BI36: 0 | BJ36: 0 | BL36: 0 | BO36: 0 | BT36: 0 | BU36: 40000000 | BV36: 0 | BW36: 0 | BX36: 0 | BY36: 11000000 | BZ36: 3 | CA36: 13200000 | CB36: 2384000 | CC36: 400000 | CD36: 447000 | CE36: 0 | CF36: 3231000 | CG36: 27431000 | CH36: 12569000 | CI36: 1135350 | CK36: 1135350 | CL36: 0 | CM36: 149000 | CN36: 0 | CP36: 344000 | CQ36: 0 | CR36: 493000 | CS36: 35140650 | CU36: 35140650 | CV36: 5066000 | CW36: 0 | CX36: 894000 | CY36: 0 | DA36: 5960000 | DB36: 9191000 | DC36: 596000 | DD36: 46556000 | DF36: MoviSouthSupply Chain Management | DG36: 3333333.3 | DH36: HO | DI36: =IFERROR(VLOOKUP($B36,[1]Timesheet!$D:$BK,51,0),0) -> 18 | DJ36: =IFERROR(VLOOKUP($B36,[1]Timesheet!$D:$BK,52,0),0) -> 0 | DK36: =IFERROR(VLOOKUP($B36,[1]Timesheet!$D:$BK,55,0),0) -> 0 | DL36: x | DM36: =IFERROR(VLOOKUP($B36,[1]Timesheet!$D:$BK,57,0),0) -> 0 | DN36: =IF(AND(DL36="x",CB36>0),MIN(ROUND(W36*1%,0),149000),0) -> 149000 | DP36: =IF(E36="Sales",IF(F36="Logistics",F36,IF(F36="Marketing",F36,DH36)),"") | DQ36: 0 | DR36: 0 | DS36: =IFERROR(VLOOKUP(E36&H36,[1]Group!$D$3:$G$40,4,0),"") | DT36: =J36&I36&DS36 -> MoviSouth
A37: 34 | B37: CM0900 | C37: MVCM0900 | D37: Huỳnh Thị Mộng Tiên | E37: Supply Chain Management | F37: Merchandise | G37: Assistant Manager | H37: Merchandise Assistant Manager | I37: South | J37: Movi | K37: Full-time | L37: Permanent | M37: 42261 | Q37: LC | R37: LTTP | S37: L | U37: 30000000 | W37: 30000000 | X37: 0 | Y37: 0 | AA37: 0 | AC37: 0 | AD37: 0 | AE37: CN | AF37: 26 | AG37: 26 | AH37: 0 | AI37: 0 | AJ37: 0 | AK37: 26 | AL37: 0 | AM37: 0 | AN37: 0 | AO37: 0 | AP37: 0 | AQ37: 0 | AR37: 30000000 | AS37: 0 | AT37: 0 | AU37: 30000000 | AV37: 0 | AW37: 0 | AX37: 0 | AY37: 0 | AZ37: 0 | BA37: 0 | BE37: 0 | BF37: 0 | BG37: 0 | BH37: 0 | BI37: 0 | BJ37: 0 | BL37: 0 | BO37: 0 | BT37: 0 | BU37: 30000000 | BV37: 0 | BW37: 0 | BX37: 0 | BY37: 11000000 | BZ37: 0 | CA37: 0 | CB37: 2384000 | CC37: 300000 | CD37: 447000 | CE37: 0 | CF37: 3131000 | CG37: 14131000 | CH37: 15869000 | CI37: 1630350 | CK37: 1630350 | CL37: 0 | CM37: 149000 | CN37: 0 | CP37: 3340000 | CQ37: 0 | CR37: 3489000 | CS37: 21749650 | CU37: 21749650 | CV37: 5066000 | CW37: 0 | CX37: 894000 | CY37: 0 | DA37: 5960000 | DB37: 9091000 | DC37: 596000 | DD37: 36556000 | DF37: MoviSouthSupply Chain Management | DG37: 2500000 | DH37: HO | DI37: =IFERROR(VLOOKUP($B37,[1]Timesheet!$D:$BK,51,0),0) -> 22 | DJ37: =IFERROR(VLOOKUP($B37,[1]Timesheet!$D:$BK,52,0),0) -> 0 | DK37: =IFERROR(VLOOKUP($B37,[1]Timesheet!$D:$BK,55,0),0) -> 0 | DL37: x | DM37: =IFERROR(VLOOKUP($B37,[1]Timesheet!$D:$BK,57,0),0) -> 0 | DN37: =IF(AND(DL37="x",CB37>0),MIN(ROUND(W37*1%,0),149000),0) -> 149000 | DP37: =IF(E37="Sales",IF(F37="Logistics",F37,IF(F37="Marketing",F37,DH37)),"") | DQ37: 43552 | DR37: 43734 | DS37: =IFERROR(VLOOKUP(E37&H37,[1]Group!$D$3:$G$40,4,0),"") | DT37: =J37&I37&DS37 -> MoviSouth
A38: 35 | B38: 6121 | C38: MV006121 | D38: Phạm Thị Hường | E38: Supply Chain Management | F38: Merchandise | G38: Associate | H38: Merchandise Officer | I38: South | J38: Movi | K38: Full-time | L38: Permanent | M38: 44320 | Q38: LC | R38: LTTP | S38: L | U38: 5000000 | W38: 5000000 | X38: 0 | Y38: 0 | AA38: 0 | AC38: 0 | AD38: 0 | AE38: CN | AF38: 26 | AG38: 26 | AH38: 0 | AI38: 0 | AJ38: 0 | AK38: 26 | AL38: 0 | AM38: 0 | AN38: 0 | AO38: 0 | AP38: 0 | AQ38: 0 | AR38: 5000000 | AS38: 0 | AT38: 0 | AU38: 5000000 | AV38: 0 | AW38: 0 | AX38: 0 | AY38: 0 | AZ38: 0 | BA38: 0 | BE38: 0 | BF38: 0 | BG38: 0 | BH38: 0 | BI38: 0 | BJ38: 0 | BL38: 0 | BO38: 0 | BT38: 0 | BU38: 5000000 | BV38: 0 | BW38: 0 | BX38: 0 | BY38: 11000000 | BZ38: 0 | CA38: 0 | CB38: 400000 | CC38: 50000 | CD38: 75000 | CE38: 0 | CF38: 525000 | CG38: 11525000 | CH38: 0 | CI38: 0 | CK38: 0 | CL38: 0 | CM38: 50000 | CN38: 0 | CP38: 400900 | CQ38: 0 | CR38: 450900 | CS38: 4024100 | CU38: 4024100 | CV38: 850000 | CW38: 0 | CX38: 150000 | CY38: 0 | DA38: 1000000 | DB38: 1525000 | DC38: 100000 | DD38: 6100000 | DF38: MoviSouthSupply Chain Management | DG38: 416666.67 | DH38: HO | DI38: =IFERROR(VLOOKUP($B38,[1]Timesheet!$D:$BK,51,0),0) -> 22 | DJ38: =IFERROR(VLOOKUP($B38,[1]Timesheet!$D:$BK,52,0),0) -> 0 | DK38: =IFERROR(VLOOKUP($B38,[1]Timesheet!$D:$BK,55,0),0) -> 0 | DL38: x | DM38: =IFERROR(VLOOKUP($B38,[1]Timesheet!$D:$BK,57,0),0) -> 0 | DN38: =IF(AND(DL38="x",CB38>0),MIN(ROUND(W38*1%,0),149000),0) -> 50000 | DP38: =IF(E38="Sales",IF(F38="Logistics",F38,IF(F38="Marketing",F38,DH38)),"") | DQ38: 0 | DR38: 0 | DS38: =IFERROR(VLOOKUP(E38&H38,[1]Group!$D$3:$G$40,4,0),"") | DT38: =J38&I38&DS38 -> MoviSouth
A39: 36 | B39: 6136 | C39: MV006136 | D39: Châu Hải Thọ | E39: Supply Chain Management | F39: Merchandise | G39: Senior Associate | H39: Merchandise Officer | I39: South | J39: Movi | K39: Full-time | L39: Permanent | M39: 44320 | Q39: LC | R39: LTTP | S39: L | U39: 10000000 | W39: 10000000 | X39: 0 | Y39: 0 | AA39: 0 | AC39: 0 | AD39: 0 | AE39: CN | AF39: 26 | AG39: 26 | AH39: 0 | AI39: 0 | AJ39: 0 | AK39: 26 | AL39: 0 | AM39: 0 | AN39: 0 | AO39: 0 | AP39: 0 | AQ39: 0 | AR39: 10000000 | AS39: 0 | AT39: 0 | AU39: 10000000 | AV39: 0 | AW39: 0 | AX39: 0 | AY39: 0 | AZ39: 0 | BA39: 0 | BE39: 0 | BF39: 0 | BG39: 0 | BH39: 0 | BI39: 0 | BJ39: 0 | BL39: 0 | BO39: 0 | BT39: 0 | BU39: 10000000 | BV39: 0 | BW39: 0 | BX39: 0 | BY39: 11000000 | BZ39: 0 | CA39: 0 | CB39: 800000 | CC39: 100000 | CD39: 150000 | CE39: 0 | CF39: 1050000 | CG39: 12050000 | CH39: 0 | CI39: 0 | CK39: 0 | CL39: 0 | CM39: 100000 | CN39: 0 | CP39: 0 | CQ39: 0 | CR39: 100000 | CS39: 8850000 | CU39: 8850000 | CV39: 1700000 | CW39: 0 | CX39: 300000 | CY39: 0 | DA39: 2000000 | DB39: 3050000 | DC39: 200000 | DD39: 12200000 | DF39: MoviSouthSupply Chain Management | DG39: 833333.33 | DH39: HO | DI39: =IFERROR(VLOOKUP($B39,[1]Timesheet!$D:$BK,51,0),0) -> 22 | DJ39: =IFERROR(VLOOKUP($B39,[1]Timesheet!$D:$BK,52,0),0) -> 0 | DK39: =IFERROR(VLOOKUP($B39,[1]Timesheet!$D:$BK,55,0),0) -> 0 | DL39: x | DM39: =IFERROR(VLOOKUP($B39,[1]Timesheet!$D:$BK,57,0),0) -> 0 | DN39: =IF(AND(DL39="x",CB39>0),MIN(ROUND(W39*1%,0),149000),0) -> 100000 | DP39: =IF(E39="Sales",IF(F39="Logistics",F39,IF(F39="Marketing",F39,DH39)),"") | DQ39: 0 | DR39: 0 | DS39: =IFERROR(VLOOKUP(E39&H39,[1]Group!$D$3:$G$40,4,0),"") | DT39: =J39&I39&DS39 -> MoviSouth
A40: 37 | B40: 4229 | C40: VP004229 | D40: Trần Hoàng Minh Ngàn | E40: Human Resources | F40: Learning & Development | G40: HOD | H40: Head of HR | I40: South | J40: Việt Phú | K40: Full-time | L40: Permanent | M40: 43089 | Q40: LC | R40: LTTP | S40: L | U40: 80000000 | W40: 80000000 | X40: 0 | Y40: 0 | AA40: 0 | AC40: 0 | AD40: 0 | AE40: TB, CN | AF40: 21 | AG40: 20 | AH40: 1 | AI40: 0 | AJ40: 0 | AK40: 21 | AL40: 0 | AM40: 0 | AN40: 0 | AO40: 0 | AP40: 0 | AQ40: 0 | AR40: 80000000 | AS40: 0 | AT40: 0 | AU40: 80000000 | AV40: 0 | AW40: 0 | AX40: 0 | AY40: 0 | AZ40: 0 | BA40: 0 | BE40: 0 | BF40: 0 | BG40: 0 | BH40: 0 | BI40: 0 | BJ40: 0 | BL40: 0 | BO40: 0 | BT40: 0 | BU40: 80000000 | BV40: 0 | BW40: 0 | BX40: 0 | BY40: 11000000 | BZ40: 5 | CA40: 22000000 | CB40: 2384000 | CC40: 800000 | CD40: 447000 | CE40: 0 | CF40: 3631000 | CG40: 36631000 | CH40: 43369000 | CI40: 7592250 | CK40: 7592250 | CL40: 0 | CM40: 149000 | CN40: 0 | CP40: 0 | CQ40: 0 | CR40: 149000 | CS40: 68627750 | CU40: 68627750 | CV40: 5066000 | CW40: 0 | CX40: 894000 | CY40: 0 | DA40: 5960000 | DB40: 9591000 | DC40: 596000 | DD40: 86556000 | DF40: Việt PhúSouthHuman Resources | DG40: 6666666.7 | DH40: HO | DI40: =IFERROR(VLOOKUP($B40,[1]Timesheet!$D:$BK,51,0),0) -> 18 | DJ40: =IFERROR(VLOOKUP($B40,[1]Timesheet!$D:$BK,52,0),0) -> 0 | DK40: =IFERROR(VLOOKUP($B40,[1]Timesheet!$D:$BK,55,0),0) -> 0 | DL40: x | DM40: =IFERROR(VLOOKUP($B40,[1]Timesheet!$D:$BK,57,0),0) -> 0 | DN40: =IF(AND(DL40="x",CB40>0),MIN(ROUND(W40*1%,0),149000),0) -> 149000 | DP40: =IF(E40="Sales",IF(F40="Logistics",F40,IF(F40="Marketing",F40,DH40)),"") | DQ40: 0 | DR40: 0 | DS40: =IFERROR(VLOOKUP(E40&H40,[1]Group!$D$3:$G$40,4,0),"") | DT40: =J40&I40&DS40 -> Việt PhúSouth
A41: 38 | B41: 6163 | C41: VP006163 | D41: Huỳnh Thị Thanh Minh | E41: Human Resources | F41: Talent Acquisition | G41: Manager | H41: HRBP and TA Manager | I41: South | J41: Việt Phú | K41: Full-time | L41: Leaving | M41: 44348 | P41: 44541 | Q41: LC | R41: LTTP | S41: L | U41: 40000000 | W41: 40000000 | X41: 0 | Y41: 0 | AA41: 0 | AC41: 0 | AD41: 0 | AE41: TB, CN | AF41: 21 | AG41: 11 | AH41: 0 | AI41: 0 | AJ41: 0 | AK41: 11 | AL41: 0 | AM41: 0 | AN41: 0 | AO41: 0 | AP41: 0 | AQ41: 0 | AR41: 20952381 | AS41: -1071429 | AT41: 0 | AU41: 19880952 | AV41: 0 | AW41: 0 | AX41: 0 | AY41: 0 | AZ41: 0 | BA41: 0 | BE41: 0 | BF41: 0 | BG41: 0 | BH41: 0 | BI41: 0 | BJ41: 0 | BL41: 0 | BO41: 0 | BT41: 0 | BU41: 19880952 | BV41: 0 | BW41: 0 | BX41: 0 | BY41: 11000000 | BZ41: 0 | CA41: 0 | CB41: 0 | CC41: 0 | CD41: 0 | CE41: 0 | CF41: 0 | CG41: 11000000 | CH41: 8880952 | CI41: 638095.2 | CK41: 638095.2 | CL41: 0 | CM41: 0 | CN41: 0 | CP41: 0 | CQ41: 0 | CR41: 0 | CS41: 19242857 | CU41: 19242857 | CV41: 0 | CW41: 0 | CX41: 0 | CY41: 0 | DA41: 0 | DB41: 0 | DC41: 0 | DD41: 19880952 | DF41: Việt PhúSouthHuman Resources | DG41: 3333333.3 | DH41: HO | DI41: =IFERROR(VLOOKUP($B41,[1]Timesheet!$D:$BK,51,0),0) -> 8 | DJ41: =IFERROR(VLOOKUP($B41,[1]Timesheet!$D:$BK,52,0),0) -> 0 | DK41: =IFERROR(VLOOKUP($B41,[1]Timesheet!$D:$BK,55,0),0) -> 0 | DL41: 0 | DM41: =IFERROR(VLOOKUP($B41,[1]Timesheet!$D:$BK,57,0),0) -> 0 | DN41: =IF(AND(DL41="x",CB41>0),MIN(ROUND(W41*1%,0),149000),0) -> 0 | DP41: =IF(E41="Sales",IF(F41="Logistics",F41,IF(F41="Marketing",F41,DH41)),"") | DQ41: 0 | DR41: 0 | DS41: =IFERROR(VLOOKUP(E41&H41,[1]Group!$D$3:$G$40,4,0),"") | DT41: =J41&I41&DS41 -> Việt PhúSouth
A42: 39 | B42: 4753 | C42: VP004753 | D42: Lý Thị Bích Nga | E42: Human Resources | F42: Talent Acquisition | G42: Senior Associate | H42: Senior Talent Acquisition Partner | I42: South | J42: Việt Phú | K42: Full-time | L42: Permanent | M42: 43304 | Q42: LC | R42: LTTP | S42: L | U42: 10000000 | W42: 10000000 | X42: 0 | Y42: 0 | AA42: 0 | AC42: 0 | AD42: 0 | AE42: TB, CN | AF42: 21 | AG42: 18.5 | AH42: 2.5 | AI42: 0 | AJ42: 0 | AK42: 21 | AL42: 0 | AM42: 0 | AN42: 0 | AO42: 0 | AP42: 0 | AQ42: 0 | AR42: 10000000 | AS42: 0 | AT42: 0 | AU42: 10000000 | AV42: 0 | AW42: 0 | AX42: 0 | AY42: 0 | AZ42: 0 | BA42: 0 | BE42: 0 | BF42: 0 | BG42: 0 | BH42: 0 | BI42: 0 | BJ42: 0 | BL42: 0 | BO42: 0 | BT42: 0 | BU42: 10000000 | BV42: 0 | BW42: 0 | BX42: 0 | BY42: 11000000 | BZ42: 0 | CA42: 0 | CB42: 800000 | CC42: 100000 | CD42: 150000 | CE42: 0 | CF42: 1050000 | CG42: 12050000 | CH42: 0 | CI42: 0 | CK42: 0 | CL42: 0 | CM42: 0 | CN42: 0 | CP42: 0 | CQ42: 0 | CR42: 0 | CS42: 8950000 | CU42: 8950000 | CV42: 1700000 | CW42: 0 | CX42: 300000 | CY42: 0 | DA42: 2000000 | DB42: 3050000 | DC42: 200000 | DD42: 12200000 | DF42: Việt PhúSouthHuman Resources | DG42: 833333.33 | DH42: HO | DI42: =IFERROR(VLOOKUP($B42,[1]Timesheet!$D:$BK,51,0),0) -> 18 | DJ42: =IFERROR(VLOOKUP($B42,[1]Timesheet!$D:$BK,52,0),0) -> 0 | DK42: =IFERROR(VLOOKUP($B42,[1]Timesheet!$D:$BK,55,0),0) -> 0 | DL42: 0 | DM42: =IFERROR(VLOOKUP($B42,[1]Timesheet!$D:$BK,57,0),0) -> 0 | DN42: =IF(AND(DL42="x",CB42>0),MIN(ROUND(W42*1%,0),149000),0) -> 0 | DP42: =IF(E42="Sales",IF(F42="Logistics",F42,IF(F42="Marketing",F42,DH42)),"") | DQ42: 0 | DR42: 0 | DS42: =IFERROR(VLOOKUP(E42&H42,[1]Group!$D$3:$G$40,4,0),"") | DT42: =J42&I42&DS42 -> Việt PhúSouth
A43: 40 | B43: 6189 | C43: VP006189 | D43: Phạm Thị Thủy | E43: Human Resources | F43: Talent Acquisition | G43: Assistant Manager | H43: Assistant TA-HRBP Manager | I43: South | J43: Việt Phú | K43: Full-time | L43: Permanent | M43: 44445 | Q43: LC | R43: LTTP | S43: L | U43: 30000000 | W43: 30000000 | X43: 0 | Y43: 0 | AA43: 0 | AC43: 0 | AD43: 0 | AE43: TB, CN | AF43: 21 | AG43: 21 | AH43: 0 | AI43: 0 | AJ43: 0 | AK43: 21 | AL43: 0 | AM43: 0 | AN43: 0 | AO43: 0 | AP43: 0 | AQ43: 0 | AR43: 30000000 | AS43: -5238095 | AT43: 0 | AU43: 24761905 | AV43: 0 | AW43: 0 | AX43: 0 | AY43: 0 | AZ43: 0 | BA43: 0 | BE43: 0 | BF43: 0 | BG43: 0 | BH43: 0 | BI43: 0 | BJ43: 0 | BL43: 0 | BO43: 0 | BT43: 0 | BU43: 24761905 | BV43: 0 | BW43: 0 | BX43: 0 | BY43: 11000000 | BZ43: 2 | CA43: 8800000 | CB43: 2384000 | CC43: 300000 | CD43: 447000 | CE43: 0 | CF43: 3131000 | CG43: 22931000 | CH43: 1830905 | CI43: 91545.25 | CK43: 91545.25 | CL43: 0 | CM43: 0 | CN43: 0 | CP43: 0 | CQ43: 0 | CR43: 0 | CS43: 21539360 | CU43: 21539360 | CV43: 5066000 | CW43: 0 | CX43: 894000 | CY43: 0 | DA43: 5960000 | DB43: 9091000 | DC43: 596000 | DD43: 31317905 | DF43: Việt PhúSouthHuman Resources | DG43: 2500000 | DH43: HO | DI43: =IFERROR(VLOOKUP($B43,[1]Timesheet!$D:$BK,51,0),0) -> 18 | DJ43: =IFERROR(VLOOKUP($B43,[1]Timesheet!$D:$BK,52,0),0) -> 0 | DK43: =IFERROR(VLOOKUP($B43,[1]Timesheet!$D:$BK,55,0),0) -> 0 | DL43: 0 | DM43: =IFERROR(VLOOKUP($B43,[1]Timesheet!$D:$BK,57,0),0) -> 0 | DN43: =IF(AND(DL43="x",CB43>0),MIN(ROUND(W43*1%,0),149000),0) -> 0 | DP43: =IF(E43="Sales",IF(F43="Logistics",F43,IF(F43="Marketing",F43,DH43)),"") | DQ43: 0 | DR43: 0 | DS43: =IFERROR(VLOOKUP(E43&H43,[1]Group!$D$3:$G$40,4,0),"") | DT43: =J43&I43&DS43 -> Việt PhúSouth
A44: 41 | B44: 5675 | C44: VP005675 | D44: Nguyễn Thị Xoan | E44: Human Resources | F44: Compensation & Benefits - HR Ops | G44: Manager | H44: HRBP and C&B Manager | I44: South | J44: Việt Phú | K44: Full-time | L44: Permanent | M44: 43963 | Q44: LC | R44: LTTP | S44: L | U44: 40000000 | W44: 40000000 | X44: 0 | Y44: 0 | AA44: 0 | AC44: 0 | AD44: 0 | AE44: TB, CN | AF44: 21 | AG44: 21 | AH44: 0 | AI44: 0 | AJ44: 0 | AK44: 21 | AL44: 0 | AM44: 0 | AN44: 0 | AO44: 0 | AP44: 0 | AQ44: 0 | AR44: 40000000 | AS44: 0 | AT44: 0 | AU44: 40000000 | AV44: 0 | AW44: 0 | AX44: 0 | AY44: 0 | AZ44: 0 | BA44: 0 | BE44: 0 | BF44: 0 | BG44: 0 | BH44: 0 | BI44: 0 | BJ44: 0 | BL44: 0 | BO44: 0 | BT44: 0 | BU44: 40000000 | BV44: 0 | BW44: 0 | BX44: 0 | BY44: 11000000 | BZ44: 0 | CA44: 0 | CB44: 2384000 | CC44: 400000 | CD44: 447000 | CE44: 0 | CF44: 3231000 | CG44: 14231000 | CH44: 25769000 | CI44: 3503800 | CK44: 3503800 | CL44: 0 | CM44: 149000 | CN44: 0 | CP44: 0 | CQ44: 0 | CR44: 149000 | CS44: 33116200 | CU44: 33116200 | CV44: 5066000 | CW44: 0 | CX44: 894000 | CY44: 0 | DA44: 5960000 | DB44: 9191000 | DC44: 596000 | DD44: 46556000 | DF44: Việt PhúSouthHuman Resources | DG44: 3333333.3 | DH44: HO | DI44: =IFERROR(VLOOKUP($B44,[1]Timesheet!$D:$BK,51,0),0) -> 18 | DJ44: =IFERROR(VLOOKUP($B44,[1]Timesheet!$D:$BK,52,0),0) -> 0 | DK44: =IFERROR(VLOOKUP($B44,[1]Timesheet!$D:$BK,55,0),0) -> 0 | DL44: x | DM44: =IFERROR(VLOOKUP($B44,[1]Timesheet!$D:$BK,57,0),0) -> 0 | DN44: =IF(AND(DL44="x",CB44>0),MIN(ROUND(W44*1%,0),149000),0) -> 149000 | DP44: =IF(E44="Sales",IF(F44="Logistics",F44,IF(F44="Marketing",F44,DH44)),"") | DQ44: 0 | DR44: 0 | DS44: =IFERROR(VLOOKUP(E44&H44,[1]Group!$D$3:$G$40,4,0),"") | DT44: =J44&I44&DS44 -> Việt PhúSouth
A45: 42 | B45: 5851 | C45: VP005851 | D45: Nguyễn Thị Thảo | E45: Human Resources | F45: Compensation & Benefits - HR Ops | G45: Senior Associate | H45: Senior HR Executive | I45: South | J45: Việt Phú | K45: Full-time | L45: Permanent | M45: 44060 | Q45: LC | R45: LTTP | S45: L | U45: 10000000 | W45: 10000000 | X45: 0 | Y45: 0 | AA45: 0 | AC45: 0 | AD45: 0 | AE45: TB, CN | AF45: 21 | AG45: 21 | AH45: 0 | AI45: 0 | AJ45: 0 | AK45: 21 | AL45: 0 | AM45: 0 | AN45: 0 | AO45: 0 | AP45: 0 | AQ45: 0 | AR45: 10000000 | AS45: 0 | AT45: 0 | AU45: 10000000 | AV45: 0 | AW45: 0 | AX45: 0 | AY45: 0 | AZ45: 0 | BA45: 0 | BE45: 0 | BF45: 0 | BG45: 0 | BH45: 0 | BI45: 0 | BJ45: 0 | BL45: 0 | BO45: 0 | BT45: 0 | BU45: 10000000 | BV45: 0 | BW45: 0 | BX45: 0 | BY45: 11000000 | BZ45: 0 | CA45: 0 | CB45: 800000 | CC45: 100000 | CD45: 150000 | CE45: 0 | CF45: 1050000 | CG45: 12050000 | CH45: 0 | CI45: 0 | CK45: 0 | CL45: 0 | CM45: 0 | CN45: 0 | CP45: 0 | CQ45: 0 | CR45: 0 | CS45: 8950000 | CU45: 8950000 | CV45: 1700000 | CW45: 0 | CX45: 300000 | CY45: 0 | DA45: 2000000 | DB45: 3050000 | DC45: 200000 | DD45: 12200000 | DF45: Việt PhúSouthHuman Resources | DG45: 833333.33 | DH45: HO | DI45: =IFERROR(VLOOKUP($B45,[1]Timesheet!$D:$BK,51,0),0) -> 18 | DJ45: =IFERROR(VLOOKUP($B45,[1]Timesheet!$D:$BK,52,0),0) -> 0 | DK45: =IFERROR(VLOOKUP($B45,[1]Timesheet!$D:$BK,55,0),0) -> 0 | DL45: 0 | DM45: =IFERROR(VLOOKUP($B45,[1]Timesheet!$D:$BK,57,0),0) -> 0 | DN45: =IF(AND(DL45="x",CB45>0),MIN(ROUND(W45*1%,0),149000),0) -> 0 | DP45: =IF(E45="Sales",IF(F45="Logistics",F45,IF(F45="Marketing",F45,DH45)),"") | DQ45: 0 | DR45: 0 | DS45: =IFERROR(VLOOKUP(E45&H45,[1]Group!$D$3:$G$40,4,0),"") | DT45: =J45&I45&DS45 -> Việt PhúSouth
A46: 43 | B46: 5698 | C46: VP005698 | D46: Hồ Thị Yến | E46: Human Resources | F46: Compensation & Benefits - HR Ops | G46: Associate | H46: HR Executive | I46: South | J46: Việt Phú | K46: Full-time | L46: Permanent | M46: 43983 | Q46: LC | R46: LTTP | S46: L | U46: 5000000 | W46: 5000000 | X46: 0 | Y46: 0 | AA46: 0 | AC46: 0 | AD46: 0 | AE46: TB, CN | AF46: 21 | AG46: 21 | AH46: 0 | AI46: 0 | AJ46: 0 | AK46: 21 | AL46: 0 | AM46: 0 | AN46: 0 | AO46: 0 | AP46: 0 | AQ46: 0 | AR46: 5000000 | AS46: 0 | AT46: 0 | AU46: 5000000 | AV46: 0 | AW46: 0 | AX46: 0 | AY46: 0 | AZ46: 0 | BA46: 0 | BE46: 0 | BF46: 0 | BG46: 0 | BH46: 0 | BI46: 0 | BJ46: 0 | BL46: 0 | BO46: 0 | BT46: 0 | BU46: 5000000 | BV46: 0 | BW46: 0 | BX46: 0 | BY46: 11000000 | BZ46: 0 | CA46: 0 | CB46: 400000 | CC46: 50000 | CD46: 75000 | CE46: 0 | CF46: 525000 | CG46: 11525000 | CH46: 0 | CI46: 0 | CK46: 0 | CL46: 0 | CM46: 0 | CN46: 0 | CP46: 0 | CQ46: 0 | CR46: 0 | CS46: 4475000 | CU46: 4475000 | CV46: 850000 | CW46: 0 | CX46: 150000 | CY46: 0 | DA46: 1000000 | DB46: 1525000 | DC46: 100000 | DD46: 6100000 | DF46: Việt PhúSouthHuman Resources | DG46: 416666.67 | DH46: HO | DI46: =IFERROR(VLOOKUP($B46,[1]Timesheet!$D:$BK,51,0),0) -> 18 | DJ46: =IFERROR(VLOOKUP($B46,[1]Timesheet!$D:$BK,52,0),0) -> 0 | DK46: =IFERROR(VLOOKUP($B46,[1]Timesheet!$D:$BK,55,0),0) -> 0 | DL46: 0 | DM46: =IFERROR(VLOOKUP($B46,[1]Timesheet!$D:$BK,57,0),0) -> 0 | DN46: =IF(AND(DL46="x",CB46>0),MIN(ROUND(W46*1%,0),149000),0) -> 0 | DP46: =IF(E46="Sales",IF(F46="Logistics",F46,IF(F46="Marketing",F46,DH46)),"") | DQ46: 0 | DR46: 0 | DS46: =IFERROR(VLOOKUP(E46&H46,[1]Group!$D$3:$G$40,4,0),"") | DT46: =J46&I46&DS46 -> Việt PhúSouth
A47: 44 | B47: 6142 | C47: VP006142 | D47: Võ Ngọc Thanh Phương | E47: Human Resources | F47: Learning & Development | G47: Manager | H47: Training and Development Manager | I47: South | J47: Việt Phú | K47: Full-time | L47: Permanent | M47: 44333 | Q47: LC | R47: LTTP | S47: L | U47: 40000000 | W47: 40000000 | X47: 0 | Y47: 0 | AA47: 0 | AC47: 0 | AD47: 0 | AE47: TB, CN | AF47: 21 | AG47: 21 | AH47: 0 | AI47: 0 | AJ47: 0 | AK47: 21 | AL47: 0 | AM47: 0 | AN47: 0 | AO47: 0 | AP47: 0 | AQ47: 0 | AR47: 40000000 | AS47: 0 | AT47: 0 | AU47: 40000000 | AV47: 0 | AW47: 0 | AX47: 0 | AY47: 0 | AZ47: 0 | BA47: 0 | BE47: 0 | BF47: 0 | BG47: 0 | BH47: 0 | BI47: 0 | BJ47: 0 | BL47: 0 | BO47: 0 | BT47: 0 | BU47: 40000000 | BV47: 0 | BW47: 0 | BX47: 0 | BY47: 11000000 | BZ47: 0 | CA47: 0 | CB47: 2384000 | CC47: 400000 | CD47: 447000 | CE47: 0 | CF47: 3231000 | CG47: 14231000 | CH47: 25769000 | CI47: 3503800 | CK47: 3503800 | CL47: 0 | CM47: 149000 | CN47: 0 | CP47: 0 | CQ47: 0 | CR47: 149000 | CS47: 33116200 | CU47: 33116200 | CV47: 5066000 | CW47: 0 | CX47: 894000 | CY47: 0 | DA47: 5960000 | DB47: 9191000 | DC47: 596000 | DD47: 46556000 | DF47: Việt PhúSouthHuman Resources | DG47: 3333333.3 | DH47: HO | DI47: =IFERROR(VLOOKUP($B47,[1]Timesheet!$D:$BK,51,0),0) -> 18 | DJ47: =IFERROR(VLOOKUP($B47,[1]Timesheet!$D:$BK,52,0),0) -> 0 | DK47: =IFERROR(VLOOKUP($B47,[1]Timesheet!$D:$BK,55,0),0) -> 0 | DL47: x | DM47: =IFERROR(VLOOKUP($B47,[1]Timesheet!$D:$BK,57,0),0) -> 0 | DN47: =IF(AND(DL47="x",CB47>0),MIN(ROUND(W47*1%,0),149000),0) -> 149000 | DP47: =IF(E47="Sales",IF(F47="Logistics",F47,IF(F47="Marketing",F47,DH47)),"") | DQ47: 0 | DR47: 0 | DS47: =IFERROR(VLOOKUP(E47&H47,[1]Group!$D$3:$G$40,4,0),"") | DT47: =J47&I47&DS47 -> Việt PhúSouth
A48: 45 | B48: 6254 | C48: VP006254 | D48: Lê Thị Hồng Hoa | E48: Human Resources | F48: Compensation & Benefits - HR Ops | G48: Associate | H48: C&B Admin | I48: South | J48: Việt Phú | K48: Full-time | L48: Leaving | M48: 44515 | P48: 44555 | Q48: JO | R48: 0.1 | S48: L | U48: 5000000 | W48: 5000000 | X48: 0 | Y48: 0 | AA48: 0 | AC48: 0 | AD48: 0 | AE48: TB, CN | AF48: 21 | AG48: 21 | AH48: 0 | AI48: 0 | AJ48: 0 | AK48: 21 | AL48: 0 | AM48: 0 | AN48: 0 | AO48: 0 | AP48: 0 | AQ48: 0 | AR48: 5000000 | AS48: 0 | AT48: 0 | AU48: 5000000 | AV48: 0 | AW48: 0 | AX48: 0 | AY48: 0 | AZ48: 0 | BA48: 0 | BE48: 0 | BF48: 0 | BG48: 0 | BH48: 0 | BI48: 0 | BJ48: 0 | BL48: 0 | BO48: 0 | BT48: 0 | BU48: 5000000 | BV48: 0 | BW48: 0 | BX48: 0 | BY48: 0 | BZ48: 0 | CA48: 0 | CB48: 0 | CC48: 0 | CD48: 0 | CE48: 0 | CF48: 0 | CG48: 0 | CH48: 5000000 | CI48: 500000 | CK48: 500000 | CL48: 0 | CM48: 0 | CN48: 0 | CP48: 0 | CQ48: 0 | CR48: 0 | CS48: 4500000 | CU48: 4500000 | CV48: 0 | CW48: 0 | CX48: 0 | CY48: 0 | DA48: 0 | DB48: 0 | DC48: 0 | DD48: 5000000 | DF48: Việt PhúSouthHuman Resources | DG48: 416666.67 | DH48: HO | DI48: =IFERROR(VLOOKUP($B48,[1]Timesheet!$D:$BK,51,0),0) -> 18 | DJ48: =IFERROR(VLOOKUP($B48,[1]Timesheet!$D:$BK,52,0),0) -> 0 | DK48: =IFERROR(VLOOKUP($B48,[1]Timesheet!$D:$BK,55,0),0) -> 0 | DL48: 0 | DM48: =IFERROR(VLOOKUP($B48,[1]Timesheet!$D:$BK,57,0),0) -> 0 | DN48: =IF(AND(DL48="x",CB48>0),MIN(ROUND(W48*1%,0),149000),0) -> 0 | DP48: =IF(E48="Sales",IF(F48="Logistics",F48,IF(F48="Marketing",F48,DH48)),"") | DQ48: 0 | DR48: 0 | DS48: =IFERROR(VLOOKUP(E48&H48,[1]Group!$D$3:$G$40,4,0),"") | DT48: =J48&I48&DS48 -> Việt PhúSouth
A49: 46 | B49: 6255 | C49: VP006255 | D49: Huỳnh Như Bảo Ngọc | E49: Human Resources | F49: Talent Acquisition | G49: Associate | H49: Talent Acquisition Partner | I49: South | J49: Việt Phú | K49: Full-time | L49: Probation | M49: 44522 | Q49: JO | R49: 0.1 | S49: L | U49: 5000000 | W49: 5000000 | X49: 0 | Y49: 0 | AA49: 0 | AC49: 0 | AD49: 0 | AE49: TB, CN | AF49: 21 | AG49: 20 | AH49: 0 | AI49: 0 | AJ49: 0 | AK49: 20 | AL49: 0 | AM49: 0 | AN49: 0 | AO49: 0 | AP49: 0 | AQ49: 0 | AR49: 4761905 | AS49: 0 | AT49: 0 | AU49: 4761905 | AV49: 0 | AW49: 0 | AX49: 0 | AY49: 0 | AZ49: 0 | BA49: 0 | BE49: 0 | BF49: 0 | BG49: 0 | BH49: 0 | BI49: 0 | BJ49: 0 | BL49: 0 | BO49: 0 | BT49: 0 | BU49: 4761905 | BV49: 0 | BW49: 0 | BX49: 0 | BY49: 0 | BZ49: 0 | CA49: 0 | CB49: 0 | CC49: 0 | CD49: 0 | CE49: 0 | CF49: 0 | CG49: 0 | CH49: 4761905 | CI49: 476190.5 | CK49: 476190.5 | CL49: 0 | CM49: 0 | CN49: 0 | CP49: 0 | CQ49: 0 | CR49: 0 | CS49: 4285715 | CU49: 4285715 | CV49: 0 | CW49: 0 | CX49: 0 | CY49: 0 | DA49: 0 | DB49: 0 | DC49: 0 | DD49: 4761905 | DF49: Việt PhúSouthHuman Resources | DG49: 416666.67 | DH49: HO | DI49: =IFERROR(VLOOKUP($B49,[1]Timesheet!$D:$BK,51,0),0) -> 17 | DJ49: =IFERROR(VLOOKUP($B49,[1]Timesheet!$D:$BK,52,0),0) -> 0 | DK49: =IFERROR(VLOOKUP($B49,[1]Timesheet!$D:$BK,55,0),0) -> 1 | DL49: 0 | DM49: =IFERROR(VLOOKUP($B49,[1]Timesheet!$D:$BK,57,0),0) -> 0 | DN49: =IF(AND(DL49="x",CB49>0),MIN(ROUND(W49*1%,0),149000),0) -> 0 | DP49: =IF(E49="Sales",IF(F49="Logistics",F49,IF(F49="Marketing",F49,DH49)),"") | DQ49: 0 | DR49: 0 | DS49: =IFERROR(VLOOKUP(E49&H49,[1]Group!$D$3:$G$40,4,0),"") | DT49: =J49&I49&DS49 -> Việt PhúSouth
A50: 47 | B50: 6237 | C50: VP006237 | D50: Lê Anh Vững | E50: Human Resources | F50: Talent Acquisition | G50: Associate | H50: Talent Acquisition Intern | I50: South | J50: Việt Phú | K50: Contractor | L50: Contractor | M50: 44508 | Q50: SC | R50: 0.1 | S50: L | U50: 5000000 | W50: 5000000 | X50: 0 | Y50: 0 | AA50: 0 | AC50: 0 | AD50: 0 | AE50: TB, CN | AF50: 21 | AG50: 21 | AH50: 0 | AI50: 0 | AJ50: 0 | AK50: 21 | AL50: 0 | AM50: 0 | AN50: 0 | AO50: 0 | AP50: 0 | AQ50: 0 | AR50: 5000000 | AS50: 0 | AT50: 0 | AU50: 5000000 | AV50: 0 | AW50: 0 | AX50: 0 | AY50: 0 | AZ50: 0 | BA50: 0 | BE50: 0 | BF50: 0 | BG50: 0 | BH50: 0 | BI50: 0 | BJ50: 0 | BL50: 0 | BO50: 0 | BT50: 0 | BU50: 5000000 | BV50: 0 | BW50: 0 | BX50: 0 | BY50: 0 | BZ50: 0 | CA50: 0 | CB50: 0 | CC50: 0 | CD50: 0 | CE50: 0 | CF50: 0 | CG50: 0 | CH50: 5000000 | CI50: 500000 | CK50: 500000 | CL50: 0 | CM50: 0 | CN50: 0 | CP50: 0 | CQ50: 0 | CR50: 0 | CS50: 4500000 | CU50: 4500000 | CV50: 0 | CW50: 0 | CX50: 0 | CY50: 0 | DA50: 0 | DB50: 0 | DC50: 0 | DD50: 5000000 | DF50: Việt PhúSouthHuman Resources | DG50: 416666.67 | DH50: HO | DI50: =IFERROR(VLOOKUP($B50,[1]Timesheet!$D:$BK,51,0),0) -> 18 | DJ50: =IFERROR(VLOOKUP($B50,[1]Timesheet!$D:$BK,52,0),0) -> 0 | DK50: =IFERROR(VLOOKUP($B50,[1]Timesheet!$D:$BK,55,0),0) -> 0 | DL50: 0 | DM50: =IFERROR(VLOOKUP($B50,[1]Timesheet!$D:$BK,57,0),0) -> 0 | DN50: =IF(AND(DL50="x",CB50>0),MIN(ROUND(W50*1%,0),149000),0) -> 0 | DP50: =IF(E50="Sales",IF(F50="Logistics",F50,IF(F50="Marketing",F50,DH50)),"") | DQ50: 0 | DR50: 0 | DS50: =IFERROR(VLOOKUP(E50&H50,[1]Group!$D$3:$G$40,4,0),"") | DT50: =J50&I50&DS50 -> Việt PhúSouth
A51: 48 | B51: 6017 | C51: VP006017 | D51: Nguyễn Vũ Ninh | E51: IT | F51: Dev App | G51: Team leader | H51: Cloud and Automation Team Leader | I51: South | J51: Việt Phú | K51: Full-time | L51: Permanent | M51: 44113 | Q51: LC | R51: LTTP | S51: L | U51: 15000000 | W51: 15000000 | X51: 0 | Y51: 0 | AA51: 0 | AC51: 0 | AD51: 0 | AE51: TB, CN | AF51: 21 | AG51: 17 | AH51: 4 | AI51: 0 | AJ51: 0 | AK51: 21 | AL51: 0 | AM51: 0 | AN51: 0 | AO51: 0 | AP51: 0 | AQ51: 0 | AR51: 15000000 | AS51: 0 | AT51: 0 | AU51: 15000000 | AV51: 0 | AW51: 0 | AX51: 0 | AY51: 0 | AZ51: 0 | BA51: 0 | BE51: 0 | BF51: 0 | BG51: 0 | BH51: 0 | BI51: 0 | BJ51: 0 | BL51: 0 | BO51: 0 | BT51: 0 | BU51: 15000000 | BV51: 0 | BW51: 0 | BX51: 0 | BY51: 11000000 | BZ51: 0 | CA51: 0 | CB51: 0 | CC51: 0 | CD51: 0 | CE51: 0 | CF51: 0 | CG51: 11000000 | CH51: 4000000 | CI51: 200000 | CK51: 200000 | CL51: 0 | CM51: 0 | CN51: 0 | CP51: 0 | CQ51: 0 | CR51: 0 | CS51: 14800000 | CU51: 14800000 | CV51: 0 | CW51: 0 | CX51: 0 | CY51: 0 | DA51: 0 | DB51: 0 | DC51: 300000 | DD51: 15300000 | DF51: Việt PhúSouthIT | DG51: 1250000 | DH51: HO | DI51: =IFERROR(VLOOKUP($B51,[1]Timesheet!$D:$BK,51,0),0) -> 18 | DJ51: =IFERROR(VLOOKUP($B51,[1]Timesheet!$D:$BK,52,0),0) -> 0 | DK51: =IFERROR(VLOOKUP($B51,[1]Timesheet!$D:$BK,55,0),0) -> 0 | DL51: 0 | DM51: =IFERROR(VLOOKUP($B51,[1]Timesheet!$D:$BK,57,0),0) -> 0 | DN51: =IF(AND(DL51="x",CB51>0),MIN(ROUND(W51*1%,0),149000),0) -> 0 | DP51: =IF(E51="Sales",IF(F51="Logistics",F51,IF(F51="Marketing",F51,DH51)),"") | DQ51: 0 | DR51: 0 | DS51: =IFERROR(VLOOKUP(E51&H51,[1]Group!$D$3:$G$40,4,0),"") | DT51: =J51&I51&DS51 -> Việt PhúSouth
A52: 49 | B52: 5156 | C52: VP005156 | D52: Nguyễn Lợi | E52: IT | F52: IT Infrastructure & Network | G52: Senior Associate | H52: IT Support/Helpdesk | I52: South | J52: Việt Phú | K52: Full-time | L52: Permanent | M52: 43668 | Q52: LC | R52: LTTP | S52: L | U52: 10000000 | W52: 10000000 | X52: 0 | Y52: 0 | AA52: 0 | AC52: 0 | AD52: 0 | AE52: CN | AF52: 26 | AG52: 26 | AH52: 0 | AI52: 0 | AJ52: 0 | AK52: 26 | AL52: 0 | AM52: 0 | AN52: 0 | AO52: 0 | AP52: 0 | AQ52: 0 | AR52: 10000000 | AS52: 0 | AT52: 0 | AU52: 10000000 | AV52: 0 | AW52: 0 | AX52: 0 | AY52: 0 | AZ52: 0 | BA52: 0 | BE52: 0 | BF52: 0 | BG52: 0 | BH52: 0 | BI52: 0 | BJ52: 0 | BL52: 0 | BO52: 0 | BT52: 0 | BU52: 10000000 | BV52: 0 | BW52: 0 | BX52: 0 | BY52: 11000000 | BZ52: 0 | CA52: 0 | CB52: 800000 | CC52: 100000 | CD52: 150000 | CE52: 0 | CF52: 1050000 | CG52: 12050000 | CH52: 0 | CI52: 0 | CK52: 0 | CL52: 0 | CM52: 0 | CN52: 0 | CP52: 0 | CQ52: 0 | CR52: 0 | CS52: 8950000 | CU52: 8950000 | CV52: 1700000 | CW52: 0 | CX52: 300000 | CY52: 0 | DA52: 2000000 | DB52: 3050000 | DC52: 200000 | DD52: 12200000 | DF52: Việt PhúSouthIT | DG52: 833333.33 | DH52: HO | DI52: =IFERROR(VLOOKUP($B52,[1]Timesheet!$D:$BK,51,0),0) -> 22 | DJ52: =IFERROR(VLOOKUP($B52,[1]Timesheet!$D:$BK,52,0),0) -> 0 | DK52: =IFERROR(VLOOKUP($B52,[1]Timesheet!$D:$BK,55,0),0) -> 0 | DL52: 0 | DM52: =IFERROR(VLOOKUP($B52,[1]Timesheet!$D:$BK,57,0),0) -> 0 | DN52: =IF(AND(DL52="x",CB52>0),MIN(ROUND(W52*1%,0),149000),0) -> 0 | DP52: =IF(E52="Sales",IF(F52="Logistics",F52,IF(F52="Marketing",F52,DH52)),"") | DQ52: 0 | DR52: 0 | DS52: =IFERROR(VLOOKUP(E52&H52,[1]Group!$D$3:$G$40,4,0),"") | DT52: =J52&I52&DS52 -> Việt PhúSouth
A53: 50 | B53: 5045 | C53: VP005045 | D53: Nguyễn Vũ Đăng Khoa | E53: IT | F53: IT Infrastructure & Network | G53: Associate | H53: IT Support/Helpdesk | I53: South | J53: Việt Phú | K53: Full-time | L53: Permanent | M53: 43605 | Q53: LC | R53: LTTP | S53: L | U53: 5000000 | W53: 5000000 | X53: 0 | Y53: 0 | AA53: 0 | AC53: 0 | AD53: 0 | AE53: CN | AF53: 26 | AG53: 24 | AH53: 2 | AI53: 0 | AJ53: 0 | AK53: 26 | AL53: 0 | AM53: 0 | AN53: 0 | AO53: 0 | AP53: 0 | AQ53: 0 | AR53: 5000000 | AS53: 0 | AT53: 0 | AU53: 5000000 | AV53: 0 | AW53: 0 | AX53: 0 | AY53: 0 | AZ53: 0 | BA53: 0 | BE53: 0 | BF53: 0 | BG53: 0 | BH53: 0 | BI53: 0 | BJ53: 0 | BL53: 0 | BO53: 0 | BT53: 0 | BU53: 5000000 | BV53: 0 | BW53: 0 | BX53: 0 | BY53: 11000000 | BZ53: 0 | CA53: 0 | CB53: 400000 | CC53: 50000 | CD53: 75000 | CE53: 0 | CF53: 525000 | CG53: 11525000 | CH53: 0 | CI53: 0 | CK53: 0 | CL53: 0 | CM53: 0 | CN53: 0 | CP53: 0 | CQ53: 0 | CR53: 0 | CS53: 4475000 | CU53: 4475000 | CV53: 850000 | CW53: 0 | CX53: 150000 | CY53: 0 | DA53: 1000000 | DB53: 1525000 | DC53: 100000 | DD53: 6100000 | DF53: Việt PhúSouthIT | DG53: 416666.67 | DH53: HO | DI53: =IFERROR(VLOOKUP($B53,[1]Timesheet!$D:$BK,51,0),0) -> 22 | DJ53: =IFERROR(VLOOKUP($B53,[1]Timesheet!$D:$BK,52,0),0) -> 0 | DK53: =IFERROR(VLOOKUP($B53,[1]Timesheet!$D:$BK,55,0),0) -> 0 | DL53: 0 | DM53: =IFERROR(VLOOKUP($B53,[1]Timesheet!$D:$BK,57,0),0) -> 0 | DN53: =IF(AND(DL53="x",CB53>0),MIN(ROUND(W53*1%,0),149000),0) -> 0 | DP53: =IF(E53="Sales",IF(F53="Logistics",F53,IF(F53="Marketing",F53,DH53)),"") | DQ53: 0 | DR53: 0 | DS53: =IFERROR(VLOOKUP(E53&H53,[1]Group!$D$3:$G$40,4,0),"") | DT53: =J53&I53&DS53 -> Việt PhúSouth
A54: 51 | B54: 2849 | C54: VP002849 | D54: Đỗ Thị Mai | E54: Support | F54: PMO/ Business Transformation | G54: Associate | H54: Junior Business Analyst | I54: South | J54: Việt Phú | K54: Full-time | L54: Permanent | M54: 42418 | Q54: LC | R54: LTTP | S54: L | U54: 5000000 | W54: 5000000 | X54: 0 | Y54: 0 | AA54: 0 | AC54: 0 | AD54: 0 | AE54: TB, CN | AF54: 21 | AG54: 16 | AH54: 5 | AI54: 0 | AJ54: 0 | AK54: 21 | AL54: 0 | AM54: 0 | AN54: 0 | AO54: 0 | AP54: 0 | AQ54: 0 | AR54: 5000000 | AS54: 0 | AT54: 0 | AU54: 5000000 | AV54: 0 | AW54: 0 | AX54: 0 | AY54: 0 | AZ54: 0 | BA54: 0 | BE54: 0 | BF54: 0 | BG54: 0 | BH54: 0 | BI54: 0 | BJ54: 0 | BL54: 0 | BO54: 0 | BT54: 0 | BU54: 5000000 | BV54: 0 | BW54: 0 | BX54: 0 | BY54: 11000000 | BZ54: 0 | CA54: 0 | CB54: 400000 | CC54: 50000 | CD54: 75000 | CE54: 0 | CF54: 525000 | CG54: 11525000 | CH54: 0 | CI54: 0 | CK54: 0 | CL54: 0 | CM54: 50000 | CN54: 0 | CP54: 0 | CQ54: 0 | CR54: 50000 | CS54: 4425000 | CU54: 4425000 | CV54: 850000 | CW54: 0 | CX54: 150000 | CY54: 0 | DA54: 1000000 | DB54: 1525000 | DC54: 100000 | DD54: 6100000 | DF54: Việt PhúSouthSupport | DG54: 416666.67 | DH54: HO | DI54: =IFERROR(VLOOKUP($B54,[1]Timesheet!$D:$BK,51,0),0) -> 18 | DJ54: =IFERROR(VLOOKUP($B54,[1]Timesheet!$D:$BK,52,0),0) -> 0 | DK54: =IFERROR(VLOOKUP($B54,[1]Timesheet!$D:$BK,55,0),0) -> 0 | DL54: x | DM54: =IFERROR(VLOOKUP($B54,[1]Timesheet!$D:$BK,57,0),0) -> 0 | DN54: =IF(AND(DL54="x",CB54>0),MIN(ROUND(W54*1%,0),149000),0) -> 50000 | DP54: =IF(E54="Sales",IF(F54="Logistics",F54,IF(F54="Marketing",F54,DH54)),"") | DQ54: 0 | DR54: 0 | DS54: =IFERROR(VLOOKUP(E54&H54,[1]Group!$D$3:$G$40,4,0),"") | DT54: =J54&I54&DS54 -> Việt PhúSouth
A55: 52 | B55: 5476 | C55: VP005476 | D55: Nguyễn Thị Thảo Trinh | E55: IT | F55: IT Application Support & Business Analysis | G55: Associate | H55: Application Support Executive | I55: South | J55: Việt Phú | K55: Full-time | L55: Permanent | M55: 43766 | Q55: LC | R55: LTTP | S55: L | U55: 5000000 | W55: 5000000 | X55: 0 | Y55: 0 | AA55: 0 | AC55: 0 | AD55: 0 | AE55: TB, CN | AF55: 21 | AG55: 18 | AH55: 3 | AI55: 0 | AJ55: 0 | AK55: 21 | AL55: 0 | AM55: 0 | AN55: 0 | AO55: 0 | AP55: 0 | AQ55: 0 | AR55: 5000000 | AS55: 0 | AT55: 0 | AU55: 5000000 | AV55: 0 | AW55: 0 | AX55: 0 | AY55: 0 | AZ55: 0 | BA55: 0 | BE55: 0 | BF55: 0 | BG55: 0 | BH55: 0 | BI55: 0 | BJ55: 0 | BL55: 0 | BO55: 0 | BT55: 0 | BU55: 5000000 | BV55: 0 | BW55: 0 | BX55: 0 | BY55: 11000000 | BZ55: 0 | CA55: 0 | CB55: 400000 | CC55: 50000 | CD55: 75000 | CE55: 0 | CF55: 525000 | CG55: 11525000 | CH55: 0 | CI55: 0 | CK55: 0 | CL55: 0 | CM55: 0 | CN55: 0 | CP55: 0 | CQ55: 0 | CR55: 0 | CS55: 4475000 | CU55: 4475000 | CV55: 850000 | CW55: 0 | CX55: 150000 | CY55: 0 | DA55: 1000000 | DB55: 1525000 | DC55: 100000 | DD55: 6100000 | DF55: Việt PhúSouthIT | DG55: 416666.67 | DH55: HO | DI55: =IFERROR(VLOOKUP($B55,[1]Timesheet!$D:$BK,51,0),0) -> 18 | DJ55: =IFERROR(VLOOKUP($B55,[1]Timesheet!$D:$BK,52,0),0) -> 0 | DK55: =IFERROR(VLOOKUP($B55,[1]Timesheet!$D:$BK,55,0),0) -> 0 | DL55: 0 | DM55: =IFERROR(VLOOKUP($B55,[1]Timesheet!$D:$BK,57,0),0) -> 0 | DN55: =IF(AND(DL55="x",CB55>0),MIN(ROUND(W55*1%,0),149000),0) -> 0 | DP55: =IF(E55="Sales",IF(F55="Logistics",F55,IF(F55="Marketing",F55,DH55)),"") | DQ55: 0 | DR55: 0 | DS55: =IFERROR(VLOOKUP(E55&H55,[1]Group!$D$3:$G$40,4,0),"") | DT55: =J55&I55&DS55 -> Việt PhúSouth
A56: 53 | B56: 5019 | C56: VP005019 | D56: Nguyễn Hoàng Long | E56: IT | F56: IT Application Support & Engineer | G56: HOD | H56: Head of IT & PMO | I56: South | J56: Việt Phú | K56: Full-time | L56: Permanent | M56: 43586 | Q56: LC | R56: LTTP | S56: L | U56: 80000000 | W56: 80000000 | X56: 0 | Y56: 0 | AA56: 0 | AC56: 0 | AD56: 0 | AE56: TB, CN | AF56: 21 | AG56: 10 | AH56: 11 | AI56: 0 | AJ56: 0 | AK56: 21 | AL56: 0 | AM56: 0 | AN56: 0 | AO56: 0 | AP56: 0 | AQ56: 0 | AR56: 80000000 | AS56: 0 | AT56: 0 | AU56: 80000000 | AV56: 0 | AW56: 0 | AX56: 0 | AY56: 0 | AZ56: 0 | BA56: 0 | BE56: 0 | BF56: 0 | BG56: 0 | BH56: 0 | BI56: 0 | BJ56: 0 | BL56: 0 | BO56: 0 | BT56: 0 | BU56: 80000000 | BV56: 0 | BW56: 0 | BX56: 0 | BY56: 11000000 | BZ56: 2 | CA56: 8800000 | CB56: 2384000 | CC56: 800000 | CD56: 447000 | CE56: 0 | CF56: 3631000 | CG56: 23431000 | CH56: 56569000 | CI56: 11120700 | CK56: 11120700 | CL56: 0 | CM56: 0 | CN56: 0 | CP56: 0 | CQ56: 0 | CR56: 0 | CS56: 65248300 | CU56: 65248300 | CV56: 5066000 | CW56: 0 | CX56: 894000 | CY56: 0 | DA56: 5960000 | DB56: 9591000 | DC56: 596000 | DD56: 86556000 | DF56: Việt PhúSouthIT | DG56: 6666666.7 | DH56: HO | DI56: =IFERROR(VLOOKUP($B56,[1]Timesheet!$D:$BK,51,0),0) -> 18 | DJ56: =IFERROR(VLOOKUP($B56,[1]Timesheet!$D:$BK,52,0),0) -> 0 | DK56: =IFERROR(VLOOKUP($B56,[1]Timesheet!$D:$BK,55,0),0) -> 0 | DL56: 0 | DM56: =IFERROR(VLOOKUP($B56,[1]Timesheet!$D:$BK,57,0),0) -> 0 | DN56: =IF(AND(DL56="x",CB56>0),MIN(ROUND(W56*1%,0),149000),0) -> 0 | DP56: =IF(E56="Sales",IF(F56="Logistics",F56,IF(F56="Marketing",F56,DH56)),"") | DQ56: 0 | DR56: 0 | DS56: =IFERROR(VLOOKUP(E56&H56,[1]Group!$D$3:$G$40,4,0),"") | DT56: =J56&I56&DS56 -> Việt PhúSouth
A57: 54 | B57: 5108 | C57: VP005108 | D57: Trịnh Đức Tân | E57: IT | F57: IT Engineer | G57: Senior Associate | H57: PHP Developer | I57: South | J57: Việt Phú | K57: Full-time | L57: Permanent | M57: 43642 | Q57: LC | R57: LTTP | S57: L | U57: 10000000 | W57: 10000000 | X57: 0 | Y57: 0 | AA57: 0 | AC57: 0 | AD57: 0 | AE57: TB, CN | AF57: 21 | AG57: 16 | AH57: 5 | AI57: 0 | AJ57: 0 | AK57: 21 | AL57: 0 | AM57: 0 | AN57: 0 | AO57: 0 | AP57: 0 | AQ57: 0 | AR57: 10000000 | AS57: 0 | AT57: 0 | AU57: 10000000 | AV57: 0 | AW57: 0 | AX57: 0 | AY57: 0 | AZ57: 0 | BA57: 0 | BE57: 0 | BF57: 0 | BG57: 0 | BH57: 0 | BI57: 0 | BJ57: 0 | BL57: 0 | BO57: 0 | BT57: 0 | BU57: 10000000 | BV57: 0 | BW57: 0 | BX57: 0 | BY57: 11000000 | BZ57: 0 | CA57: 0 | CB57: 800000 | CC57: 100000 | CD57: 150000 | CE57: 0 | CF57: 1050000 | CG57: 12050000 | CH57: 0 | CI57: 0 | CK57: 0 | CL57: 0 | CM57: 0 | CN57: 0 | CP57: 0 | CQ57: 0 | CR57: 0 | CS57: 8950000 | CU57: 8950000 | CV57: 1700000 | CW57: 0 | CX57: 300000 | CY57: 0 | DA57: 2000000 | DB57: 3050000 | DC57: 200000 | DD57: 12200000 | DF57: Việt PhúSouthIT | DG57: 833333.33 | DH57: HO | DI57: =IFERROR(VLOOKUP($B57,[1]Timesheet!$D:$BK,51,0),0) -> 18 | DJ57: =IFERROR(VLOOKUP($B57,[1]Timesheet!$D:$BK,52,0),0) -> 0 | DK57: =IFERROR(VLOOKUP($B57,[1]Timesheet!$D:$BK,55,0),0) -> 0 | DL57: 0 | DM57: =IFERROR(VLOOKUP($B57,[1]Timesheet!$D:$BK,57,0),0) -> 0 | DN57: =IF(AND(DL57="x",CB57>0),MIN(ROUND(W57*1%,0),149000),0) -> 0 | DP57: =IF(E57="Sales",IF(F57="Logistics",F57,IF(F57="Marketing",F57,DH57)),"") | DQ57: 0 | DR57: 0 | DS57: =IFERROR(VLOOKUP(E57&H57,[1]Group!$D$3:$G$40,4,0),"") | DT57: =J57&I57&DS57 -> Việt PhúSouth
A58: 55 | B58: 5163 | C58: VP005163 | D58: Tạ Hữu Bang | E58: IT | F58: IT Engineer | G58: Senior Associate | H58: PHP Developer | I58: South | J58: Việt Phú | K58: Full-time | L58: Permanent | M58: 43678 | Q58: LC | R58: LTTP | S58: L | U58: 10000000 | W58: 10000000 | X58: 0 | Y58: 0 | AA58: 0 | AC58: 0 | AD58: 0 | AE58: TB, CN | AF58: 21 | AG58: 15 | AH58: 6 | AI58: 0 | AJ58: 0 | AK58: 21 | AL58: 0 | AM58: 0 | AN58: 0 | AO58: 0 | AP58: 0 | AQ58: 0 | AR58: 10000000 | AS58: 0 | AT58: 0 | AU58: 10000000 | AV58: 0 | AW58: 0 | AX58: 0 | AY58: 0 | AZ58: 0 | BA58: 0 | BE58: 0 | BF58: 0 | BG58: 0 | BH58: 0 | BI58: 0 | BJ58: 0 | BL58: 0 | BO58: 0 | BT58: 0 | BU58: 10000000 | BV58: 0 | BW58: 0 | BX58: 0 | BY58: 11000000 | BZ58: 1 | CA58: 4400000 | CB58: 800000 | CC58: 100000 | CD58: 150000 | CE58: 0 | CF58: 1050000 | CG58: 16450000 | CH58: 0 | CI58: 0 | CK58: 0 | CL58: 0 | CM58: 0 | CN58: 0 | CP58: 0 | CQ58: 0 | CR58: 0 | CS58: 8950000 | CU58: 8950000 | CV58: 1700000 | CW58: 0 | CX58: 300000 | CY58: 0 | DA58: 2000000 | DB58: 3050000 | DC58: 200000 | DD58: 12200000 | DF58: Việt PhúSouthIT | DG58: 833333.33 | DH58: HO | DI58: =IFERROR(VLOOKUP($B58,[1]Timesheet!$D:$BK,51,0),0) -> 18 | DJ58: =IFERROR(VLOOKUP($B58,[1]Timesheet!$D:$BK,52,0),0) -> 0 | DK58: =IFERROR(VLOOKUP($B58,[1]Timesheet!$D:$BK,55,0),0) -> 0 | DL58: 0 | DM58: =IFERROR(VLOOKUP($B58,[1]Timesheet!$D:$BK,57,0),0) -> 0 | DN58: =IF(AND(DL58="x",CB58>0),MIN(ROUND(W58*1%,0),149000),0) -> 0 | DP58: =IF(E58="Sales",IF(F58="Logistics",F58,IF(F58="Marketing",F58,DH58)),"") | DQ58: 0 | DR58: 0 | DS58: =IFERROR(VLOOKUP(E58&H58,[1]Group!$D$3:$G$40,4,0),"") | DT58: =J58&I58&DS58 -> Việt PhúSouth
A59: 56 | B59: 5816 | C59: VP005816 | D59: Võ Tấn Hùng | E59: IT | F59: IT Engineer | G59: Senior Associate | H59: Senior Developer | I59: South | J59: Việt Phú | K59: Full-time | L59: Permanent | M59: 44046 | Q59: LC | R59: LTTP | S59: L | U59: 10000000 | W59: 10000000 | X59: 0 | Y59: 0 | AA59: 0 | AC59: 0 | AD59: 0 | AE59: TB, CN | AF59: 21 | AG59: 15.5 | AH59: 5.5 | AI59: 0 | AJ59: 0 | AK59: 21 | AL59: 0 | AM59: 0 | AN59: 0 | AO59: 0 | AP59: 0 | AQ59: 0 | AR59: 10000000 | AS59: 0 | AT59: 0 | AU59: 10000000 | AV59: 0 | AW59: 0 | AX59: 0 | AY59: 0 | AZ59: 0 | BA59: 0 | BE59: 0 | BF59: 0 | BG59: 0 | BH59: 0 | BI59: 0 | BJ59: 0 | BL59: 0 | BO59: 0 | BT59: 0 | BU59: 10000000 | BV59: 0 | BW59: 0 | BX59: 0 | BY59: 11000000 | BZ59: 4 | CA59: 17600000 | CB59: 800000 | CC59: 100000 | CD59: 150000 | CE59: 0 | CF59: 1050000 | CG59: 29650000 | CH59: 0 | CI59: 0 | CK59: 0 | CL59: 0 | CM59: 100000 | CN59: 0 | CP59: 0 | CQ59: 0 | CR59: 100000 | CS59: 8850000 | CU59: 8850000 | CV59: 1700000 | CW59: 0 | CX59: 300000 | CY59: 0 | DA59: 2000000 | DB59: 3050000 | DC59: 200000 | DD59: 12200000 | DF59: Việt PhúSouthIT | DG59: 833333.33 | DH59: HO | DI59: =IFERROR(VLOOKUP($B59,[1]Timesheet!$D:$BK,51,0),0) -> 18 | DJ59: =IFERROR(VLOOKUP($B59,[1]Timesheet!$D:$BK,52,0),0) -> 0 | DK59: =IFERROR(VLOOKUP($B59,[1]Timesheet!$D:$BK,55,0),0) -> 0 | DL59: x | DM59: =IFERROR(VLOOKUP($B59,[1]Timesheet!$D:$BK,57,0),0) -> 0 | DN59: =IF(AND(DL59="x",CB59>0),MIN(ROUND(W59*1%,0),149000),0) -> 100000 | DP59: =IF(E59="Sales",IF(F59="Logistics",F59,IF(F59="Marketing",F59,DH59)),"") | DQ59: 0 | DR59: 0 | DS59: =IFERROR(VLOOKUP(E59&H59,[1]Group!$D$3:$G$40,4,0),"") | DT59: =J59&I59&DS59 -> Việt PhúSouth
A60: 57 | B60: 5218 | C60: VP005218 | D60: Lê Ánh Thiên | E60: IT | F60: IT Engineer | G60: Associate | H60: Java Developer | I60: South | J60: Việt Phú | K60: Full-time | L60: Permanent | M60: 43711 | Q60: LC | R60: LTTP | S60: L | U60: 5000000 | W60: 5000000 | X60: 0 | Y60: 0 | AA60: 0 | AC60: 0 | AD60: 0 | AE60: TB, CN | AF60: 21 | AG60: 16 | AH60: 5 | AI60: 0 | AJ60: 0 | AK60: 21 | AL60: 0 | AM60: 0 | AN60: 0 | AO60: 0 | AP60: 0 | AQ60: 0 | AR60: 5000000 | AS60: 0 | AT60: 0 | AU60: 5000000 | AV60: 0 | AW60: 0 | AX60: 0 | AY60: 0 | AZ60: 0 | BA60: 0 | BE60: 0 | BF60: 0 | BG60: 0 | BH60: 0 | BI60: 0 | BJ60: 0 | BL60: 0 | BO60: 0 | BT60: 0 | BU60: 5000000 | BV60: 0 | BW60: 0 | BX60: 0 | BY60: 11000000 | BZ60: 0 | CA60: 0 | CB60: 400000 | CC60: 50000 | CD60: 75000 | CE60: 0 | CF60: 525000 | CG60: 11525000 | CH60: 0 | CI60: 0 | CK60: 0 | CL60: 0 | CM60: 0 | CN60: 0 | CP60: 0 | CQ60: 0 | CR60: 0 | CS60: 4475000 | CU60: 4475000 | CV60: 850000 | CW60: 0 | CX60: 150000 | CY60: 0 | DA60: 1000000 | DB60: 1525000 | DC60: 100000 | DD60: 6100000 | DF60: Việt PhúSouthIT | DG60: 416666.67 | DH60: HO | DI60: =IFERROR(VLOOKUP($B60,[1]Timesheet!$D:$BK,51,0),0) -> 18 | DJ60: =IFERROR(VLOOKUP($B60,[1]Timesheet!$D:$BK,52,0),0) -> 0 | DK60: =IFERROR(VLOOKUP($B60,[1]Timesheet!$D:$BK,55,0),0) -> 0 | DL60: 0 | DM60: =IFERROR(VLOOKUP($B60,[1]Timesheet!$D:$BK,57,0),0) -> 0 | DN60: =IF(AND(DL60="x",CB60>0),MIN(ROUND(W60*1%,0),149000),0) -> 0 | DP60: =IF(E60="Sales",IF(F60="Logistics",F60,IF(F60="Marketing",F60,DH60)),"") | DQ60: 0 | DR60: 0 | DS60: =IFERROR(VLOOKUP(E60&H60,[1]Group!$D$3:$G$40,4,0),"") | DT60: =J60&I60&DS60 -> Việt PhúSouth
A61: 58 | B61: 5653 | C61: VP005653 | D61: Nguyễn Trần Tòng | E61: IT | F61: IT Engineer | G61: Manager | H61: IT Engineer Manager | I61: South | J61: Việt Phú | K61: Full-time | L61: Permanent | M61: 43878 | Q61: LC | R61: LTTP | S61: L | U61: 40000000 | W61: 40000000 | X61: 0 | Y61: 0 | AA61: 0 | AC61: 0 | AD61: 0 | AE61: TB, CN | AF61: 21 | AG61: 19.5 | AH61: 1.5 | AI61: 0 | AJ61: 0 | AK61: 21 | AL61: 0 | AM61: 0 | AN61: 0 | AO61: 0 | AP61: 0 | AQ61: 0 | AR61: 40000000 | AS61: 0 | AT61: 0 | AU61: 40000000 | AV61: 0 | AW61: 0 | AX61: 0 | AY61: 0 | AZ61: 0 | BA61: 0 | BE61: 0 | BF61: 0 | BG61: 0 | BH61: 0 | BI61: 0 | BJ61: 0 | BL61: 0 | BO61: 0 | BT61: 0 | BU61: 40000000 | BV61: 0 | BW61: 0 | BX61: 0 | BY61: 11000000 | BZ61: 4 | CA61: 17600000 | CB61: 2384000 | CC61: 400000 | CD61: 447000 | CE61: 0 | CF61: 3231000 | CG61: 31831000 | CH61: 8169000 | CI61: 566900 | CK61: 566900 | CL61: 0 | CM61: 0 | CN61: 0 | CP61: 0 | CQ61: 0 | CR61: 0 | CS61: 36202100 | CU61: 36202100 | CV61: 5066000 | CW61: 0 | CX61: 894000 | CY61: 0 | DA61: 5960000 | DB61: 9191000 | DC61: 596000 | DD61: 46556000 | DF61: Việt PhúSouthIT | DG61: 3333333.3 | DH61: HO | DI61: =IFERROR(VLOOKUP($B61,[1]Timesheet!$D:$BK,51,0),0) -> 18 | DJ61: =IFERROR(VLOOKUP($B61,[1]Timesheet!$D:$BK,52,0),0) -> 0 | DK61: =IFERROR(VLOOKUP($B61,[1]Timesheet!$D:$BK,55,0),0) -> 0 | DL61: 0 | DM61: =IFERROR(VLOOKUP($B61,[1]Timesheet!$D:$BK,57,0),0) -> 0 | DN61: =IF(AND(DL61="x",CB61>0),MIN(ROUND(W61*1%,0),149000),0) -> 0 | DP61: =IF(E61="Sales",IF(F61="Logistics",F61,IF(F61="Marketing",F61,DH61)),"") | DQ61: 0 | DR61: 0 | DS61: =IFERROR(VLOOKUP(E61&H61,[1]Group!$D$3:$G$40,4,0),"") | DT61: =J61&I61&DS61 -> Việt PhúSouth
A62: 59 | B62: 6110 | C62: VP006110 | D62: Trần Văn Thắng | E62: IT | F62: IT Infrastructure & Network | G62: Team leader | H62: System and Infrastructure Team Leader | I62: South | J62: Việt Phú | K62: Full-time | L62: Permanent | M62: 44300 | Q62: LC | R62: LTTP | S62: L | U62: 15000000 | W62: 15000000 | X62: 0 | Y62: 0 | AA62: 0 | AC62: 0 | AD62: 0 | AE62: TB, CN | AF62: 21 | AG62: 21 | AH62: 0 | AI62: 0 | AJ62: 0 | AK62: 21 | AL62: 0 | AM62: 0 | AN62: 0 | AO62: 0 | AP62: 0 | AQ62: 0 | AR62: 15000000 | AS62: 0 | AT62: 0 | AU62: 15000000 | AV62: 0 | AW62: 0 | AX62: 0 | AY62: 0 | AZ62: 0 | BA62: 0 | BE62: 0 | BF62: 0 | BG62: 0 | BH62: 0 | BI62: 0 | BJ62: 0 | BL62: 0 | BO62: 0 | BT62: 0 | BU62: 15000000 | BV62: 0 | BW62: 0 | BX62: 0 | BY62: 11000000 | BZ62: 1 | CA62: 4400000 | CB62: 1200000 | CC62: 150000 | CD62: 225000 | CE62: 0 | CF62: 1575000 | CG62: 16975000 | CH62: 0 | CI62: 0 | CK62: 0 | CL62: 0 | CM62: 0 | CN62: 0 | CP62: 0 | CQ62: 0 | CR62: 0 | CS62: 13425000 | CU62: 13425000 | CV62: 2550000 | CW62: 0 | CX62: 450000 | CY62: 0 | DA62: 3000000 | DB62: 4575000 | DC62: 300000 | DD62: 18300000 | DF62: Việt PhúSouthIT | DG62: 1250000 | DH62: HO | DI62: =IFERROR(VLOOKUP($B62,[1]Timesheet!$D:$BK,51,0),0) -> 18 | DJ62: =IFERROR(VLOOKUP($B62,[1]Timesheet!$D:$BK,52,0),0) -> 0 | DK62: =IFERROR(VLOOKUP($B62,[1]Timesheet!$D:$BK,55,0),0) -> 0 | DL62: 0 | DM62: =IFERROR(VLOOKUP($B62,[1]Timesheet!$D:$BK,57,0),0) -> 0 | DN62: =IF(AND(DL62="x",CB62>0),MIN(ROUND(W62*1%,0),149000),0) -> 0 | DP62: =IF(E62="Sales",IF(F62="Logistics",F62,IF(F62="Marketing",F62,DH62)),"") | DQ62: 0 | DR62: 0 | DS62: =IFERROR(VLOOKUP(E62&H62,[1]Group!$D$3:$G$40,4,0),"") | DT62: =J62&I62&DS62 -> Việt PhúSouth
A63: 60 | B63: 6122 | C63: VP006122 | D63: Nghiêm Văn Sang | E63: IT | F63: IT Engineer | G63: Senior Associate | H63: Senior Software Engineer | I63: South | J63: Việt Phú | K63: Full-time | L63: Permanent | M63: 44320 | Q63: LC | R63: LTTP | S63: L | U63: 10000000 | W63: 10000000 | X63: 0 | Y63: 0 | AA63: 0 | AC63: 0 | AD63: 0 | AE63: TB, CN | AF63: 21 | AG63: 21 | AH63: 0 | AI63: 0 | AJ63: 0 | AK63: 21 | AL63: 0 | AM63: 0 | AN63: 0 | AO63: 0 | AP63: 0 | AQ63: 0 | AR63: 10000000 | AS63: 0 | AT63: 0 | AU63: 10000000 | AV63: 0 | AW63: 0 | AX63: 0 | AY63: 0 | AZ63: 0 | BA63: 0 | BE63: 0 | BF63: 0 | BG63: 0 | BH63: 0 | BI63: 0 | BJ63: 0 | BL63: 0 | BO63: 0 | BT63: 0 | BU63: 10000000 | BV63: 0 | BW63: 0 | BX63: 0 | BY63: 11000000 | BZ63: 2 | CA63: 8800000 | CB63: 800000 | CC63: 100000 | CD63: 150000 | CE63: 0 | CF63: 1050000 | CG63: 20850000 | CH63: 0 | CI63: 0 | CK63: 0 | CL63: 0 | CM63: 0 | CN63: 0 | CP63: 0 | CQ63: 0 | CR63: 0 | CS63: 8950000 | CU63: 8950000 | CV63: 1700000 | CW63: 0 | CX63: 300000 | CY63: 0 | DA63: 2000000 | DB63: 3050000 | DC63: 200000 | DD63: 12200000 | DF63: Việt PhúSouthIT | DG63: 833333.33 | DH63: HO | DI63: =IFERROR(VLOOKUP($B63,[1]Timesheet!$D:$BK,51,0),0) -> 18 | DJ63: =IFERROR(VLOOKUP($B63,[1]Timesheet!$D:$BK,52,0),0) -> 0 | DK63: =IFERROR(VLOOKUP($B63,[1]Timesheet!$D:$BK,55,0),0) -> 0 | DL63: 0 | DM63: =IFERROR(VLOOKUP($B63,[1]Timesheet!$D:$BK,57,0),0) -> 0 | DN63: =IF(AND(DL63="x",CB63>0),MIN(ROUND(W63*1%,0),149000),0) -> 0 | DP63: =IF(E63="Sales",IF(F63="Logistics",F63,IF(F63="Marketing",F63,DH63)),"") | DQ63: 0 | DR63: 0 | DS63: =IFERROR(VLOOKUP(E63&H63,[1]Group!$D$3:$G$40,4,0),"") | DT63: =J63&I63&DS63 -> Việt PhúSouth
A64: 61 | B64: 6156 | C64: VP006156 | D64: Trần Anh Quốc | E64: IT | F64: IT Engineer | G64: Associate | H64: IOS Developer | I64: South | J64: Việt Phú | K64: Full-time | L64: Permanent | M64: 44354 | Q64: LC | R64: LTTP | S64: L | U64: 5000000 | W64: 5000000 | X64: 0 | Y64: 0 | AA64: 0 | AC64: 0 | AD64: 0 | AE64: TB, CN | AF64: 21 | AG64: 18 | AH64: 3 | AI64: 0 | AJ64: 0 | AK64: 21 | AL64: 0 | AM64: 0 | AN64: 0 | AO64: 0 | AP64: 0 | AQ64: 0 | AR64: 5000000 | AS64: 0 | AT64: 0 | AU64: 5000000 | AV64: 0 | AW64: 0 | AX64: 0 | AY64: 0 | AZ64: 0 | BA64: 0 | BE64: 0 | BF64: 0 | BG64: 0 | BH64: 0 | BI64: 0 | BJ64: 0 | BL64: 0 | BO64: 0 | BT64: 0 | BU64: 5000000 | BV64: 0 | BW64: 0 | BX64: 0 | BY64: 11000000 | BZ64: 1 | CA64: 4400000 | CB64: 400000 | CC64: 50000 | CD64: 75000 | CE64: 0 | CF64: 525000 | CG64: 15925000 | CH64: 0 | CI64: 0 | CK64: 0 | CL64: 0 | CM64: 0 | CN64: 0 | CP64: 0 | CQ64: 0 | CR64: 0 | CS64: 4475000 | CU64: 4475000 | CV64: 850000 | CW64: 0 | CX64: 150000 | CY64: 0 | DA64: 1000000 | DB64: 1525000 | DC64: 100000 | DD64: 6100000 | DF64: Việt PhúSouthIT | DG64: 416666.67 | DH64: HO | DI64: =IFERROR(VLOOKUP($B64,[1]Timesheet!$D:$BK,51,0),0) -> 18 | DJ64: =IFERROR(VLOOKUP($B64,[1]Timesheet!$D:$BK,52,0),0) -> 0 | DK64: =IFERROR(VLOOKUP($B64,[1]Timesheet!$D:$BK,55,0),0) -> 0 | DL64: 0 | DM64: =IFERROR(VLOOKUP($B64,[1]Timesheet!$D:$BK,57,0),0) -> 0 | DN64: =IF(AND(DL64="x",CB64>0),MIN(ROUND(W64*1%,0),149000),0) -> 0 | DP64: =IF(E64="Sales",IF(F64="Logistics",F64,IF(F64="Marketing",F64,DH64)),"") | DQ64: 0 | DR64: 0 | DS64: =IFERROR(VLOOKUP(E64&H64,[1]Group!$D$3:$G$40,4,0),"") | DT64: =J64&I64&DS64 -> Việt PhúSouth
A65: 62 | B65: 6171 | C65: VP006171 | D65: Bùi Thanh Tiến | E65: IT | F65: IT Engineer | G65: Senior Associate | H65: Senior Software Engineer | I65: South | J65: Việt Phú | K65: Full-time | L65: Permanent | M65: 44362 | Q65: LC | R65: LTTP | S65: L | U65: 10000000 | W65: 10000000 | X65: 0 | Y65: 0 | AA65: 0 | AC65: 0 | AD65: 0 | AE65: TB, CN | AF65: 21 | AG65: 20 | AH65: 1 | AI65: 0 | AJ65: 0 | AK65: 21 | AL65: 0 | AM65: 0 | AN65: 0 | AO65: 0 | AP65: 0 | AQ65: 0 | AR65: 10000000 | AS65: 0 | AT65: 0 | AU65: 10000000 | AV65: 0 | AW65: 0 | AX65: 0 | AY65: 0 | AZ65: 0 | BA65: 0 | BE65: 0 | BF65: 0 | BG65: 0 | BH65: 0 | BI65: 0 | BJ65: 0 | BL65: 0 | BO65: 0 | BT65: 0 | BU65: 10000000 | BV65: 0 | BW65: 0 | BX65: 0 | BY65: 11000000 | BZ65: 3 | CA65: 13200000 | CB65: 800000 | CC65: 100000 | CD65: 150000 | CE65: 0 | CF65: 1050000 | CG65: 25250000 | CH65: 0 | CI65: 0 | CK65: 0 | CL65: 0 | CM65: 0 | CN65: 0 | CP65: 0 | CQ65: 0 | CR65: 0 | CS65: 8950000 | CU65: 8950000 | CV65: 1700000 | CW65: 0 | CX65: 300000 | CY65: 0 | DA65: 2000000 | DB65: 3050000 | DC65: 200000 | DD65: 12200000 | DF65: Việt PhúSouthIT | DG65: 833333.33 | DH65: HO | DI65: =IFERROR(VLOOKUP($B65,[1]Timesheet!$D:$BK,51,0),0) -> 18 | DJ65: =IFERROR(VLOOKUP($B65,[1]Timesheet!$D:$BK,52,0),0) -> 0 | DK65: =IFERROR(VLOOKUP($B65,[1]Timesheet!$D:$BK,55,0),0) -> 0 | DL65: 0 | DM65: =IFERROR(VLOOKUP($B65,[1]Timesheet!$D:$BK,57,0),0) -> 0 | DN65: =IF(AND(DL65="x",CB65>0),MIN(ROUND(W65*1%,0),149000),0) -> 0 | DP65: =IF(E65="Sales",IF(F65="Logistics",F65,IF(F65="Marketing",F65,DH65)),"") | DQ65: 0 | DR65: 0 | DS65: =IFERROR(VLOOKUP(E65&H65,[1]Group!$D$3:$G$40,4,0),"") | DT65: =J65&I65&DS65 -> Việt PhúSouth
A66: 63 | B66: 6169 | C66: VP006169 | D66: Phạm Huy Hoàng | E66: IT | F66: IT Information Security | G66: Team leader | H66: Information Security Team Leader | I66: South | J66: Việt Phú | K66: Full-time | L66: Permanent | M66: 44365 | Q66: LC | R66: LTTP | S66: L | U66: 15000000 | W66: 15000000 | X66: 0 | Y66: 0 | AA66: 0 | AC66: 0 | AD66: 0 | AE66: TB, CN | AF66: 21 | AG66: 19 | AH66: 2 | AI66: 0 | AJ66: 0 | AK66: 21 | AL66: 0 | AM66: 0 | AN66: 0 | AO66: 0 | AP66: 0 | AQ66: 0 | AR66: 15000000 | AS66: 0 | AT66: 0 | AU66: 15000000 | AV66: 0 | AW66: 0 | AX66: 0 | AY66: 0 | AZ66: 0 | BA66: 0 | BE66: 0 | BF66: 0 | BG66: 0 | BH66: 0 | BI66: 0 | BJ66: 0 | BL66: 0 | BO66: 0 | BT66: 0 | BU66: 15000000 | BV66: 0 | BW66: 0 | BX66: 0 | BY66: 11000000 | BZ66: 0 | CA66: 0 | CB66: 1200000 | CC66: 150000 | CD66: 225000 | CE66: 0 | CF66: 1575000 | CG66: 12575000 | CH66: 2425000 | CI66: 121250 | CK66: 121250 | CL66: 0 | CM66: 0 | CN66: 0 | CP66: 0 | CQ66: 0 | CR66: 0 | CS66: 13303750 | CU66: 13303750 | CV66: 2550000 | CW66: 0 | CX66: 450000 | CY66: 0 | DA66: 3000000 | DB66: 4575000 | DC66: 300000 | DD66: 18300000 | DF66: Việt PhúSouthIT | DG66: 1250000 | DH66: HO | DI66: =IFERROR(VLOOKUP($B66,[1]Timesheet!$D:$BK,51,0),0) -> 18 | DJ66: =IFERROR(VLOOKUP($B66,[1]Timesheet!$D:$BK,52,0),0) -> 0 | DK66: =IFERROR(VLOOKUP($B66,[1]Timesheet!$D:$BK,55,0),0) -> 0 | DL66: 0 | DM66: =IFERROR(VLOOKUP($B66,[1]Timesheet!$D:$BK,57,0),0) -> 0 | DN66: =IF(AND(DL66="x",CB66>0),MIN(ROUND(W66*1%,0),149000),0) -> 0 | DP66: =IF(E66="Sales",IF(F66="Logistics",F66,IF(F66="Marketing",F66,DH66)),"") | DQ66: 0 | DR66: 0 | DS66: =IFERROR(VLOOKUP(E66&H66,[1]Group!$D$3:$G$40,4,0),"") | DT66: =J66&I66&DS66 -> Việt PhúSouth
A67: 64 | B67: 4764 | C67: MV004764 | D67: Diệp Mỹ Hảo | E67: Marketing & Communication | F67: Marketing & Communication | G67: Manager (HOD) | H67: Marketing & Communication Manager | I67: South | J67: Movi | K67: Full-time | L67: Permanent | M67: 43327 | Q67: LC | R67: LTTP | S67: L | U67: 60000000 | W67: 60000000 | X67: 0 | Y67: 0 | AA67: 0 | AC67: 0 | AD67: 0 | AE67: TB, CN | AF67: 21 | AG67: 21 | AH67: 0 | AI67: 0 | AJ67: 0 | AK67: 21 | AL67: 0 | AM67: 6 | AN67: 0 | AO67: 6 | AP67: 12 | AQ67: 6 | AR67: 60000000 | AS67: 0 | AT67: 4285714 | AU67: 64285714 | AV67: 0 | AW67: 0 | AX67: 0 | AY67: 0 | AZ67: 0 | BA67: 0 | BE67: 0 | BF67: 0 | BG67: 0 | BH67: 0 | BI67: 0 | BJ67: 0 | BL67: 0 | BO67: 0 | BT67: 0 | BU67: 64285714 | BV67: 2142857.1 | BW67: 0 | BX67: 0 | BY67: 11000000 | BZ67: 2 | CA67: 8800000 | CB67: 2384000 | CC67: 600000 | CD67: 447000 | CE67: 0 | CF67: 3431000 | CG67: 25373857 | CH67: 38911857 | CI67: 6477964.2 | CK67: 6477964.2 | CL67: 0 | CM67: 149000 | CN67: 0 | CP67: 523000 | CQ67: 0 | CR67: 672000 | CS67: 53704750 | CU67: 53704750 | CV67: 5066000 | CW67: 0 | CX67: 894000 | CY67: 0 | DA67: 5960000 | DB67: 9391000 | DC67: 596000 | DD67: 70841714 | DF67: MoviSouthMarketing & Communication | DG67: 5000000 | DH67: HO | DI67: =IFERROR(VLOOKUP($B67,[1]Timesheet!$D:$BK,51,0),0) -> 18 | DJ67: =IFERROR(VLOOKUP($B67,[1]Timesheet!$D:$BK,52,0),0) -> 0 | DK67: =IFERROR(VLOOKUP($B67,[1]Timesheet!$D:$BK,55,0),0) -> 0 | DL67: x | DM67: =IFERROR(VLOOKUP($B67,[1]Timesheet!$D:$BK,57,0),0) -> 0 | DN67: =IF(AND(DL67="x",CB67>0),MIN(ROUND(W67*1%,0),149000),0) -> 149000 | DP67: =IF(E67="Sales",IF(F67="Logistics",F67,IF(F67="Marketing",F67,DH67)),"") | DQ67: 0 | DR67: 0 | DS67: =IFERROR(VLOOKUP(E67&H67,[1]Group!$D$3:$G$40,4,0),"") | DT67: =J67&I67&DS67 -> MoviSouth
A68: 65 | B68: 5674 | C68: MV005674 | D68: Lê Quang Nhật Tân | E68: Marketing & Communication | F68: Branding & Communication | G68: Senior Associate | H68: Senior Designer | I68: South | J68: Movi | K68: Full-time | L68: Permanent | M68: 43958 | Q68: LC | R68: LTTP | S68: L | U68: 10000000 | W68: 10000000 | X68: 0 | Y68: 0 | AA68: 0 | AC68: 0 | AD68: 0 | AE68: TB, CN | AF68: 21 | AG68: 21 | AH68: 0 | AI68: 0 | AJ68: 0 | AK68: 21 | AL68: 0 | AM68: 0 | AN68: 0 | AO68: 0 | AP68: 0 | AQ68: 0 | AR68: 10000000 | AS68: 0 | AT68: 0 | AU68: 10000000 | AV68: 0 | AW68: 0 | AX68: 0 | AY68: 0 | AZ68: 0 | BA68: 0 | BE68: 0 | BF68: 0 | BG68: 0 | BH68: 0 | BI68: 0 | BJ68: 0 | BL68: 0 | BO68: 0 | BT68: 0 | BU68: 10000000 | BV68: 0 | BW68: 0 | BX68: 0 | BY68: 11000000 | BZ68: 0 | CA68: 0 | CB68: 800000 | CC68: 100000 | CD68: 150000 | CE68: 0 | CF68: 1050000 | CG68: 12050000 | CH68: 0 | CI68: 0 | CK68: 0 | CL68: 0 | CM68: 100000 | CN68: 0 | CP68: 0 | CQ68: 0 | CR68: 100000 | CS68: 8850000 | CU68: 8850000 | CV68: 1700000 | CW68: 0 | CX68: 300000 | CY68: 0 | DA68: 2000000 | DB68: 3050000 | DC68: 200000 | DD68: 12200000 | DF68: MoviSouthMarketing & Communication | DG68: 833333.33 | DH68: HO | DI68: =IFERROR(VLOOKUP($B68,[1]Timesheet!$D:$BK,51,0),0) -> 18 | DJ68: =IFERROR(VLOOKUP($B68,[1]Timesheet!$D:$BK,52,0),0) -> 0 | DK68: =IFERROR(VLOOKUP($B68,[1]Timesheet!$D:$BK,55,0),0) -> 0 | DL68: x | DM68: =IFERROR(VLOOKUP($B68,[1]Timesheet!$D:$BK,57,0),0) -> 0 | DN68: =IF(AND(DL68="x",CB68>0),MIN(ROUND(W68*1%,0),149000),0) -> 100000 | DP68: =IF(E68="Sales",IF(F68="Logistics",F68,IF(F68="Marketing",F68,DH68)),"") | DQ68: 0 | DR68: 0 | DS68: =IFERROR(VLOOKUP(E68&H68,[1]Group!$D$3:$G$40,4,0),"") | DT68: =J68&I68&DS68 -> MoviSouth
A69: 66 | B69: 5704 | C69: MV005704 | D69: Trần Thị Mỹ Dung | E69: Marketing & Communication | F69: Field Marketing | G69: Team leader | H69: Field Marketing Team Leader | I69: South | J69: Movi | K69: Full-time | L69: Permanent | M69: 43990 | Q69: LC | R69: LTTP | S69: L | U69: 15000000 | W69: 15000000 | X69: 0 | Y69: 0 | AA69: 0 | AC69: 0 | AD69: 0 | AE69: TB, CN | AF69: 21 | AG69: 20 | AH69: 1 | AI69: 0 | AJ69: 0 | AK69: 21 | AL69: 0 | AM69: 6 | AN69: 0 | AO69: 6 | AP69: 12 | AQ69: 6 | AR69: 15000000 | AS69: 0 | AT69: 1071429 | AU69: 16071429 | AV69: 0 | AW69: 0 | AX69: 0 | AY69: 0 | AZ69: 0 | BA69: 0 | BE69: 0 | BF69: 0 | BG69: 0 | BH69: 0 | BI69: 0 | BJ69: 0 | BL69: 0 | BO69: 0 | BT69: 0 | BU69: 16071429 | BV69: 535714.29 | BW69: 0 | BX69: 0 | BY69: 11000000 | BZ69: 0 | CA69: 0 | CB69: 1200000 | CC69: 150000 | CD69: 225000 | CE69: 0 | CF69: 1575000 | CG69: 13110714 | CH69: 2960714.7 | CI69: 148035.74 | CK69: 148035.74 | CL69: 0 | CM69: 149000 | CN69: 0 | CP69: 499900 | CQ69: 0 | CR69: 648900 | CS69: 13699493 | CU69: 13699493 | CV69: 2550000 | CW69: 0 | CX69: 450000 | CY69: 0 | DA69: 3000000 | DB69: 4575000 | DC69: 300000 | DD69: 19371429 | DF69: MoviSouthMarketing & Communication | DG69: 1250000 | DH69: HO | DI69: =IFERROR(VLOOKUP($B69,[1]Timesheet!$D:$BK,51,0),0) -> 18 | DJ69: =IFERROR(VLOOKUP($B69,[1]Timesheet!$D:$BK,52,0),0) -> 0 | DK69: =IFERROR(VLOOKUP($B69,[1]Timesheet!$D:$BK,55,0),0) -> 0 | DL69: x | DM69: =IFERROR(VLOOKUP($B69,[1]Timesheet!$D:$BK,57,0),0) -> 0 | DN69: =IF(AND(DL69="x",CB69>0),MIN(ROUND(W69*1%,0),149000),0) -> 149000 | DP69: =IF(E69="Sales",IF(F69="Logistics",F69,IF(F69="Marketing",F69,DH69)),"") | DQ69: 0 | DR69: 0 | DS69: =IFERROR(VLOOKUP(E69&H69,[1]Group!$D$3:$G$40,4,0),"") | DT69: =J69&I69&DS69 -> MoviSouth
A70: 67 | B70: 5745 | C70: MV005745 | D70: Trần Thanh Bình | E70: Marketing & Communication | F70: Field Marketing | G70: Associate | H70: Marketing Coordinator | I70: South | J70: Movi | K70: Full-time | L70: Permanent | M70: 44021 | Q70: LC | R70: LTTP | S70: L | U70: 5000000 | W70: 5000000 | X70: 0 | Y70: 0 | AA70: 0 | AC70: 0 | AD70: 0 | AE70: TB, CN | AF70: 21 | AG70: 21 | AH70: 0 | AI70: 0 | AJ70: 0 | AK70: 21 | AL70: 0 | AM70: 6 | AN70: 0 | AO70: 6 | AP70: 12 | AQ70: 6 | AR70: 5000000 | AS70: 0 | AT70: 357143 | AU70: 5357143 | AV70: 0 | AW70: 0 | AX70: 0 | AY70: 0 | AZ70: 0 | BA70: 0 | BE70: 0 | BF70: 0 | BG70: 0 | BH70: 0 | BI70: 0 | BJ70: 0 | BL70: 0 | BO70: 0 | BT70: 0 | BU70: 5357143 | BV70: 178571.43 | BW70: 0 | BX70: 0 | BY70: 11000000 | BZ70: 0 | CA70: 0 | CB70: 400000 | CC70: 50000 | CD70: 75000 | CE70: 0 | CF70: 525000 | CG70: 11703571 | CH70: 0 | CI70: 0 | CK70: 0 | CL70: 0 | CM70: 50000 | CN70: 0 | CP70: 0 | CQ70: 0 | CR70: 50000 | CS70: 4782143 | CU70: 4782143 | CV70: 850000 | CW70: 0 | CX70: 150000 | CY70: 0 | DA70: 1000000 | DB70: 1525000 | DC70: 100000 | DD70: 6457143 | DF70: MoviSouthMarketing & Communication | DG70: 416666.67 | DH70: HO | DI70: =IFERROR(VLOOKUP($B70,[1]Timesheet!$D:$BK,51,0),0) -> 18 | DJ70: =IFERROR(VLOOKUP($B70,[1]Timesheet!$D:$BK,52,0),0) -> 0 | DK70: =IFERROR(VLOOKUP($B70,[1]Timesheet!$D:$BK,55,0),0) -> 0 | DL70: x | DM70: =IFERROR(VLOOKUP($B70,[1]Timesheet!$D:$BK,57,0),0) -> 0 | DN70: =IF(AND(DL70="x",CB70>0),MIN(ROUND(W70*1%,0),149000),0) -> 50000 | DP70: =IF(E70="Sales",IF(F70="Logistics",F70,IF(F70="Marketing",F70,DH70)),"") | DQ70: 0 | DR70: 0 | DS70: =IFERROR(VLOOKUP(E70&H70,[1]Group!$D$3:$G$40,4,0),"") | DT70: =J70&I70&DS70 -> MoviSouth
A71: 68 | B71: 5862 | C71: MV005862 | D71: Nguyễn Minh Tân | E71: Marketing & Communication | F71: Branding & Communication | G71: Associate | H71: Junior Designer | I71: South | J71: Movi | K71: Full-time | L71: Permanent | M71: 44060 | Q71: LC | R71: LTTP | S71: L | U71: 5000000 | W71: 5000000 | X71: 0 | Y71: 0 | AA71: 0 | AC71: 0 | AD71: 0 | AE71: TB, CN | AF71: 21 | AG71: 21 | AH71: 0 | AI71: 0 | AJ71: 0 | AK71: 21 | AL71: 0 | AM71: 6 | AN71: 0 | AO71: 6 | AP71: 12 | AQ71: 6 | AR71: 5000000 | AS71: 0 | AT71: 357143 | AU71: 5357143 | AV71: 0 | AW71: 0 | AX71: 0 | AY71: 0 | AZ71: 0 | BA71: 0 | BE71: 0 | BF71: 0 | BG71: 0 | BH71: 0 | BI71: 0 | BJ71: 0 | BL71: 0 | BO71: 0 | BT71: 0 | BU71: 5357143 | BV71: 178571.43 | BW71: 0 | BX71: 0 | BY71: 11000000 | BZ71: 0 | CA71: 0 | CB71: 400000 | CC71: 50000 | CD71: 75000 | CE71: 0 | CF71: 525000 | CG71: 11703571 | CH71: 0 | CI71: 0 | CK71: 0 | CL71: 0 | CM71: 0 | CN71: 0 | CP71: 0 | CQ71: 0 | CR71: 0 | CS71: 4832143 | CU71: 4832143 | CV71: 850000 | CW71: 0 | CX71: 150000 | CY71: 0 | DA71: 1000000 | DB71: 1525000 | DC71: 100000 | DD71: 6457143 | DF71: MoviSouthMarketing & Communication | DG71: 416666.67 | DH71: HO | DI71: =IFERROR(VLOOKUP($B71,[1]Timesheet!$D:$BK,51,0),0) -> 18 | DJ71: =IFERROR(VLOOKUP($B71,[1]Timesheet!$D:$BK,52,0),0) -> 0 | DK71: =IFERROR(VLOOKUP($B71,[1]Timesheet!$D:$BK,55,0),0) -> 0 | DL71: 0 | DM71: =IFERROR(VLOOKUP($B71,[1]Timesheet!$D:$BK,57,0),0) -> 0 | DN71: =IF(AND(DL71="x",CB71>0),MIN(ROUND(W71*1%,0),149000),0) -> 0 | DP71: =IF(E71="Sales",IF(F71="Logistics",F71,IF(F71="Marketing",F71,DH71)),"") | DQ71: 0 | DR71: 0 | DS71: =IFERROR(VLOOKUP(E71&H71,[1]Group!$D$3:$G$40,4,0),"") | DT71: =J71&I71&DS71 -> MoviSouth
A72: 69 | B72: 6087 | C72: MV006087 | D72: Nguyễn Thị Đông Quỳnh | E72: Marketing & Communication | F72: Field Marketing | G72: Associate | H72: Field Marketing Officer | I72: South | J72: Movi | K72: Full-time | L72: Permanent | M72: 44291 | Q72: LC | R72: LTTP | S72: L | U72: 5000000 | W72: 5000000 | X72: 0 | Y72: 0 | AA72: 0 | AC72: 0 | AD72: 0 | AE72: TB, CN | AF72: 21 | AG72: 19 | AH72: 2 | AI72: 0 | AJ72: 0 | AK72: 21 | AL72: 0 | AM72: 6 | AN72: 0 | AO72: 6 | AP72: 12 | AQ72: 6 | AR72: 5000000 | AS72: 0 | AT72: 357143 | AU72: 5357143 | AV72: 0 | AW72: 0 | AX72: 0 | AY72: 0 | AZ72: 0 | BA72: 0 | BE72: 0 | BF72: 0 | BG72: 0 | BH72: 0 | BI72: 0 | BJ72: 0 | BL72: 0 | BO72: 0 | BT72: 0 | BU72: 5357143 | BV72: 178571.43 | BW72: 0 | BX72: 0 | BY72: 11000000 | BZ72: 0 | CA72: 0 | CB72: 400000 | CC72: 50000 | CD72: 75000 | CE72: 0 | CF72: 525000 | CG72: 11703571 | CH72: 0 | CI72: 0 | CK72: 0 | CL72: 0 | CM72: 0 | CN72: 0 | CP72: 0 | CQ72: 0 | CR72: 0 | CS72: 4832143 | CU72: 4832143 | CV72: 850000 | CW72: 0 | CX72: 150000 | CY72: 0 | DA72: 1000000 | DB72: 1525000 | DC72: 100000 | DD72: 6457143 | DF72: MoviSouthMarketing & Communication | DG72: 416666.67 | DH72: HO | DI72: =IFERROR(VLOOKUP($B72,[1]Timesheet!$D:$BK,51,0),0) -> 18 | DJ72: =IFERROR(VLOOKUP($B72,[1]Timesheet!$D:$BK,52,0),0) -> 0 | DK72: =IFERROR(VLOOKUP($B72,[1]Timesheet!$D:$BK,55,0),0) -> 0 | DL72: 0 | DM72: =IFERROR(VLOOKUP($B72,[1]Timesheet!$D:$BK,57,0),0) -> 0 | DN72: =IF(AND(DL72="x",CB72>0),MIN(ROUND(W72*1%,0),149000),0) -> 0 | DP72: =IF(E72="Sales",IF(F72="Logistics",F72,IF(F72="Marketing",F72,DH72)),"") | DQ72: 0 | DR72: 0 | DS72: =IFERROR(VLOOKUP(E72&H72,[1]Group!$D$3:$G$40,4,0),"") | DT72: =J72&I72&DS72 -> MoviSouth
A73: 70 | B73: 6088 | C73: MV006088 | D73: Nguyễn Văn Ngọc | E73: Marketing & Communication | F73: Field Marketing | G73: Associate | H73: Field Marketing Officer | I73: South | J73: Movi | K73: Full-time | L73: Leaving | M73: 44291 | P73: 44535 | Q73: LC | R73: LTTP | S73: L | U73: 5000000 | W73: 5000000 | X73: 0 | Y73: 0 | AA73: 0 | AC73: 0 | AD73: 0 | AE73: TB, CN | AF73: 21 | AG73: 6 | AH73: 0 | AI73: 0 | AJ73: 0 | AK73: 6 | AL73: 0 | AM73: 6 | AN73: 0 | AO73: 6 | AP73: 12 | AQ73: 6 | AR73: 1428571 | AS73: 2666667 | AT73: 357143 | AU73: 4452381 | AV73: 0 | AW73: 0 | AX73: 0 | AY73: 0 | AZ73: 0 | BA73: 0 | BE73: 0 | BF73: 0 | BG73: 0 | BH73: 0 | BI73: 0 | BJ73: 0 | BL73: 0 | BO73: 0 | BT73: 0 | BU73: 4452381 | BV73: 178571.43 | BW73: 0 | BX73: 0 | BY73: 11000000 | BZ73: 0 | CA73: 0 | CB73: 0 | CC73: 0 | CD73: 0 | CE73: 0 | CF73: 0 | CG73: 11178571 | CH73: 0 | CI73: 0 | CK73: 0 | CL73: 0 | CM73: 0 | CN73: 0 | CP73: 0 | CQ73: 0 | CR73: 0 | CS73: 4452381 | CU73: 4452381 | CV73: 0 | CW73: 0 | CX73: 0 | CY73: 0 | DA73: 0 | DB73: 0 | DC73: 0 | DD73: 4452381 | DF73: MoviSouthMarketing & Communication | DG73: 416666.67 | DH73: HO | DI73: =IFERROR(VLOOKUP($B73,[1]Timesheet!$D:$BK,51,0),0) -> 3 | DJ73: =IFERROR(VLOOKUP($B73,[1]Timesheet!$D:$BK,52,0),0) -> 0 | DK73: =IFERROR(VLOOKUP($B73,[1]Timesheet!$D:$BK,55,0),0) -> 0 | DL73: 0 | DM73: =IFERROR(VLOOKUP($B73,[1]Timesheet!$D:$BK,57,0),0) -> 0 | DN73: =IF(AND(DL73="x",CB73>0),MIN(ROUND(W73*1%,0),149000),0) -> 0 | DP73: =IF(E73="Sales",IF(F73="Logistics",F73,IF(F73="Marketing",F73,DH73)),"") | DQ73: 0 | DR73: 0 | DS73: =IFERROR(VLOOKUP(E73&H73,[1]Group!$D$3:$G$40,4,0),"") | DT73: =J73&I73&DS73 -> MoviSouth
A74: 71 | B74: 6104 | C74: MV006104 | D74: Nguyễn Bửu | E74: Marketing & Communication | F74: Field Marketing | G74: Associate | H74: Field Marketing Officer | I74: South | J74: Movi | K74: Full-time | L74: Permanent | M74: 44298 | Q74: LC | R74: LTTP | S74: L | U74: 5000000 | W74: 5000000 | X74: 0 | Y74: 0 | AA74: 0 | AC74: 0 | AD74: 0 | AE74: TB, CN | AF74: 21 | AG74: 19 | AH74: 2 | AI74: 0 | AJ74: 0 | AK74: 21 | AL74: 0 | AM74: 0 | AN74: 0 | AO74: 0 | AP74: 0 | AQ74: 0 | AR74: 5000000 | AS74: 0 | AT74: 0 | AU74: 5000000 | AV74: 0 | AW74: 0 | AX74: 0 | AY74: 0 | AZ74: 0 | BA74: 0 | BE74: 0 | BF74: 0 | BG74: 0 | BH74: 0 | BI74: 0 | BJ74: 0 | BL74: 0 | BO74: 0 | BT74: 0 | BU74: 5000000 | BV74: 0 | BW74: 0 | BX74: 0 | BY74: 11000000 | BZ74: 0 | CA74: 0 | CB74: 400000 | CC74: 50000 | CD74: 75000 | CE74: 0 | CF74: 525000 | CG74: 11525000 | CH74: 0 | CI74: 0 | CK74: 0 | CL74: 0 | CM74: 0 | CN74: 0 | CP74: 0 | CQ74: 0 | CR74: 0 | CS74: 4475000 | CU74: 4475000 | CV74: 850000 | CW74: 0 | CX74: 150000 | CY74: 0 | DA74: 1000000 | DB74: 1525000 | DC74: 100000 | DD74: 6100000 | DF74: MoviSouthMarketing & Communication | DG74: 416666.67 | DH74: HO | DI74: =IFERROR(VLOOKUP($B74,[1]Timesheet!$D:$BK,51,0),0) -> 18 | DJ74: =IFERROR(VLOOKUP($B74,[1]Timesheet!$D:$BK,52,0),0) -> 0 | DK74: =IFERROR(VLOOKUP($B74,[1]Timesheet!$D:$BK,55,0),0) -> 0 | DL74: 0 | DM74: =IFERROR(VLOOKUP($B74,[1]Timesheet!$D:$BK,57,0),0) -> 0 | DN74: =IF(AND(DL74="x",CB74>0),MIN(ROUND(W74*1%,0),149000),0) -> 0 | DP74: =IF(E74="Sales",IF(F74="Logistics",F74,IF(F74="Marketing",F74,DH74)),"") | DQ74: 0 | DR74: 0 | DS74: =IFERROR(VLOOKUP(E74&H74,[1]Group!$D$3:$G$40,4,0),"") | DT74: =J74&I74&DS74 -> MoviSouth
A75: 72 | B75: 6151 | C75: MV006151 | D75: Nguyễn Thị Thanh Xuân | E75: Marketing & Communication | F75: Field Marketing | G75: Associate | H75: Field Marketing Officer | I75: South | J75: Movi | K75: Full-time | L75: Permanent | M75: 44342 | Q75: LC | R75: LTTP | S75: L | U75: 5000000 | W75: 5000000 | X75: 0 | Y75: 0 | AA75: 0 | AC75: 0 | AD75: 0 | AE75: TB, CN | AF75: 21 | AG75: 19 | AH75: 2 | AI75: 0 | AJ75: 0 | AK75: 21 | AL75: 0 | AM75: 6 | AN75: 0 | AO75: 6 | AP75: 12 | AQ75: 6 | AR75: 5000000 | AS75: 0 | AT75: 357143 | AU75: 5357143 | AV75: 0 | AW75: 0 | AX75: 0 | AY75: 0 | AZ75: 0 | BA75: 0 | BE75: 0 | BF75: 0 | BG75: 0 | BH75: 0 | BI75: 0 | BJ75: 0 | BL75: 0 | BO75: 0 | BT75: 0 | BU75: 5357143 | BV75: 178571.43 | BW75: 0 | BX75: 0 | BY75: 11000000 | BZ75: 0 | CA75: 0 | CB75: 400000 | CC75: 50000 | CD75: 75000 | CE75: 0 | CF75: 525000 | CG75: 11703571 | CH75: 0 | CI75: 0 | CK75: 0 | CL75: 0 | CM75: 0 | CN75: 0 | CP75: 0 | CQ75: 0 | CR75: 0 | CS75: 4832143 | CU75: 4832143 | CV75: 850000 | CW75: 0 | CX75: 150000 | CY75: 0 | DA75: 1000000 | DB75: 1525000 | DC75: 100000 | DD75: 6457143 | DF75: MoviSouthMarketing & Communication | DG75: 416666.67 | DH75: HO | DI75: =IFERROR(VLOOKUP($B75,[1]Timesheet!$D:$BK,51,0),0) -> 18 | DJ75: =IFERROR(VLOOKUP($B75,[1]Timesheet!$D:$BK,52,0),0) -> 0 | DK75: =IFERROR(VLOOKUP($B75,[1]Timesheet!$D:$BK,55,0),0) -> 0 | DL75: 0 | DM75: =IFERROR(VLOOKUP($B75,[1]Timesheet!$D:$BK,57,0),0) -> 0 | DN75: =IF(AND(DL75="x",CB75>0),MIN(ROUND(W75*1%,0),149000),0) -> 0 | DP75: =IF(E75="Sales",IF(F75="Logistics",F75,IF(F75="Marketing",F75,DH75)),"") | DQ75: 0 | DR75: 0 | DS75: =IFERROR(VLOOKUP(E75&H75,[1]Group!$D$3:$G$40,4,0),"") | DT75: =J75&I75&DS75 -> MoviSouth
A76: 73 | B76: 6186 | C76: MV006186 | D76: Nguyễn Nhựt Thành | E76: Marketing & Communication | F76: Digital Marketing | G76: Senior Associate | H76: Senior Digital Marketing Executive | I76: South | J76: Movi | K76: Full-time | L76: Permanent | M76: 44455 | Q76: LC | R76: LTTP | S76: L | U76: 10000000 | W76: 10000000 | X76: 0 | Y76: 0 | AA76: 0 | AC76: 0 | AD76: 0 | AE76: TB, CN | AF76: 21 | AG76: 21 | AH76: 0 | AI76: 0 | AJ76: 0 | AK76: 21 | AL76: 0 | AM76: 6 | AN76: 0 | AO76: 6 | AP76: 12 | AQ76: 6 | AR76: 10000000 | AS76: 0 | AT76: 714286 | AU76: 10714286 | AV76: 0 | AW76: 0 | AX76: 0 | AY76: 0 | AZ76: 0 | BA76: 0 | BE76: 0 | BF76: 0 | BG76: 0 | BH76: 0 | BI76: 0 | BJ76: 0 | BL76: 0 | BO76: 0 | BT76: 0 | BU76: 10714286 | BV76: 357142.86 | BW76: 0 | BX76: 0 | BY76: 11000000 | BZ76: 0 | CA76: 0 | CB76: 800000 | CC76: 100000 | CD76: 150000 | CE76: 0 | CF76: 1050000 | CG76: 12407143 | CH76: 0 | CI76: 0 | CK76: 0 | CL76: 0 | CM76: 100000 | CN76: 0 | CP76: 0 | CQ76: 0 | CR76: 100000 | CS76: 9564286 | CU76: 9564286 | CV76: 1700000 | CW76: 0 | CX76: 300000 | CY76: 0 | DA76: 2000000 | DB76: 3050000 | DC76: 200000 | DD76: 12914286 | DF76: MoviSouthMarketing & Communication | DG76: 833333.33 | DH76: HO | DI76: =IFERROR(VLOOKUP($B76,[1]Timesheet!$D:$BK,51,0),0) -> 18 | DJ76: =IFERROR(VLOOKUP($B76,[1]Timesheet!$D:$BK,52,0),0) -> 1 | DK76: =IFERROR(VLOOKUP($B76,[1]Timesheet!$D:$BK,55,0),0) -> 0 | DL76: x | DM76: =IFERROR(VLOOKUP($B76,[1]Timesheet!$D:$BK,57,0),0) -> 0 | DN76: =IF(AND(DL76="x",CB76>0),MIN(ROUND(W76*1%,0),149000),0) -> 100000 | DP76: =IF(E76="Sales",IF(F76="Logistics",F76,IF(F76="Marketing",F76,DH76)),"") | DQ76: 0 | DR76: 0 | DS76: =IFERROR(VLOOKUP(E76&H76,[1]Group!$D$3:$G$40,4,0),"") | DT76: =J76&I76&DS76 -> MoviSouth
A77: 74 | B77: 5315 | C77: MV005315 | D77: Huỳnh Thị Thanh Thảo | E77: Product | F77: Product | G77: HOD | H77: Head of Product | I77: South | J77: Movi | K77: Full-time | L77: Permanent | M77: 43718 | Q77: LC | R77: LTTP | S77: L | U77: 80000000 | W77: 80000000 | X77: 0 | Y77: 0 | AA77: 0 | AC77: 0 | AD77: 0 | AE77: TB, CN | AF77: 21 | AG77: 14 | AH77: 7 | AI77: 0 | AJ77: 0 | AK77: 21 | AL77: 0 | AM77: 0 | AN77: 0 | AO77: 0 | AP77: 0 | AQ77: 0 | AR77: 80000000 | AS77: 0 | AT77: 0 | AU77: 80000000 | AV77: 0 | AW77: 0 | AX77: 0 | AY77: 0 | AZ77: 0 | BA77: 0 | BE77: 0 | BF77: 0 | BG77: 0 | BH77: 0 | BI77: 0 | BJ77: 0 | BL77: 0 | BO77: 0 | BT77: 0 | BU77: 80000000 | BV77: 0 | BW77: 0 | BX77: 0 | BY77: 11000000 | BZ77: 0 | CA77: 0 | CB77: 2384000 | CC77: 800000 | CD77: 447000 | CE77: 0 | CF77: 3631000 | CG77: 14631000 | CH77: 65369000 | CI77: 13760700 | CK77: 13760700 | CL77: 0 | CM77: 0 | CN77: 0 | CP77: 0 | CQ77: 0 | CR77: 0 | CS77: 62608300 | CU77: 62608300 | CV77: 5066000 | CW77: 0 | CX77: 894000 | CY77: 0 | DA77: 5960000 | DB77: 9591000 | DC77: 596000 | DD77: 86556000 | DF77: MoviSouthProduct | DG77: 6666666.7 | DH77: HO | DI77: =IFERROR(VLOOKUP($B77,[1]Timesheet!$D:$BK,51,0),0) -> 18 | DJ77: =IFERROR(VLOOKUP($B77,[1]Timesheet!$D:$BK,52,0),0) -> 0 | DK77: =IFERROR(VLOOKUP($B77,[1]Timesheet!$D:$BK,55,0),0) -> 0 | DL77: 0 | DM77: =IFERROR(VLOOKUP($B77,[1]Timesheet!$D:$BK,57,0),0) -> 0 | DN77: =IF(AND(DL77="x",CB77>0),MIN(ROUND(W77*1%,0),149000),0) -> 0 | DP77: =IF(E77="Sales",IF(F77="Logistics",F77,IF(F77="Marketing",F77,DH77)),"") | DQ77: 0 | DR77: 0 | DS77: =IFERROR(VLOOKUP(E77&H77,[1]Group!$D$3:$G$40,4,0),"") | DT77: =J77&I77&DS77 -> MoviSouth
A78: 75 | B78: 5932 | C78: MV005932 | D78: Nguyễn Hoàng Oanh | E78: Product | F78: Product | G78: Assistant Manager | H78: Assistant Product Manager | I78: South | J78: Movi | K78: Full-time | L78: Permanent | M78: 44102 | Q78: LC | R78: LTTP | S78: L | U78: 30000000 | W78: 30000000 | X78: 0 | Y78: 0 | AA78: 0 | AC78: 0 | AD78: 0 | AE78: TB, CN | AF78: 21 | AG78: 16 | AH78: 5 | AI78: 0 | AJ78: 0 | AK78: 21 | AL78: 0 | AM78: 0 | AN78: 0 | AO78: 0 | AP78: 0 | AQ78: 0 | AR78: 30000000 | AS78: 0 | AT78: 0 | AU78: 30000000 | AV78: 0 | AW78: 0 | AX78: 0 | AY78: 0 | AZ78: 0 | BA78: 0 | BE78: 0 | BF78: 0 | BG78: 0 | BH78: 0 | BI78: 0 | BJ78: 0 | BL78: 0 | BO78: 0 | BT78: 0 | BU78: 30000000 | BV78: 0 | BW78: 0 | BX78: 0 | BY78: 11000000 | BZ78: 0 | CA78: 0 | CB78: 2384000 | CC78: 300000 | CD78: 447000 | CE78: 0 | CF78: 3131000 | CG78: 14131000 | CH78: 15869000 | CI78: 1630350 | CK78: 1630350 | CL78: 0 | CM78: 0 | CN78: 0 | CP78: 0 | CQ78: 0 | CR78: 0 | CS78: 25238650 | CU78: 25238650 | CV78: 5066000 | CW78: 0 | CX78: 894000 | CY78: 0 | DA78: 5960000 | DB78: 9091000 | DC78: 596000 | DD78: 36556000 | DF78: MoviSouthProduct | DG78: 2500000 | DH78: HO | DI78: =IFERROR(VLOOKUP($B78,[1]Timesheet!$D:$BK,51,0),0) -> 18 | DJ78: =IFERROR(VLOOKUP($B78,[1]Timesheet!$D:$BK,52,0),0) -> 0 | DK78: =IFERROR(VLOOKUP($B78,[1]Timesheet!$D:$BK,55,0),0) -> 0 | DL78: 0 | DM78: =IFERROR(VLOOKUP($B78,[1]Timesheet!$D:$BK,57,0),0) -> 0 | DN78: =IF(AND(DL78="x",CB78>0),MIN(ROUND(W78*1%,0),149000),0) -> 0 | DP78: =IF(E78="Sales",IF(F78="Logistics",F78,IF(F78="Marketing",F78,DH78)),"") | DQ78: 0 | DR78: 0 | DS78: =IFERROR(VLOOKUP(E78&H78,[1]Group!$D$3:$G$40,4,0),"") | DT78: =J78&I78&DS78 -> MoviSouth
A79: 76 | B79: 5003 | C79: VP005003 | D79: Nguyễn Thành Nhân | E79: Risk | F79: Fraud Control & Prevention | G79: Team leader | H79: Team Leader Fraud Control | I79: South | J79: Việt Phú | K79: Full-time | L79: Permanent | M79: 43563 | Q79: LC | R79: LTTP | S79: L | U79: 15000000 | W79: 15000000 | X79: 0 | Y79: 0 | AA79: 0 | AC79: 0 | AD79: 0 | AE79: TB, CN | AF79: 21 | AG79: 21 | AH79: 0 | AI79: 0 | AJ79: 0 | AK79: 21 | AL79: 0 | AM79: 0 | AN79: 0 | AO79: 0 | AP79: 0 | AQ79: 0 | AR79: 15000000 | AS79: 0 | AT79: 0 | AU79: 15000000 | AV79: 0 | AW79: 0 | AX79: 0 | AY79: 0 | AZ79: 0 | BA79: 0 | BE79: 0 | BF79: 0 | BG79: 0 | BH79: 0 | BI79: 0 | BJ79: 0 | BL79: 0 | BO79: 0 | BT79: 0 | BU79: 15000000 | BV79: 0 | BW79: 0 | BX79: 0 | BY79: 11000000 | BZ79: 0 | CA79: 0 | CB79: 1200000 | CC79: 150000 | CD79: 225000 | CE79: 0 | CF79: 1575000 | CG79: 12575000 | CH79: 2425000 | CI79: 121250 | CK79: 121250 | CL79: 0 | CM79: 0 | CN79: 0 | CP79: 0 | CQ79: 0 | CR79: 0 | CS79: 13303750 | CU79: 13303750 | CV79: 2550000 | CW79: 0 | CX79: 450000 | CY79: 0 | DA79: 3000000 | DB79: 4575000 | DC79: 300000 | DD79: 18300000 | DF79: Việt PhúSouthRisk | DG79: 1250000 | DH79: HO | DI79: =IFERROR(VLOOKUP($B79,[1]Timesheet!$D:$BK,51,0),0) -> 18 | DJ79: =IFERROR(VLOOKUP($B79,[1]Timesheet!$D:$BK,52,0),0) -> 0 | DK79: =IFERROR(VLOOKUP($B79,[1]Timesheet!$D:$BK,55,0),0) -> 0 | DL79: 0 | DM79: =IFERROR(VLOOKUP($B79,[1]Timesheet!$D:$BK,57,0),0) -> 0 | DN79: =IF(AND(DL79="x",CB79>0),MIN(ROUND(W79*1%,0),149000),0) -> 0 | DP79: =IF(E79="Sales",IF(F79="Logistics",F79,IF(F79="Marketing",F79,DH79)),"") | DQ79: 0 | DR79: 0 | DS79: =IFERROR(VLOOKUP(E79&H79,[1]Group!$D$3:$G$40,4,0),"") | DT79: =J79&I79&DS79 -> Việt PhúSouth
A80: 77 | B80: 5341 | C80: VP005341 | D80: Lê Thị Bích Ngọc | E80: Risk | F80: Fraud Control & Prevention | G80: Associate | H80: Fraud Control Administrator | I80: South | J80: Việt Phú | K80: Full-time | L80: Permanent | M80: 43724 | Q80: LC | R80: LTTP | S80: L | U80: 5000000 | W80: 5000000 | X80: 0 | Y80: 0 | AA80: 0 | AC80: 0 | AD80: 0 | AE80: TB, CN | AF80: 21 | AG80: 17 | AH80: 4 | AI80: 0 | AJ80: 0 | AK80: 21 | AL80: 0 | AM80: 0 | AN80: 0 | AO80: 0 | AP80: 0 | AQ80: 0 | AR80: 5000000 | AS80: 0 | AT80: 0 | AU80: 5000000 | AV80: 0 | AW80: 0 | AX80: 0 | AY80: 0 | AZ80: 0 | BA80: 0 | BE80: 0 | BF80: 0 | BG80: 0 | BH80: 0 | BI80: 0 | BJ80: 0 | BL80: 0 | BO80: 0 | BT80: 0 | BU80: 5000000 | BV80: 0 | BW80: 0 | BX80: 0 | BY80: 11000000 | BZ80: 0 | CA80: 0 | CB80: 400000 | CC80: 50000 | CD80: 75000 | CE80: 0 | CF80: 525000 | CG80: 11525000 | CH80: 0 | CI80: 0 | CK80: 0 | CL80: 0 | CM80: 0 | CN80: 0 | CP80: 0 | CQ80: 0 | CR80: 0 | CS80: 4475000 | CU80: 4475000 | CV80: 850000 | CW80: 0 | CX80: 150000 | CY80: 0 | DA80: 1000000 | DB80: 1525000 | DC80: 100000 | DD80: 6100000 | DF80: Việt PhúSouthRisk | DG80: 416666.67 | DH80: HO | DI80: =IFERROR(VLOOKUP($B80,[1]Timesheet!$D:$BK,51,0),0) -> 18 | DJ80: =IFERROR(VLOOKUP($B80,[1]Timesheet!$D:$BK,52,0),0) -> 0 | DK80: =IFERROR(VLOOKUP($B80,[1]Timesheet!$D:$BK,55,0),0) -> 0 | DL80: 0 | DM80: =IFERROR(VLOOKUP($B80,[1]Timesheet!$D:$BK,57,0),0) -> 0 | DN80: =IF(AND(DL80="x",CB80>0),MIN(ROUND(W80*1%,0),149000),0) -> 0 | DP80: =IF(E80="Sales",IF(F80="Logistics",F80,IF(F80="Marketing",F80,DH80)),"") | DQ80: 0 | DR80: 0 | DS80: =IFERROR(VLOOKUP(E80&H80,[1]Group!$D$3:$G$40,4,0),"") | DT80: =J80&I80&DS80 -> Việt PhúSouth
A81: 78 | B81: 5151 | C81: VP005151 | D81: Nguyễn Thị Xuân Thanh | E81: Risk | F81: Quality and Process Assurance | G81: Manager | H81: Manager, Quality and Process Assurance | I81: South | J81: Việt Phú | K81: Full-time | L81: Permanent | M81: 43661 | Q81: LC | R81: LTTP | S81: L | U81: 40000000 | W81: 40000000 | X81: 0 | Y81: 0 | AA81: 0 | AC81: 0 | AD81: 0 | AE81: TB, CN | AF81: 21 | AG81: 18 | AH81: 3 | AI81: 0 | AJ81: 0 | AK81: 21 | AL81: 0 | AM81: 0 | AN81: 0 | AO81: 0 | AP81: 0 | AQ81: 0 | AR81: 40000000 | AS81: 0 | AT81: 0 | AU81: 40000000 | AV81: 0 | AW81: 0 | AX81: 0 | AY81: 0 | AZ81: 0 | BA81: 0 | BE81: 0 | BF81: 0 | BG81: 0 | BH81: 0 | BI81: 0 | BJ81: 0 | BL81: 0 | BO81: 0 | BT81: 0 | BU81: 40000000 | BV81: 0 | BW81: 0 | BX81: 0 | BY81: 11000000 | BZ81: 2 | CA81: 8800000 | CB81: 2384000 | CC81: 400000 | CD81: 447000 | CE81: 0 | CF81: 3231000 | CG81: 23031000 | CH81: 16969000 | CI81: 1795350 | CK81: 1795350 | CL81: 0 | CM81: 0 | CN81: 0 | CP81: 0 | CQ81: 0 | CR81: 0 | CS81: 34973650 | CU81: 34973650 | CV81: 5066000 | CW81: 0 | CX81: 894000 | CY81: 0 | DA81: 5960000 | DB81: 9191000 | DC81: 596000 | DD81: 46556000 | DF81: Việt PhúSouthRisk | DG81: 3333333.3 | DH81: HO | DI81: =IFERROR(VLOOKUP($B81,[1]Timesheet!$D:$BK,51,0),0) -> 18 | DJ81: =IFERROR(VLOOKUP($B81,[1]Timesheet!$D:$BK,52,0),0) -> 0 | DK81: =IFERROR(VLOOKUP($B81,[1]Timesheet!$D:$BK,55,0),0) -> 0 | DL81: 0 | DM81: =IFERROR(VLOOKUP($B81,[1]Timesheet!$D:$BK,57,0),0) -> 0 | DN81: =IF(AND(DL81="x",CB81>0),MIN(ROUND(W81*1%,0),149000),0) -> 0 | DP81: =IF(E81="Sales",IF(F81="Logistics",F81,IF(F81="Marketing",F81,DH81)),"") | DQ81: 0 | DR81: 0 | DS81: =IFERROR(VLOOKUP(E81&H81,[1]Group!$D$3:$G$40,4,0),"") | DT81: =J81&I81&DS81 -> Việt PhúSouth
A82: 79 | B82: 1809 | C82: VP001809 | D82: Đặng Minh Quân | E82: Risk | F82: Quality and Process Assurance | G82: Associate | H82: Quality and Process Assurance Officer | I82: South | J82: Việt Phú | K82: Full-time | L82: Permanent | M82: 42107 | Q82: LC | R82: LTTP | S82: L | U82: 5000000 | W82: 5000000 | X82: 0 | Y82: 0 | AA82: 0 | AC82: 0 | AD82: 0 | AE82: TB, CN | AF82: 21 | AG82: 16 | AH82: 5 | AI82: 0 | AJ82: 0 | AK82: 21 | AL82: 0 | AM82: 0 | AN82: 0 | AO82: 0 | AP82: 0 | AQ82: 0 | AR82: 5000000 | AS82: 0 | AT82: 0 | AU82: 5000000 | AV82: 0 | AW82: 0 | AX82: 0 | AY82: 0 | AZ82: 0 | BA82: 0 | BE82: 0 | BF82: 0 | BG82: 0 | BH82: 0 | BI82: 0 | BJ82: 0 | BL82: 0 | BO82: 0 | BT82: 0 | BU82: 5000000 | BV82: 0 | BW82: 0 | BX82: 0 | BY82: 11000000 | BZ82: 0 | CA82: 0 | CB82: 400000 | CC82: 50000 | CD82: 75000 | CE82: 0 | CF82: 525000 | CG82: 11525000 | CH82: 0 | CI82: 0 | CK82: 0 | CL82: 0 | CM82: 0 | CN82: 0 | CP82: 0 | CQ82: 0 | CR82: 0 | CS82: 4475000 | CU82: 4475000 | CV82: 850000 | CW82: 0 | CX82: 150000 | CY82: 0 | DA82: 1000000 | DB82: 1525000 | DC82: 100000 | DD82: 6100000 | DF82: Việt PhúSouthRisk | DG82: 416666.67 | DH82: HO | DI82: =IFERROR(VLOOKUP($B82,[1]Timesheet!$D:$BK,51,0),0) -> 18 | DJ82: =IFERROR(VLOOKUP($B82,[1]Timesheet!$D:$BK,52,0),0) -> 0 | DK82: =IFERROR(VLOOKUP($B82,[1]Timesheet!$D:$BK,55,0),0) -> 0 | DL82: 0 | DM82: =IFERROR(VLOOKUP($B82,[1]Timesheet!$D:$BK,57,0),0) -> 0 | DN82: =IF(AND(DL82="x",CB82>0),MIN(ROUND(W82*1%,0),149000),0) -> 0 | DP82: =IF(E82="Sales",IF(F82="Logistics",F82,IF(F82="Marketing",F82,DH82)),"") | DQ82: 0 | DR82: 0 | DS82: =IFERROR(VLOOKUP(E82&H82,[1]Group!$D$3:$G$40,4,0),"") | DT82: =J82&I82&DS82 -> Việt PhúSouth
A83: 80 | B83: 6038 | C83: VP006038 | D83: Đỗ Thị Hương Trang | E83: Risk | F83: Risk Analytics & Business Intelligence | G83: Associate | H83: Data Analyst | I83: South | J83: Việt Phú | K83: Full-time | L83: Leaving | M83: 44179 | P83: 44578 | Q83: LC | R83: LTTP | S83: L | U83: 5000000 | W83: 5000000 | X83: 0 | Y83: 0 | AA83: 0 | AC83: 0 | AD83: 0 | AE83: TB, CN | AF83: 21 | AG83: 18 | AH83: 3 | AI83: 0 | AJ83: 0 | AK83: 21 | AL83: 0 | AM83: 0 | AN83: 0 | AO83: 0 | AP83: 0 | AQ83: 0 | AR83: 5000000 | AS83: 0 | AT83: 0 | AU83: 5000000 | AV83: 0 | AW83: 0 | AX83: 0 | AY83: 0 | AZ83: 0 | BA83: 0 | BE83: 0 | BF83: 0 | BG83: 0 | BH83: 0 | BI83: 0 | BJ83: 0 | BL83: 0 | BO83: 0 | BT83: 0 | BU83: 5000000 | BV83: 0 | BW83: 0 | BX83: 0 | BY83: 11000000 | BZ83: 0 | CA83: 0 | CB83: 400000 | CC83: 50000 | CD83: 75000 | CE83: 0 | CF83: 525000 | CG83: 11525000 | CH83: 0 | CI83: 0 | CK83: 0 | CL83: 0 | CM83: 0 | CN83: 0 | CP83: 0 | CQ83: 0 | CR83: 0 | CS83: 4475000 | CU83: 4475000 | CV83: 850000 | CW83: 0 | CX83: 150000 | CY83: 0 | DA83: 1000000 | DB83: 1525000 | DC83: 100000 | DD83: 6100000 | DF83: Việt PhúSouthRisk | DG83: 416666.67 | DH83: HO | DI83: =IFERROR(VLOOKUP($B83,[1]Timesheet!$D:$BK,51,0),0) -> 18 | DJ83: =IFERROR(VLOOKUP($B83,[1]Timesheet!$D:$BK,52,0),0) -> 0 | DK83: =IFERROR(VLOOKUP($B83,[1]Timesheet!$D:$BK,55,0),0) -> 0 | DL83: 0 | DM83: =IFERROR(VLOOKUP($B83,[1]Timesheet!$D:$BK,57,0),0) -> 0 | DN83: =IF(AND(DL83="x",CB83>0),MIN(ROUND(W83*1%,0),149000),0) -> 0 | DP83: =IF(E83="Sales",IF(F83="Logistics",F83,IF(F83="Marketing",F83,DH83)),"") | DQ83: 0 | DR83: 0 | DS83: =IFERROR(VLOOKUP(E83&H83,[1]Group!$D$3:$G$40,4,0),"") | DT83: =J83&I83&DS83 -> Việt PhúSouth
A84: 81 | B84: 6160 | C84: VP006160 | D84: Nguyễn Thị Tố Quyên | E84: Risk | F84: Risk Analytics & Business Intelligence | G84: Senior Associate | H84: Data Analyst | I84: South | J84: Việt Phú | K84: Full-time | L84: Permanent | M84: 44342 | Q84: LC | R84: LTTP | S84: L | U84: 10000000 | W84: 10000000 | X84: 0 | Y84: 0 | AA84: 0 | AC84: 0 | AD84: 0 | AE84: TB, CN | AF84: 21 | AG84: 21 | AH84: 0 | AI84: 0 | AJ84: 0 | AK84: 21 | AL84: 0 | AM84: 0 | AN84: 0 | AO84: 0 | AP84: 0 | AQ84: 0 | AR84: 10000000 | AS84: 0 | AT84: 0 | AU84: 10000000 | AV84: 0 | AW84: 0 | AX84: 0 | AY84: 0 | AZ84: 0 | BA84: 0 | BE84: 0 | BF84: 0 | BG84: 0 | BH84: 0 | BI84: 0 | BJ84: 0 | BL84: 0 | BO84: 0 | BT84: 0 | BU84: 10000000 | BV84: 0 | BW84: 0 | BX84: 0 | BY84: 11000000 | BZ84: 0 | CA84: 0 | CB84: 800000 | CC84: 100000 | CD84: 150000 | CE84: 0 | CF84: 1050000 | CG84: 12050000 | CH84: 0 | CI84: 0 | CK84: 0 | CL84: 0 | CM84: 0 | CN84: 0 | CP84: 0 | CQ84: 0 | CR84: 0 | CS84: 8950000 | CU84: 8950000 | CV84: 1700000 | CW84: 0 | CX84: 300000 | CY84: 0 | DA84: 2000000 | DB84: 3050000 | DC84: 200000 | DD84: 12200000 | DF84: Việt PhúSouthRisk | DG84: 833333.33 | DH84: HO | DI84: =IFERROR(VLOOKUP($B84,[1]Timesheet!$D:$BK,51,0),0) -> 18 | DJ84: =IFERROR(VLOOKUP($B84,[1]Timesheet!$D:$BK,52,0),0) -> 0 | DK84: =IFERROR(VLOOKUP($B84,[1]Timesheet!$D:$BK,55,0),0) -> 0 | DL84: 0 | DM84: =IFERROR(VLOOKUP($B84,[1]Timesheet!$D:$BK,57,0),0) -> 0 | DN84: =IF(AND(DL84="x",CB84>0),MIN(ROUND(W84*1%,0),149000),0) -> 0 | DP84: =IF(E84="Sales",IF(F84="Logistics",F84,IF(F84="Marketing",F84,DH84)),"") | DQ84: 0 | DR84: 0 | DS84: =IFERROR(VLOOKUP(E84&H84,[1]Group!$D$3:$G$40,4,0),"") | DT84: =J84&I84&DS84 -> Việt PhúSouth
A85: 82 | B85: 6187 | C85: VP006187 | D85: Võ Đăng Tâm | E85: Risk | F85: Risk Analytics & Business Intelligence | G85: Associate | H85: Data Engineer | I85: South | J85: Việt Phú | K85: Full-time | L85: Permanent | M85: 44455 | Q85: LC | R85: LTTP | S85: L | U85: 5000000 | W85: 5000000 | X85: 0 | Y85: 0 | AA85: 0 | AC85: 0 | AD85: 0 | AE85: TB, CN | AF85: 21 | AG85: 21 | AH85: 0 | AI85: 0 | AJ85: 0 | AK85: 21 | AL85: 0 | AM85: 0 | AN85: 0 | AO85: 0 | AP85: 0 | AQ85: 0 | AR85: 5000000 | AS85: 0 | AT85: 0 | AU85: 5000000 | AV85: 0 | AW85: 0 | AX85: 0 | AY85: 0 | AZ85: 0 | BA85: 0 | BE85: 0 | BF85: 0 | BG85: 0 | BH85: 0 | BI85: 0 | BJ85: 0 | BL85: 0 | BO85: 0 | BT85: 0 | BU85: 5000000 | BV85: 0 | BW85: 0 | BX85: 0 | BY85: 11000000 | BZ85: 0 | CA85: 0 | CB85: 400000 | CC85: 50000 | CD85: 75000 | CE85: 0 | CF85: 525000 | CG85: 11525000 | CH85: 0 | CI85: 0 | CK85: 0 | CL85: 0 | CM85: 0 | CN85: 0 | CP85: 0 | CQ85: 0 | CR85: 0 | CS85: 4475000 | CU85: 4475000 | CV85: 850000 | CW85: 0 | CX85: 150000 | CY85: 0 | DA85: 1000000 | DB85: 1525000 | DC85: 100000 | DD85: 6100000 | DF85: Việt PhúSouthRisk | DG85: 416666.67 | DH85: HO | DI85: =IFERROR(VLOOKUP($B85,[1]Timesheet!$D:$BK,51,0),0) -> 18 | DJ85: =IFERROR(VLOOKUP($B85,[1]Timesheet!$D:$BK,52,0),0) -> 1 | DK85: =IFERROR(VLOOKUP($B85,[1]Timesheet!$D:$BK,55,0),0) -> 0 | DL85: 0 | DM85: =IFERROR(VLOOKUP($B85,[1]Timesheet!$D:$BK,57,0),0) -> 0 | DN85: =IF(AND(DL85="x",CB85>0),MIN(ROUND(W85*1%,0),149000),0) -> 0 | DP85: =IF(E85="Sales",IF(F85="Logistics",F85,IF(F85="Marketing",F85,DH85)),"") | DQ85: 0 | DR85: 0 | DS85: =IFERROR(VLOOKUP(E85&H85,[1]Group!$D$3:$G$40,4,0),"") | DT85: =J85&I85&DS85 -> Việt PhúSouth
A86: 83 | B86: 6190 | C86: VP006190 | D86: Nguyễn Thị Ngọc Hiệp | E86: Risk | F86: Operational & Enterprise Risk | G86: Manager | H86: Operational Risk & Control Manager | I86: South | J86: Việt Phú | K86: Full-time | L86: Permanent | M86: 44445 | Q86: LC | R86: LTTP | S86: L | U86: 40000000 | W86: 40000000 | X86: 0 | Y86: 0 | AA86: 0 | AC86: 0 | AD86: 0 | AE86: TB, CN | AF86: 21 | AG86: 19 | AH86: 2 | AI86: 0 | AJ86: 0 | AK86: 21 | AL86: 0 | AM86: 0 | AN86: 0 | AO86: 0 | AP86: 0 | AQ86: 0 | AR86: 40000000 | AS86: 0 | AT86: 0 | AU86: 40000000 | AV86: 0 | AW86: 0 | AX86: 0 | AY86: 0 | AZ86: 0 | BA86: 0 | BE86: 0 | BF86: 0 | BG86: 0 | BH86: 0 | BI86: 0 | BJ86: 0 | BL86: 0 | BO86: 0 | BT86: 0 | BU86: 40000000 | BV86: 0 | BW86: 0 | BX86: 0 | BY86: 11000000 | BZ86: 0 | CA86: 0 | CB86: 2384000 | CC86: 400000 | CD86: 447000 | CE86: 0 | CF86: 3231000 | CG86: 14231000 | CH86: 25769000 | CI86: 3503800 | CK86: 3503800 | CL86: 0 | CM86: 0 | CN86: 0 | CP86: 0 | CQ86: 0 | CR86: 0 | CS86: 33265200 | CU86: 33265200 | CV86: 5066000 | CW86: 0 | CX86: 894000 | CY86: 0 | DA86: 5960000 | DB86: 9191000 | DC86: 596000 | DD86: 46556000 | DF86: Việt PhúSouthRisk | DG86: 3333333.3 | DH86: HO | DI86: =IFERROR(VLOOKUP($B86,[1]Timesheet!$D:$BK,51,0),0) -> 18 | DJ86: =IFERROR(VLOOKUP($B86,[1]Timesheet!$D:$BK,52,0),0) -> 0 | DK86: =IFERROR(VLOOKUP($B86,[1]Timesheet!$D:$BK,55,0),0) -> 0 | DL86: 0 | DM86: =IFERROR(VLOOKUP($B86,[1]Timesheet!$D:$BK,57,0),0) -> 0 | DN86: =IF(AND(DL86="x",CB86>0),MIN(ROUND(W86*1%,0),149000),0) -> 0 | DP86: =IF(E86="Sales",IF(F86="Logistics",F86,IF(F86="Marketing",F86,DH86)),"") | DQ86: 0 | DR86: 0 | DS86: =IFERROR(VLOOKUP(E86&H86,[1]Group!$D$3:$G$40,4,0),"") | DT86: =J86&I86&DS86 -> Việt PhúSouth
A87: 84 | B87: 5041 | C87: VP005041 | D87: Ngô Tuấn Kiệt | E87: Risk | F87: Collection | G87: Manager | H87: Manager, Collection | I87: South | J87: Việt Phú | K87: Full-time | L87: Permanent | M87: 43600 | Q87: LC | R87: LTTP | S87: L | U87: 40000000 | W87: 40000000 | X87: 0 | Y87: 0 | AA87: 0 | AC87: 0 | AD87: 0 | AE87: TB, CN | AF87: 21 | AG87: 16 | AH87: 5 | AI87: 0 | AJ87: 0 | AK87: 21 | AL87: 0 | AM87: 0 | AN87: 0 | AO87: 0 | AP87: 0 | AQ87: 0 | AR87: 40000000 | AS87: 0 | AT87: 0 | AU87: 40000000 | AV87: 0 | AW87: 0 | AX87: 0 | AY87: 0 | AZ87: 0 | BA87: 0 | BE87: 0 | BF87: 0 | BG87: 0 | BH87: 0 | BI87: 0 | BJ87: 0 | BL87: 0 | BO87: 0 | BT87: 0 | BU87: 40000000 | BV87: 0 | BW87: 0 | BX87: 0 | BY87: 11000000 | BZ87: 6 | CA87: 26400000 | CB87: 2384000 | CC87: 400000 | CD87: 447000 | CE87: 0 | CF87: 3231000 | CG87: 40631000 | CH87: 0 | CI87: 0 | CK87: 0 | CL87: 0 | CM87: 0 | CN87: 0 | CP87: 0 | CQ87: 0 | CR87: 0 | CS87: 36769000 | CU87: 36769000 | CV87: 5066000 | CW87: 0 | CX87: 894000 | CY87: 0 | DA87: 5960000 | DB87: 9191000 | DC87: 596000 | DD87: 46556000 | DF87: Việt PhúSouthRisk | DG87: 3333333.3 | DH87: HO | DI87: =IFERROR(VLOOKUP($B87,[1]Timesheet!$D:$BK,51,0),0) -> 18 | DJ87: =IFERROR(VLOOKUP($B87,[1]Timesheet!$D:$BK,52,0),0) -> 0 | DK87: =IFERROR(VLOOKUP($B87,[1]Timesheet!$D:$BK,55,0),0) -> 0 | DL87: 0 | DM87: =IFERROR(VLOOKUP($B87,[1]Timesheet!$D:$BK,57,0),0) -> 0 | DN87: =IF(AND(DL87="x",CB87>0),MIN(ROUND(W87*1%,0),149000),0) -> 0 | DP87: =IF(E87="Sales",IF(F87="Logistics",F87,IF(F87="Marketing",F87,DH87)),"") | DQ87: 0 | DR87: 0 | DS87: =IFERROR(VLOOKUP(E87&H87,[1]Group!$D$3:$G$40,4,0),"") | DT87: =J87&I87&DS87 -> Việt PhúSouth
A88: 85 | B88: 5150 | C88: VP005150 | D88: Nguyễn Thị Bích Thủy | E88: Risk | F88: Collection | G88: Assistant Manager | H88: Assistant Collection Manager | I88: South | J88: Việt Phú | K88: Full-time | L88: Permanent | M88: 43661 | Q88: LC | R88: LTTP | S88: L | U88: 30000000 | W88: 30000000 | X88: 0 | Y88: 0 | AA88: 0 | AC88: 0 | AD88: 0 | AE88: TB, CN | AF88: 21 | AG88: 15.5 | AH88: 5.5 | AI88: 0 | AJ88: 0 | AK88: 21 | AL88: 0 | AM88: 0 | AN88: 0 | AO88: 0 | AP88: 0 | AQ88: 0 | AR88: 30000000 | AS88: 0 | AT88: 0 | AU88: 30000000 | AV88: 0 | AW88: 0 | AX88: 0 | AY88: 0 | AZ88: 0 | BA88: 0 | BE88: 0 | BF88: 0 | BG88: 0 | BH88: 0 | BI88: 0 | BJ88: 0 | BL88: 0 | BO88: 0 | BT88: 0 | BU88: 30000000 | BV88: 0 | BW88: 0 | BX88: 0 | BY88: 11000000 | BZ88: 7 | CA88: 30800000 | CB88: 2384000 | CC88: 300000 | CD88: 447000 | CE88: 0 | CF88: 3131000 | CG88: 44931000 | CH88: 0 | CI88: 0 | CK88: 0 | CL88: 0 | CM88: 0 | CN88: 0 | CP88: 0 | CQ88: 0 | CR88: 0 | CS88: 26869000 | CU88: 26869000 | CV88: 5066000 | CW88: 0 | CX88: 894000 | CY88: 0 | DA88: 5960000 | DB88: 9091000 | DC88: 596000 | DD88: 36556000 | DF88: Việt PhúSouthRisk | DG88: 2500000 | DH88: HO | DI88: =IFERROR(VLOOKUP($B88,[1]Timesheet!$D:$BK,51,0),0) -> 18 | DJ88: =IFERROR(VLOOKUP($B88,[1]Timesheet!$D:$BK,52,0),0) -> 0 | DK88: =IFERROR(VLOOKUP($B88,[1]Timesheet!$D:$BK,55,0),0) -> 0 | DL88: 0 | DM88: =IFERROR(VLOOKUP($B88,[1]Timesheet!$D:$BK,57,0),0) -> 0 | DN88: =IF(AND(DL88="x",CB88>0),MIN(ROUND(W88*1%,0),149000),0) -> 0 | DP88: =IF(E88="Sales",IF(F88="Logistics",F88,IF(F88="Marketing",F88,DH88)),"") | DQ88: 0 | DR88: 0 | DS88: =IFERROR(VLOOKUP(E88&H88,[1]Group!$D$3:$G$40,4,0),"") | DT88: =J88&I88&DS88 -> Việt PhúSouth
A89: 86 | B89: 5542 | C89: VP005542 | D89: Nguyễn Thị Thanh Huệ | E89: Risk | F89: Collection | G89: Team leader | H89: Team Leader Call Collection | I89: South | J89: Việt Phú | K89: Full-time | L89: Permanent | M89: 43801 | Q89: LC | R89: LTTP | S89: L | U89: 15000000 | W89: 15000000 | X89: 0 | Y89: 0 | AA89: 0 | AC89: 0 | AD89: 0 | AE89: CN | AF89: 26 | AG89: 25.5 | AH89: 0.5 | AI89: 0 | AJ89: 0 | AK89: 26 | AL89: 0 | AM89: 0 | AN89: 0 | AO89: 0 | AP89: 0 | AQ89: 0 | AR89: 15000000 | AS89: 0 | AT89: 0 | AU89: 15000000 | AV89: 0 | AW89: 0 | AX89: 0 | AY89: 0 | AZ89: 0 | BA89: 0 | BE89: 0 | BF89: 0 | BG89: 0 | BH89: 0 | BI89: 0 | BJ89: 13268961 | BL89: 0 | BO89: 0 | BT89: 13268961 | BU89: 28268961 | BV89: 0 | BW89: 0 | BX89: 0 | BY89: 11000000 | BZ89: 2 | CA89: 8800000 | CB89: 1200000 | CC89: 150000 | CD89: 225000 | CE89: 0 | CF89: 1575000 | CG89: 21375000 | CH89: 6893961 | CI89: 439396.1 | CK89: 439396.1 | CL89: 0 | CM89: 149000 | CN89: 0 | CP89: 0 | CQ89: 0 | CR89: 149000 | CS89: 26105565 | CU89: 26105565 | CV89: 2550000 | CW89: 0 | CX89: 450000 | CY89: 0 | DA89: 3000000 | DB89: 4575000 | DC89: 300000 | DD89: 31568961 | DF89: Việt PhúSouthRisk | DG89: 1250000 | DH89: HO | DI89: =IFERROR(VLOOKUP($B89,[1]Timesheet!$D:$BK,51,0),0) -> 22 | DJ89: =IFERROR(VLOOKUP($B89,[1]Timesheet!$D:$BK,52,0),0) -> 0 | DK89: =IFERROR(VLOOKUP($B89,[1]Timesheet!$D:$BK,55,0),0) -> 0 | DL89: x | DM89: =IFERROR(VLOOKUP($B89,[1]Timesheet!$D:$BK,57,0),0) -> 0 | DN89: =IF(AND(DL89="x",CB89>0),MIN(ROUND(W89*1%,0),149000),0) -> 149000 | DP89: =IF(E89="Sales",IF(F89="Logistics",F89,IF(F89="Marketing",F89,DH89)),"") | DQ89: 0 | DR89: 0 | DS89: =IFERROR(VLOOKUP(E89&H89,[1]Group!$D$3:$G$40,4,0),"") | DT89: =J89&I89&DS89 -> Việt PhúSouth
A90: 87 | B90: CM0669 | C90: VPCM0669 | D90: Mai Thị Sương | E90: Risk | F90: Collection | G90: Associate | H90: Debt Collection Officer | I90: South | J90: Việt Phú | K90: Full-time | L90: Permanent | M90: 42191 | Q90: LC | R90: LTTP | S90: L | U90: 5000000 | W90: 5000000 | X90: 0 | Y90: 0 | AA90: 0 | AC90: 0 | AD90: 0 | AE90: CN | AF90: 26 | AG90: 24 | AH90: 2 | AI90: 0 | AJ90: 0 | AK90: 26 | AL90: 0 | AM90: 0 | AN90: 0 | AO90: 0 | AP90: 0 | AQ90: 0 | AR90: 5000000 | AS90: 0 | AT90: 0 | AU90: 5000000 | AV90: 0 | AW90: 0 | AX90: 0 | AY90: 0 | AZ90: 0 | BA90: 0 | BE90: 0 | BF90: 0 | BG90: 0 | BH90: 0 | BI90: 0 | BJ90: 7839061 | BL90: 0 | BO90: 0 | BT90: 7839061 | BU90: 12839061 | BV90: 0 | BW90: 0 | BX90: 0 | BY90: 11000000 | BZ90: 0 | CA90: 0 | CB90: 400000 | CC90: 50000 | CD90: 75000 | CE90: 0 | CF90: 525000 | CG90: 11525000 | CH90: 1314061 | CI90: 65703.05 | CK90: 65703.05 | CL90: 0 | CM90: 50000 | CN90: 0 | CP90: 0 | CQ90: 0 | CR90: 50000 | CS90: 12198358 | CU90: 12198358 | CV90: 850000 | CW90: 0 | CX90: 150000 | CY90: 0 | DA90: 1000000 | DB90: 1525000 | DC90: 100000 | DD90: 13939061 | DF90: Việt PhúSouthRisk | DG90: 416666.67 | DH90: HO | DI90: =IFERROR(VLOOKUP($B90,[1]Timesheet!$D:$BK,51,0),0) -> 22 | DJ90: =IFERROR(VLOOKUP($B90,[1]Timesheet!$D:$BK,52,0),0) -> 0 | DK90: =IFERROR(VLOOKUP($B90,[1]Timesheet!$D:$BK,55,0),0) -> 0 | DL90: x | DM90: =IFERROR(VLOOKUP($B90,[1]Timesheet!$D:$BK,57,0),0) -> 0 | DN90: =IF(AND(DL90="x",CB90>0),MIN(ROUND(W90*1%,0),149000),0) -> 50000 | DP90: =IF(E90="Sales",IF(F90="Logistics",F90,IF(F90="Marketing",F90,DH90)),"") | DQ90: 0 | DR90: 0 | DS90: =IFERROR(VLOOKUP(E90&H90,[1]Group!$D$3:$G$40,4,0),"") | DT90: =J90&I90&DS90 -> Việt PhúSouth
A91: 88 | B91: 2580 | C91: VP002580 | D91: Đinh Thị Anh Thư | E91: Risk | F91: Collection | G91: Associate | H91: Debt Collection Officer | I91: South | J91: Việt Phú | K91: Full-time | L91: Maternity | M91: 42254 | N91: 23/12/2021 - 22/06/2022 | Q91: LC | R91: LTTP | S91: L | U91: 5000000 | W91: 5000000 | X91: 0 | Y91: 0 | AA91: 0 | AC91: 0 | AD91: 0 | AE91: CN | AF91: 26 | AG91: 19 | AH91: 4 | AI91: 0 | AJ91: 0 | AK91: 23 | AL91: 0 | AM91: 0 | AN91: 0 | AO91: 0 | AP91: 0 | AQ91: 0 | AR91: 4423077 | AS91: 0 | AT91: 0 | AU91: 4423077 | AV91: 0 | AW91: 0 | AX91: 0 | AY91: 0 | AZ91: 0 | BA91: 0 | BE91: 0 | BF91: 0 | BG91: 0 | BH91: 0 | BI91: 0 | BJ91: 6570017 | BL91: 0 | BO91: 0 | BT91: 6570017 | BU91: 10993094 | BV91: 0 | BW91: 0 | BX91: 0 | BY91: 11000000 | BZ91: 0 | CA91: 0 | CB91: 400000 | CC91: 50000 | CD91: 75000 | CE91: 0 | CF91: 525000 | CG91: 11525000 | CH91: 0 | CI91: 0 | CK91: 0 | CL91: 0 | CM91: 50000 | CN91: 0 | CP91: 0 | CQ91: 0 | CR91: 50000 | CS91: 10418094 | CU91: 10418094 | CV91: 850000 | CW91: 0 | CX91: 150000 | CY91: 0 | DA91: 1000000 | DB91: 1525000 | DC91: 100000 | DD91: 12093094 | DF91: Việt PhúSouthRisk | DG91: 416666.67 | DH91: HO | DI91: =IFERROR(VLOOKUP($B91,[1]Timesheet!$D:$BK,51,0),0) -> 19 | DJ91: =IFERROR(VLOOKUP($B91,[1]Timesheet!$D:$BK,52,0),0) -> 0 | DK91: =IFERROR(VLOOKUP($B91,[1]Timesheet!$D:$BK,55,0),0) -> 0 | DL91: x | DM91: =IFERROR(VLOOKUP($B91,[1]Timesheet!$D:$BK,57,0),0) -> 0 | DN91: =IF(AND(DL91="x",CB91>0),MIN(ROUND(W91*1%,0),149000),0) -> 50000 | DP91: =IF(E91="Sales",IF(F91="Logistics",F91,IF(F91="Marketing",F91,DH91)),"") | DQ91: 44553 | DR91: 44734 | DS91: =IFERROR(VLOOKUP(E91&H91,[1]Group!$D$3:$G$40,4,0),"") | DT91: =J91&I91&DS91 -> Việt PhúSouth
A92: 89 | B92: 4647 | C92: VP004647 | D92: Trần Thị Thu Thủy Tiên | E92: Risk | F92: Collection | G92: Associate | H92: Debt Collection Officer | I92: South | J92: Việt Phú | K92: Full-time | L92: Permanent | M92: 43249 | Q92: LC | R92: LTTP | S92: L | U92: 5000000 | W92: 5000000 | X92: 0 | Y92: 0 | AA92: 0 | AC92: 0 | AD92: 0 | AE92: CN | AF92: 26 | AG92: 24 | AH92: 0 | AI92: 0 | AJ92: 0 | AK92: 24 | AL92: 0 | AM92: 0 | AN92: 0 | AO92: 0 | AP92: 0 | AQ92: 0 | AR92: 4615385 | AS92: -230769 | AT92: 0 | AU92: 4384616 | AV92: 0 | AW92: 0 | AX92: 0 | AY92: 0 | AZ92: 0 | BA92: 0 | BE92: 0 | BF92: 0 | BG92: 0 | BH92: 0 | BI92: 0 | BJ92: 5733461 | BL92: 0 | BO92: 0 | BT92: 5733461 | BU92: 10118077 | BV92: 0 | BW92: 0 | BX92: 0 | BY92: 11000000 | BZ92: 0 | CA92: 0 | CB92: 400000 | CC92: 50000 | CD92: 75000 | CE92: 0 | CF92: 525000 | CG92: 11525000 | CH92: 0 | CI92: 0 | CK92: 0 | CL92: 0 | CM92: 50000 | CN92: 0 | CP92: 0 | CQ92: 0 | CR92: 50000 | CS92: 9543077 | CU92: 9543077 | CV92: 850000 | CW92: 0 | CX92: 150000 | CY92: 0 | DA92: 1000000 | DB92: 1525000 | DC92: 100000 | DD92: 11218077 | DF92: Việt PhúSouthRisk | DG92: 416666.67 | DH92: HO | DI92: =IFERROR(VLOOKUP($B92,[1]Timesheet!$D:$BK,51,0),0) -> 19 | DJ92: =IFERROR(VLOOKUP($B92,[1]Timesheet!$D:$BK,52,0),0) -> 0 | DK92: =IFERROR(VLOOKUP($B92,[1]Timesheet!$D:$BK,55,0),0) -> 3 | DL92: x | DM92: =IFERROR(VLOOKUP($B92,[1]Timesheet!$D:$BK,57,0),0) -> 0 | DN92: =IF(AND(DL92="x",CB92>0),MIN(ROUND(W92*1%,0),149000),0) -> 50000 | DP92: =IF(E92="Sales",IF(F92="Logistics",F92,IF(F92="Marketing",F92,DH92)),"") | DQ92: 0 | DR92: 0 | DS92: =IFERROR(VLOOKUP(E92&H92,[1]Group!$D$3:$G$40,4,0),"") | DT92: =J92&I92&DS92 -> Việt PhúSouth
A93: 90 | B93: 5646 | C93: VP005646 | D93: Phạm Hữu Anh Thư | E93: Risk | F93: Collection | G93: Associate | H93: Debt Collection Officer | I93: South | J93: Việt Phú | K93: Full-time | L93: Maternity | M93: 43837 | N93: 17/10/2021 - 16/04/2022 | Q93: LC | R93: LTTP | S93: L | U93: 5000000 | W93: 5000000 | X93: 0 | Y93: 0 | AA93: 0 | AC93: 0 | AD93: 0 | AE93: CN | AF93: 26 | AG93: 0 | AH93: 0 | AI93: 0 | AJ93: 0 | AK93: 0 | AL93: 0 | AM93: 0 | AN93: 0 | AO93: 0 | AP93: 0 | AQ93: 0 | AR93: 0 | AS93: 0 | AT93: 0 | AU93: 0 | AV93: 0 | AW93: 0 | AX93: 0 | AY93: 0 | AZ93: 0 | BA93: 0 | BE93: 0 | BF93: 0 | BG93: 0 | BH93: 0 | BI93: 0 | BJ93: 0 | BL93: 0 | BO93: 0 | BT93: 0 | BU93: 0 | BV93: 0 | BW93: 0 | BX93: 0 | BY93: 11000000 | BZ93: 3 | CA93: 13200000 | CB93: 0 | CC93: 0 | CD93: 0 | CE93: 0 | CF93: 0 | CG93: 24200000 | CH93: 0 | CI93: 0 | CK93: 0 | CL93: 0 | CM93: 0 | CN93: 0 | CP93: 0 | CQ93: 0 | CR93: 0 | CS93: 0 | CU93: 0 | CV93: 0 | CW93: 0 | CX93: 0 | CY93: 0 | DA93: 0 | DB93: 0 | DC93: 0 | DD93: 0 | DF93: Việt PhúSouthRisk | DG93: 416666.67 | DH93: HO | DI93: =IFERROR(VLOOKUP($B93,[1]Timesheet!$D:$BK,51,0),0) -> 0 | DJ93: =IFERROR(VLOOKUP($B93,[1]Timesheet!$D:$BK,52,0),0) -> 0 | DK93: =IFERROR(VLOOKUP($B93,[1]Timesheet!$D:$BK,55,0),0) -> 0 | DL93: 0 | DM93: =IFERROR(VLOOKUP($B93,[1]Timesheet!$D:$BK,57,0),0) -> 0 | DN93: =IF(AND(DL93="x",CB93>0),MIN(ROUND(W93*1%,0),149000),0) -> 0 | DP93: =IF(E93="Sales",IF(F93="Logistics",F93,IF(F93="Marketing",F93,DH93)),"") | DQ93: 44486 | DR93: 44667 | DS93: =IFERROR(VLOOKUP(E93&H93,[1]Group!$D$3:$G$40,4,0),"") | DT93: =J93&I93&DS93 -> Việt PhúSouth
A94: 91 | B94: 5660 | C94: VP005660 | D94: Huỳnh Thị Thanh Trúc | E94: Risk | F94: Collection | G94: Associate | H94: Debt Collection Officer | I94: South | J94: Việt Phú | K94: Full-time | L94: Permanent | M94: 43896 | Q94: LC | R94: LTTP | S94: L | U94: 5000000 | W94: 5000000 | X94: 0 | Y94: 0 | AA94: 0 | AC94: 0 | AD94: 0 | AE94: CN | AF94: 26 | AG94: 24.5 | AH94: 0 | AI94: 0 | AJ94: 0 | AK94: 24.5 | AL94: 0 | AM94: 0 | AN94: 0 | AO94: 0 | AP94: 0 | AQ94: 0 | AR94: 4711538 | AS94: -115385 | AT94: 0 | AU94: 4596153 | AV94: 0 | AW94: 0 | AX94: 0 | AY94: 0 | AZ94: 0 | BA94: 0 | BE94: 0 | BF94: 0 | BG94: 0 | BH94: 0 | BI94: 0 | BJ94: 5978879 | BL94: 0 | BO94: 0 | BT94: 5978879 | BU94: 10575032 | BV94: 0 | BW94: 0 | BX94: 0 | BY94: 11000000 | BZ94: 0 | CA94: 0 | CB94: 400000 | CC94: 50000 | CD94: 75000 | CE94: 0 | CF94: 525000 | CG94: 11525000 | CH94: 0 | CI94: 0 | CK94: 0 | CL94: 0 | CM94: 50000 | CN94: 0 | CP94: 0 | CQ94: 0 | CR94: 50000 | CS94: 10000032 | CU94: 10000032 | CV94: 850000 | CW94: 0 | CX94: 150000 | CY94: 0 | DA94: 1000000 | DB94: 1525000 | DC94: 100000 | DD94: 11675032 | DF94: Việt PhúSouthRisk | DG94: 416666.67 | DH94: HO | DI94: =IFERROR(VLOOKUP($B94,[1]Timesheet!$D:$BK,51,0),0) -> 20 | DJ94: =IFERROR(VLOOKUP($B94,[1]Timesheet!$D:$BK,52,0),0) -> 0 | DK94: =IFERROR(VLOOKUP($B94,[1]Timesheet!$D:$BK,55,0),0) -> 2 | DL94: x | DM94: =IFERROR(VLOOKUP($B94,[1]Timesheet!$D:$BK,57,0),0) -> 0 | DN94: =IF(AND(DL94="x",CB94>0),MIN(ROUND(W94*1%,0),149000),0) -> 50000 | DP94: =IF(E94="Sales",IF(F94="Logistics",F94,IF(F94="Marketing",F94,DH94)),"") | DQ94: 0 | DR94: 0 | DS94: =IFERROR(VLOOKUP(E94&H94,[1]Group!$D$3:$G$40,4,0),"") | DT94: =J94&I94&DS94 -> Việt PhúSouth
A95: 92 | B95: 5662 | C95: VP005662 | D95: Đỗ Thị Ngọc Hằng | E95: Risk | F95: Collection | G95: Associate | H95: Debt Collection Officer | I95: South | J95: Việt Phú | K95: Full-time | L95: Permanent | M95: 43899 | Q95: LC | R95: LTTP | S95: L | U95: 5000000 | W95: 5000000 | X95: 0 | Y95: 0 | AA95: 0 | AC95: 0 | AD95: 0 | AE95: CN | AF95: 26 | AG95: 24 | AH95: 2 | AI95: 0 | AJ95: 0 | AK95: 26 | AL95: 0 | AM95: 0 | AN95: 0 | AO95: 0 | AP95: 0 | AQ95: 0 | AR95: 5000000 | AS95: 0 | AT95: 0 | AU95: 5000000 | AV95: 0 | AW95: 0 | AX95: 0 | AY95: 0 | AZ95: 0 | BA95: 0 | BE95: 0 | BF95: 0 | BG95: 0 | BH95: 0 | BI95: 0 | BJ95: 372385 | BL95: 0 | BO95: 0 | BT95: 372385 | BU95: 5372385 | BV95: 0 | BW95: 0 | BX95: 0 | BY95: 11000000 | BZ95: 0 | CA95: 0 | CB95: 400000 | CC95: 50000 | CD95: 75000 | CE95: 0 | CF95: 525000 | CG95: 11525000 | CH95: 0 | CI95: 0 | CK95: 0 | CL95: 0 | CM95: 0 | CN95: 0 | CP95: 0 | CQ95: 0 | CR95: 0 | CS95: 4847385 | CU95: 4847385 | CV95: 850000 | CW95: 0 | CX95: 150000 | CY95: 0 | DA95: 1000000 | DB95: 1525000 | DC95: 100000 | DD95: 6472385 | DF95: Việt PhúSouthRisk | DG95: 416666.67 | DH95: HO | DI95: =IFERROR(VLOOKUP($B95,[1]Timesheet!$D:$BK,51,0),0) -> 22 | DJ95: =IFERROR(VLOOKUP($B95,[1]Timesheet!$D:$BK,52,0),0) -> 0 | DK95: =IFERROR(VLOOKUP($B95,[1]Timesheet!$D:$BK,55,0),0) -> 0 | DL95: 0 | DM95: =IFERROR(VLOOKUP($B95,[1]Timesheet!$D:$BK,57,0),0) -> 0 | DN95: =IF(AND(DL95="x",CB95>0),MIN(ROUND(W95*1%,0),149000),0) -> 0 | DP95: =IF(E95="Sales",IF(F95="Logistics",F95,IF(F95="Marketing",F95,DH95)),"") | DQ95: 0 | DR95: 0 | DS95: =IFERROR(VLOOKUP(E95&H95,[1]Group!$D$3:$G$40,4,0),"") | DT95: =J95&I95&DS95 -> Việt PhúSouth
A96: 93 | B96: 5667 | C96: VP005667 | D96: Nguyễn Ngô Quốc Bảo | E96: Risk | F96: Collection | G96: Associate | H96: Debt Collection Officer | I96: South | J96: Việt Phú | K96: Full-time | L96: Permanent | M96: 43920 | Q96: LC | R96: LTTP | S96: L | U96: 5000000 | W96: 5000000 | X96: 0 | Y96: 0 | AA96: 0 | AC96: 0 | AD96: 0 | AE96: CN | AF96: 26 | AG96: 24 | AH96: 2 | AI96: 0 | AJ96: 0 | AK96: 26 | AL96: 0 | AM96: 0 | AN96: 0 | AO96: 0 | AP96: 0 | AQ96: 0 | AR96: 5000000 | AS96: 0 | AT96: 0 | AU96: 5000000 | AV96: 0 | AW96: 0 | AX96: 0 | AY96: 0 | AZ96: 0 | BA96: 0 | BE96: 0 | BF96: 0 | BG96: 0 | BH96: 0 | BI96: 0 | BJ96: 5735031 | BL96: 0 | BO96: 0 | BT96: 5735031 | BU96: 10735031 | BV96: 0 | BW96: 0 | BX96: 0 | BY96: 11000000 | BZ96: 0 | CA96: 0 | CB96: 400000 | CC96: 50000 | CD96: 75000 | CE96: 0 | CF96: 525000 | CG96: 11525000 | CH96: 0 | CI96: 0 | CK96: 0 | CL96: 0 | CM96: 50000 | CN96: 0 | CP96: 0 | CQ96: 0 | CR96: 50000 | CS96: 10160031 | CU96: 10160031 | CV96: 850000 | CW96: 0 | CX96: 150000 | CY96: 0 | DA96: 1000000 | DB96: 1525000 | DC96: 100000 | DD96: 11835031 | DF96: Việt PhúSouthRisk | DG96: 416666.67 | DH96: HO | DI96: =IFERROR(VLOOKUP($B96,[1]Timesheet!$D:$BK,51,0),0) -> 22 | DJ96: =IFERROR(VLOOKUP($B96,[1]Timesheet!$D:$BK,52,0),0) -> 0 | DK96: =IFERROR(VLOOKUP($B96,[1]Timesheet!$D:$BK,55,0),0) -> 0 | DL96: x | DM96: =IFERROR(VLOOKUP($B96,[1]Timesheet!$D:$BK,57,0),0) -> 0 | DN96: =IF(AND(DL96="x",CB96>0),MIN(ROUND(W96*1%,0),149000),0) -> 50000 | DP96: =IF(E96="Sales",IF(F96="Logistics",F96,IF(F96="Marketing",F96,DH96)),"") | DQ96: 0 | DR96: 0 | DS96: =IFERROR(VLOOKUP(E96&H96,[1]Group!$D$3:$G$40,4,0),"") | DT96: =J96&I96&DS96 -> Việt PhúSouth
A97: 94 | B97: 5720 | C97: VP005720 | D97: Nguyễn Võ Kiều Oanh | E97: Risk | F97: Collection | G97: Associate | H97: Debt Collection Officer | I97: South | J97: Việt Phú | K97: Full-time | L97: Permanent | M97: 44004 | Q97: LC | R97: LTTP | S97: L | U97: 5000000 | W97: 5000000 | X97: 0 | Y97: 0 | AA97: 0 | AC97: 0 | AD97: 0 | AE97: CN | AF97: 26 | AG97: 22.5 | AH97: 3.5 | AI97: 0 | AJ97: 0 | AK97: 26 | AL97: 0 | AM97: 0 | AN97: 0 | AO97: 0 | AP97: 0 | AQ97: 0 | AR97: 5000000 | AS97: 0 | AT97: 0 | AU97: 5000000 | AV97: 0 | AW97: 0 | AX97: 0 | AY97: 0 | AZ97: 0 | BA97: 0 | BE97: 0 | BF97: 0 | BG97: 0 | BH97: 0 | BI97: 0 | BJ97: 4544940 | BL97: 0 | BO97: 0 | BT97: 4544940 | BU97: 9544940 | BV97: 0 | BW97: 0 | BX97: 0 | BY97: 11000000 | BZ97: 0 | CA97: 0 | CB97: 400000 | CC97: 50000 | CD97: 75000 | CE97: 0 | CF97: 525000 | CG97: 11525000 | CH97: 0 | CI97: 0 | CK97: 0 | CL97: 0 | CM97: 50000 | CN97: 0 | CP97: 128200 | CQ97: 0 | CR97: 178200 | CS97: 8841740 | CU97: 8841740 | CV97: 850000 | CW97: 0 | CX97: 150000 | CY97: 0 | DA97: 1000000 | DB97: 1525000 | DC97: 100000 | DD97: 10644940 | DF97: Việt PhúSouthRisk | DG97: 416666.67 | DH97: HO | DI97: =IFERROR(VLOOKUP($B97,[1]Timesheet!$D:$BK,51,0),0) -> 22 | DJ97: =IFERROR(VLOOKUP($B97,[1]Timesheet!$D:$BK,52,0),0) -> 0 | DK97: =IFERROR(VLOOKUP($B97,[1]Timesheet!$D:$BK,55,0),0) -> 0 | DL97: x | DM97: =IFERROR(VLOOKUP($B97,[1]Timesheet!$D:$BK,57,0),0) -> 0 | DN97: =IF(AND(DL97="x",CB97>0),MIN(ROUND(W97*1%,0),149000),0) -> 50000 | DP97: =IF(E97="Sales",IF(F97="Logistics",F97,IF(F97="Marketing",F97,DH97)),"") | DQ97: 0 | DR97: 0 | DS97: =IFERROR(VLOOKUP(E97&H97,[1]Group!$D$3:$G$40,4,0),"") | DT97: =J97&I97&DS97 -> Việt PhúSouth
A98: 95 | B98: 5722 | C98: VP005722 | D98: Lê Thị Yến Nhi | E98: Risk | F98: Collection | G98: Associate | H98: Debt Collection Officer | I98: South | J98: Việt Phú | K98: Full-time | L98: Permanent | M98: 44004 | Q98: LC | R98: LTTP | S98: L | U98: 5000000 | W98: 5000000 | X98: 0 | Y98: 0 | AA98: 0 | AC98: 0 | AD98: 0 | AE98: CN | AF98: 26 | AG98: 22 | AH98: 4 | AI98: 0 | AJ98: 0 | AK98: 26 | AL98: 0 | AM98: 0 | AN98: 0 | AO98: 0 | AP98: 0 | AQ98: 0 | AR98: 5000000 | AS98: 0 | AT98: 0 | AU98: 5000000 | AV98: 0 | AW98: 0 | AX98: 0 | AY98: 0 | AZ98: 0 | BA98: 0 | BE98: 0 | BF98: 0 | BG98: 0 | BH98: 0 | BI98: 0 | BJ98: 3890425 | BL98: 0 | BO98: 0 | BT98: 3890425 | BU98: 8890425 | BV98: 0 | BW98: 0 | BX98: 0 | BY98: 11000000 | BZ98: 1 | CA98: 4400000 | CB98: 400000 | CC98: 50000 | CD98: 75000 | CE98: 0 | CF98: 525000 | CG98: 15925000 | CH98: 0 | CI98: 0 | CK98: 0 | CL98: 0 | CM98: 50000 | CN98: 0 | CP98: 0 | CQ98: 0 | CR98: 50000 | CS98: 8315425 | CU98: 8315425 | CV98: 850000 | CW98: 0 | CX98: 150000 | CY98: 0 | DA98: 1000000 | DB98: 1525000 | DC98: 100000 | DD98: 9990425 | DF98: Việt PhúSouthRisk | DG98: 416666.67 | DH98: HO | DI98: =IFERROR(VLOOKUP($B98,[1]Timesheet!$D:$BK,51,0),0) -> 22 | DJ98: =IFERROR(VLOOKUP($B98,[1]Timesheet!$D:$BK,52,0),0) -> 0 | DK98: =IFERROR(VLOOKUP($B98,[1]Timesheet!$D:$BK,55,0),0) -> 0 | DL98: x | DM98: =IFERROR(VLOOKUP($B98,[1]Timesheet!$D:$BK,57,0),0) -> 0 | DN98: =IF(AND(DL98="x",CB98>0),MIN(ROUND(W98*1%,0),149000),0) -> 50000 | DP98: =IF(E98="Sales",IF(F98="Logistics",F98,IF(F98="Marketing",F98,DH98)),"") | DQ98: 0 | DR98: 0 | DS98: =IFERROR(VLOOKUP(E98&H98,[1]Group!$D$3:$G$40,4,0),"") | DT98: =J98&I98&DS98 -> Việt PhúSouth
A99: 96 | B99: 5728 | C99: VP005728 | D99: Nguyễn Tấn Hào | E99: Risk | F99: Collection | G99: Associate | H99: Debt Collection Officer | I99: South | J99: Việt Phú | K99: Full-time | L99: Leaving | M99: 44007 | P99: 44560 | Q99: LC | R99: LTTP | S99: L | U99: 5000000 | W99: 5000000 | X99: 0 | Y99: 0 | AA99: 0 | AC99: 0 | AD99: 0 | AE99: CN | AF99: 26 | AG99: 23.5 | AH99: 2.5 | AI99: 0 | AJ99: 0 | AK99: 26 | AL99: 0 | AM99: 0 | AN99: 0 | AO99: 0 | AP99: 0 | AQ99: 0 | AR99: 5000000 | AS99: 0 | AT99: 0 | AU99: 5000000 | AV99: 0 | AW99: 0 | AX99: 0 | AY99: 0 | AZ99: 0 | BA99: 0 | BE99: 0 | BF99: 0 | BG99: 0 | BH99: 0 | BI99: 0 | BJ99: 4081368 | BL99: 0 | BO99: 0 | BT99: 4081368 | BU99: 9081368 | BV99: 0 | BW99: 0 | BX99: 0 | BY99: 11000000 | BZ99: 0 | CA99: 0 | CB99: 400000 | CC99: 50000 | CD99: 75000 | CE99: 0 | CF99: 525000 | CG99: 11525000 | CH99: 0 | CI99: 0 | CK99: 0 | CL99: 0 | CM99: 50000 | CN99: 0 | CP99: 264000 | CQ99: 0 | CR99: 314000 | CS99: 8242368 | CU99: 8242368 | CV99: 850000 | CW99: 0 | CX99: 150000 | CY99: 0 | DA99: 1000000 | DB99: 1525000 | DC99: 100000 | DD99: 10181368 | DF99: Việt PhúSouthRisk | DG99: 416666.67 | DH99: HO | DI99: =IFERROR(VLOOKUP($B99,[1]Timesheet!$D:$BK,51,0),0) -> 22 | DJ99: =IFERROR(VLOOKUP($B99,[1]Timesheet!$D:$BK,52,0),0) -> 0 | DK99: =IFERROR(VLOOKUP($B99,[1]Timesheet!$D:$BK,55,0),0) -> 0 | DL99: x | DM99: =IFERROR(VLOOKUP($B99,[1]Timesheet!$D:$BK,57,0),0) -> 0 | DN99: =IF(AND(DL99="x",CB99>0),MIN(ROUND(W99*1%,0),149000),0) -> 50000 | DP99: =IF(E99="Sales",IF(F99="Logistics",F99,IF(F99="Marketing",F99,DH99)),"") | DQ99: 0 | DR99: 0 | DS99: =IFERROR(VLOOKUP(E99&H99,[1]Group!$D$3:$G$40,4,0),"") | DT99: =J99&I99&DS99 -> Việt PhúSouth
A100: 97 | B100: 5737 | C100: VP005737 | D100: Đặng Xuân Diên | E100: Risk | F100: Collection | G100: Associate | H100: Debt Collection Officer | I100: South | J100: Việt Phú | K100: Full-time | L100: Permanent | M100: 44021 | Q100: LC | R100: LTTP | S100: L | U100: 5000000 | W100: 5000000 | X100: 0 | Y100: 0 | AA100: 0 | AC100: 0 | AD100: 0 | AE100: CN | AF100: 26 | AG100: 24.5 | AH100: 1.5 | AI100: 0 | AJ100: 0 | AK100: 26 | AL100: 0 | AM100: 0 | AN100: 0 | AO100: 0 | AP100: 0 | AQ100: 0 | AR100: 5000000 | AS100: 0 | AT100: 0 | AU100: 5000000 | AV100: 0 | AW100: 0 | AX100: 0 | AY100: 0 | AZ100: 0 | BA100: 0 | BE100: 0 | BF100: 0 | BG100: 0 | BH100: 0 | BI100: 0 | BJ100: 6586563 | BL100: 0 | BO100: 0 | BT100: 6586563 | BU100: 11586563 | BV100: 0 | BW100: 0 | BX100: 0 | BY100: 11000000 | BZ100: 0 | CA100: 0 | CB100: 400000 | CC100: 50000 | CD100: 75000 | CE100: 0 | CF100: 525000 | CG100: 11525000 | CH100: 61563 | CI100: 3078.15 | CK100: 3078.15 | CL100: 0 | CM100: 50000 | CN100: 0 | CP100: 0 | CQ100: 0 | CR100: 50000 | CS100: 11008485 | CU100: 11008485 | CV100: 850000 | CW100: 0 | CX100: 150000 | CY100: 0 | DA100: 1000000 | DB100: 1525000 | DC100: 100000 | DD100: 12686563 | DF100: Việt PhúSouthRisk | DG100: 416666.67 | DH100: HO | DI100: =IFERROR(VLOOKUP($B100,[1]Timesheet!$D:$BK,51,0),0) -> 22 | DJ100: =IFERROR(VLOOKUP($B100,[1]Timesheet!$D:$BK,52,0),0) -> 0 | DK100: =IFERROR(VLOOKUP($B100,[1]Timesheet!$D:$BK,55,0),0) -> 0 | DL100: x | DM100: =IFERROR(VLOOKUP($B100,[1]Timesheet!$D:$BK,57,0),0) -> 0 | DN100: =IF(AND(DL100="x",CB100>0),MIN(ROUND(W100*1%,0),149000),0) -> 50000 | DP100: =IF(E100="Sales",IF(F100="Logistics",F100,IF(F100="Marketing",F100,DH100)),"") | DQ100: 0 | DR100: 0 | DS100: =IFERROR(VLOOKUP(E100&H100,[1]Group!$D$3:$G$40,4,0),"") | DT100: =J100&I100&DS100 -> Việt PhúSouth
...

Sheet FPT
A1: No. | B1: ID | C1: Full Name | D1: Department | E1: Business Unit | F1: Internal Job Band | G1: Current Job Title | H1: Region | I1: Company | J1: Type of Employee | K1: Employment Status | L1: Joining Date | M1: Matenity Leaving Date | N1: Unpaid | O1: Effective Leaving Date | P1: Type of contract | T1: Contract salary | W1: ALLOWANCE | AD1: Time Attendance | AK1: Over times | AQ1: Actual Gross Salary | AT1: Total Actual Gross Salary | AU1: Actual Allowance | BE1: Total Actual Allowance | BF1: INCENTIVE/BONUS | BS1: Total Bonus/ Incentive | BT1: TOTAL INCOME | BU1: Tax relief | CA1: 0.08 | CB1: 0.01 | CC1: 0.015 | CD1: 0.045 | CE1: Total SMU | CF1: Total Tax Relief | CG1: PIT | CK1: Severance Allow Payment/Net adjustments | CL1: Net Deduction | CQ1: Total Net Deduction | CR1: INCOME | CU1: 0.17 | CV1: 0.01 | CW1: 0.03 | CX1: 0 | CY1: 0.045 | CZ1: 21.0% by ER | DA1: 0.315 | DB1: 0.02
P2: JO/ LC/ SC | Q2: TYPE OF PIT | R2: E/L | S2: Count days for Expat | T2: Basic Salary | U2: KPI salary | V2: Total Contract Salary | W2: Laptop | X2: Transportation | Y2: Position | Z2: Phone | AA2: Housing | AB2: Meal Allowance | AC2: Total Allowance | AD2: Standard weekly | AE2: Standard WK Days | AF2: Actual WK Days | AG2: Annual Leave days | AH2: Public Holidays | AI2: Other Paid leave | AJ2: Total Actual WK Days | AK2: Standard Nomal day | AL2: Weekend | AM2: Public Holiday | AN2: Total OT hours | AO2: Total OT hours x rating OT | AP2: Nontaxable - Total OT hous x rating OT | AQ2: Actual Gross Salary | AR2: Other adjustment (+/-) | AS2: OT Payment | AU2: Laptop | AV2: Transportation | AW2: Position | AX2: Phone | AY2: Gasoline | AZ2: Housing | BA2: Training | BB2: Public Holiday | BC2: Special Allowance | BD2: Meal Allowance | BF2: Incentive for FL & TLS | BG2: Bonus for FL & TLS | BH2: Candidate referral bonus | BI2: Debt collection | BJ2: MKT Bonus | BK2: MA/MD Bonus | BL2: Delivery Bonus | BM2: B2B Bonus | BN2: CS Bonus | BO2: Logistics Bonus | BP2: 13th Bonus | BQ2: Bonus paid by region/ Benefit - in -kind or pay out cash | BR2: Engagement Program Bonus | BU2: OT-nontaxable | BV2: Phone | BW2: Meal - Non tax | BX2: Personal Deduction | BY2: No.of Dedendants | BZ2: Deduction of Dependants | CA2: SI | CB2: UI | CC2: HI | CD2: Special case | CG2: Taxed Income | CH2: PIT in month | CI2: PIT Finalization/ Adjusment (-return/+collect) | CJ2: PIT payable | CL2: Trade Union Fee | CM2: Cash advance | CN2: Mobilephone | CO2: MCA Amount | CP2: Other Deduction | CR2: NET INCOME | CS2: PAID | CT2: BANK TRANSFER TO EE (NTH>0) | CU2: SI | CV2: UI | CW2: HI | CX2: ADI | CY2: Special case | CZ2: SI+HI+UI+ADI | DA2: Total SMU | DB2: Trade Union (2%) | DC2: GRAND TOTAL COMPANY COST | DD2: NOTE | DE2: for C&B Report | DF2: 13rd Bonus Budget | DG2: Area | DH2: Group | DI2: for Expense Report (Group) | DJ2: Total WD 1st - 25th | DK2: For SMU | DL2: Total Unpaid Leave for SHUI | DM2: List of union staff | DN2: Laptop | DO2: Trade Union Fee (employee) | DP2: Days of Phone Allowance | DQ2: Area for report (Revenue South) | DR2: Maternity from | DS2: Maternity to
A3: # | B3: 1 | C3: 2 | D3: 3 | E3: =+D3+1 -> 4 | F3: =+E3+1 -> 5 | G3: =+F3+1 -> 6 | H3: =+G3+1 -> 7 | I3: =+H3+1 -> 8 | J3: =+I3+1 -> 9 | K3: =+J3+1 -> 10 | L3: =+K3+1 -> 11 | ... CN3: =+CM3+1 -> 91 | CO3: 92 | CP3: =+CO3+1 -> 93 | CQ3: =+CP3+1 -> 94 | CR3: =+CQ3+1 -> 95 | CS3: =+CR3+1 -> 96 | CT3: =+CS3+1 -> 97 | CU3: =+CT3+1 -> 98 | CV3: =+CU3+1 -> 99 | CW3: =+CV3+1 -> 100 | ... DS3: =+DR3+1 -> 122
A4: 1 | B4: VP006183 | C4: Phạm Kim Ngân | D4: Buy now pay later | E4: BNPL | F4: HOD | G4: Head of Buy now pay later | H4: South | I4: Việt Phú | J4: Full-time | K4: Permanent | L4: 44452 | P4: LC | Q4: LTTP | R4: L | S4: 0 | T4: 80000000 | V4: 80000000 | W4: 0 | X4: 0 | Y4: 0 | Z4: 0 | AA4: 0 | AB4: 0 | AC4: 0 | AD4: TB, CN | AE4: 21 | AF4: 21 | AG4: 0 | AH4: 0 | AI4: 0 | AJ4: 21 | AK4: 0 | AL4: 0 | AM4: 0 | AN4: 0 | AO4: 0 | AP4: 0 | AQ4: 80000000 | AR4: 0 | AS4: 0 | AT4: 80000000 | AU4: 0 | AV4: 0 | AW4: 0 | AX4: 0 | AY4: 0 | AZ4: 0 | BA4: 0 | BB4: 0 | BC4: 0 | BD4: 0 | BE4: 0 | BF4: 0 | BG4: 0 | BH4: 0 | BI4: 0 | BJ4: 0 | BK4: 0 | BL4: 0 | BM4: 0 | BN4: 0 | BO4: 0 | BP4: 0 | BQ4: 0 | BR4: 0 | BS4: 0 | BT4: 80000000 | BU4: 0 | BV4: 0 | BW4: 0 | BX4: 11000000 | BY4: 0 | BZ4: 0 | CA4: 2384000 | CB4: 800000 | CC4: 447000 | CD4: 0 | CE4: 3631000 | CF4: 14631000 | CG4: 65369000 | CH4: 13760700 | CI4: 0 | CJ4: 13760700 | CK4: 0 | CL4: 0 | CM4: 0 | CN4: 0 | CO4: 0 | CP4: 1317000 | CQ4: 1317000 | CR4: 61291300 | CS4: 0 | CT4: 61291300 | CU4: 5066000 | CV4: 0 | CW4: 894000 | CY4: 0 | CZ4: 5960000 | DA4: 9591000 | DB4: 596000 | DC4: 86556000 | DE4: Việt PhúSouthBuy now pay later | DF4: 6666666.7 | DG4: HO | DI4: Việt PhúSouth
A5: 2 | B5: VP006208 | C5: Nguyễn Ngọc Thảo Vy | D5: Buy now pay later | E5: BNPL - Business Dev | F5: Associate | G5: Operation Executive cum Assistant | H5: South | I5: Việt Phú | J5: Full-time | K5: Permanent | L5: 44473 | P5: LC | Q5: LTTP | R5: L | S5: 0 | T5: 5000000 | V5: 5000000 | W5: 0 | X5: 0 | Y5: 0 | Z5: 0 | AA5: 0 | AB5: 0 | AC5: 0 | AD5: TB, CN | AE5: 21 | AF5: 21 | AG5: 0 | AH5: 0 | AI5: 0 | AJ5: 21 | AK5: 0 | AL5: 0 | AM5: 0 | AN5: 0 | AO5: 0 | AP5: 0 | AQ5: 5000000 | AR5: 0 | AS5: 0 | AT5: 5000000 | AU5: 0 | AV5: 0 | AW5: 0 | AX5: 0 | AY5: 0 | AZ5: 0 | BA5: 0 | BB5: 0 | BC5: 0 | BD5: 0 | BE5: 0 | BF5: 0 | BG5: 0 | BH5: 0 | BI5: 0 | BJ5: 0 | BK5: 0 | BL5: 0 | BM5: 0 | BN5: 0 | BO5: 0 | BP5: 0 | BQ5: 0 | BR5: 0 | BS5: 0 | BT5: 5000000 | BU5: 0 | BV5: 0 | BW5: 0 | BX5: 11000000 | BY5: 0 | BZ5: 0 | CA5: 400000 | CB5: 50000 | CC5: 75000 | CD5: 0 | CE5: 525000 | CF5: 11525000 | CG5: 0 | CH5: 0 | CI5: 0 | CJ5: 0 | CK5: 0 | CL5: 0 | CM5: 0 | CN5: 0 | CO5: 0 | CP5: 0 | CQ5: 0 | CR5: 4475000 | CS5: 0 | CT5: 4475000 | CU5: 850000 | CV5: 0 | CW5: 150000 | CY5: 0 | CZ5: 1000000 | DA5: 1525000 | DB5: 100000 | DC5: 6100000 | DE5: Việt PhúSouthBuy now pay later | DF5: 416666.67 | DG5: HO | DI5: Việt PhúSouth
A6: 3 | B6: VP006201 | C6: Vũ Thị Mỹ Ngọc | D6: Buy now pay later | E6: BNPL - Business Dev | F6: Manager | G6: Buy now pay later Business Development Manager | H6: South | I6: Việt Phú | J6: Full-time | K6: Permanent | L6: 44455 | P6: LC | Q6: LTTP | R6: L | S6: 0 | T6: 40000000 | V6: 40000000 | W6: 0 | X6: 0 | Y6: 0 | Z6: 0 | AA6: 0 | AB6: 0 | AC6: 0 | AD6: TB, CN | AE6: 21 | AF6: 20 | AG6: 1 | AH6: 0 | AI6: 0 | AJ6: 21 | AK6: 0 | AL6: 0 | AM6: 0 | AN6: 0 | AO6: 0 | AP6: 0 | AQ6: 40000000 | AR6: 0 | AS6: 0 | AT6: 40000000 | AU6: 0 | AV6: 0 | AW6: 0 | AX6: 0 | AY6: 0 | AZ6: 0 | BA6: 0 | BB6: 0 | BC6: 0 | BD6: 0 | BE6: 0 | BF6: 0 | BG6: 0 | BH6: 0 | BI6: 0 | BJ6: 0 | BK6: 0 | BL6: 0 | BM6: 0 | BN6: 0 | BO6: 0 | BP6: 0 | BQ6: 0 | BR6: 0 | BS6: 0 | BT6: 40000000 | BU6: 0 | BV6: 0 | BW6: 0 | BX6: 11000000 | BY6: 0 | BZ6: 0 | CA6: 2384000 | CB6: 400000 | CC6: 447000 | CD6: 0 | CE6: 3231000 | CF6: 14231000 | CG6: 25769000 | CH6: 3503800 | CI6: 0 | CJ6: 3503800 | CK6: 0 | CL6: 0 | CM6: 0 | CN6: 0 | CO6: 0 | CP6: 0 | CQ6: 0 | CR6: 33265200 | CS6: 0 | CT6: 33265200 | CU6: 5066000 | CV6: 0 | CW6: 894000 | CY6: 0 | CZ6: 5960000 | DA6: 9191000 | DB6: 596000 | DC6: 46556000 | DE6: Việt PhúSouthBuy now pay later | DF6: 3333333.3 | DG6: HO | DI6: Việt PhúSouth
A7: 4 | B7: admin.fpt | C7: Admin FPT | D7: Buy now pay later | E7: BNPL - Business Dev | F7: Assistant Manager | G7: Technology Lead | I7: Việt Phú | J7: Full-time | K7: Permanent | L7: 44197 | P7: LC | Q7: LTTP | R7: L | S7: 0 | T7: 1000000 | V7: 1000000 | W7: 0 | X7: 0 | Y7: 0 | Z7: 0 | AA7: 0 | AB7: 0 | AC7: 0 | AD7: CN | AE7: 26 | AF7: 26 | AG7: 0 | AH7: 0 | AI7: 0 | AJ7: 26 | AK7: 0 | AL7: 0 | AM7: 0 | AN7: 0 | AO7: 0 | AP7: 0 | AQ7: 1000000 | AR7: 0 | AS7: 0 | AT7: 1000000 | AU7: 0 | AV7: 0 | AW7: 0 | AX7: 0 | AY7: 0 | AZ7: 0 | BA7: 0 | BB7: 0 | BC7: 0 | BD7: 0 | BE7: 0 | BF7: 0 | BG7: 0 | BH7: 0 | BI7: 0 | BJ7: 0 | BK7: 0 | BL7: 0 | BM7: 0 | BN7: 0 | BO7: 0 | BP7: 0 | BQ7: 0 | BR7: 0 | BS7: 0 | BT7: 1000000 | BU7: 0 | BV7: 0 | BW7: 0 | BX7: 11000000 | BY7: 0 | BZ7: 0 | CA7: 400000 | CB7: 50000 | CC7: 75000 | CD7: 0 | CE7: 525000 | CF7: 11525000 | CG7: 0 | CH7: 0 | CI7: 0 | CJ7: 0 | CK7: 0 | CL7: 50000 | CM7: 0 | CN7: 0 | CO7: 0 | CP7: 0 | CQ7: 50000 | CR7: 425000 | CS7: 0 | CT7: 425000 | CU7: 850000 | CV7: 0 | CW7: 150000 | CY7: 0 | CZ7: 1000000 | DA7: 1525000 | DB7: 100000 | DC7: 2100000 | DF7: 83333.333
A8: 5 | B8: VP006205 | C8: Trần Bá Ca | D8: Buy now pay later | E8: BNPL - Marketing | F8: Senior Associate | G8: Senior Graphic Designer | H8: South | I8: Việt Phú | J8: Full-time | K8: Permanent | L8: 44473 | P8: LC | Q8: LTTP | R8: L | S8: 0 | T8: 10000000 | V8: 10000000 | W8: 0 | X8: 0 | Y8: 0 | Z8: 0 | AA8: 0 | AB8: 0 | AC8: 0 | AD8: TB, CN | AE8: 21 | AF8: 21 | AG8: 0 | AH8: 0 | AI8: 0 | AJ8: 21 | AK8: 0 | AL8: 0 | AM8: 0 | AN8: 0 | AO8: 0 | AP8: 0 | AQ8: 10000000 | AR8: 0 | AS8: 0 | AT8: 10000000 | AU8: 0 | AV8: 0 | AW8: 0 | AX8: 0 | AY8: 0 | AZ8: 0 | BA8: 0 | BB8: 0 | BC8: 0 | BD8: 0 | BE8: 0 | BF8: 0 | BG8: 0 | BH8: 0 | BI8: 0 | BJ8: 0 | BK8: 0 | BL8: 0 | BM8: 0 | BN8: 0 | BO8: 0 | BP8: 0 | BQ8: 0 | BR8: 0 | BS8: 0 | BT8: 10000000 | BU8: 0 | BV8: 0 | BW8: 0 | BX8: 11000000 | BY8: 0 | BZ8: 0 | CA8: 800000 | CB8: 100000 | CC8: 150000 | CD8: 0 | CE8: 1050000 | CF8: 12050000 | CG8: 0 | CH8: 0 | CI8: 0 | CJ8: 0 | CK8: 0 | CL8: 0 | CM8: 0 | CN8: 0 | CO8: 0 | CP8: 0 | CQ8: 0 | CR8: 8950000 | CS8: 0 | CT8: 8950000 | CU8: 1700000 | CV8: 0 | CW8: 300000 | CY8: 0 | CZ8: 2000000 | DA8: 3050000 | DB8: 200000 | DC8: 12200000 | DE8: Việt PhúSouthBuy now pay later | DF8: 833333.33 | DG8: HO | DI8: Việt PhúSouth
A9: 6 | B9: VP006177 | C9: Trịnh Nguyên Giang | D9: Buy now pay later | E9: BNPL - Product | F9: Manager | G9: Buy now pay later Product Manager | H9: South | I9: Việt Phú | J9: Full-time | K9: Permanent | L9: 44455 | P9: LC | Q9: LTTP | R9: L | S9: 0 | T9: 40000000 | V9: 40000000 | W9: 0 | X9: 0 | Y9: 0 | Z9: 0 | AA9: 0 | AB9: 0 | AC9: 0 | AD9: TB, CN | AE9: 21 | AF9: 21 | AG9: 0 | AH9: 0 | AI9: 0 | AJ9: 21 | AK9: 0 | AL9: 0 | AM9: 0 | AN9: 0 | AO9: 0 | AP9: 0 | AQ9: 40000000 | AR9: 0 | AS9: 0 | AT9: 40000000 | AU9: 0 | AV9: 0 | AW9: 0 | AX9: 0 | AY9: 0 | AZ9: 0 | BA9: 0 | BB9: 0 | BC9: 0 | BD9: 0 | BE9: 0 | BF9: 0 | BG9: 0 | BH9: 0 | BI9: 0 | BJ9: 0 | BK9: 0 | BL9: 0 | BM9: 0 | BN9: 0 | BO9: 0 | BP9: 0 | BQ9: 0 | BR9: 0 | BS9: 0 | BT9: 40000000 | BU9: 0 | BV9: 0 | BW9: 0 | BX9: 11000000 | BY9: 0 | BZ9: 0 | CA9: 2384000 | CB9: 400000 | CC9: 447000 | CD9: 0 | CE9: 3231000 | CF9: 14231000 | CG9: 25769000 | CH9: 3503800 | CI9: 0 | CJ9: 3503800 | CK9: 0 | CL9: 0 | CM9: 0 | CN9: 0 | CO9: 0 | CP9: 0 | CQ9: 0 | CR9: 33265200 | CS9: 0 | CT9: 33265200 | CU9: 5066000 | CV9: 0 | CW9: 894000 | CY9: 0 | CZ9: 5960000 | DA9: 9191000 | DB9: 596000 | DC9: 46556000 | DE9: Việt PhúSouthBuy now pay later | DF9: 3333333.3 | DG9: HO | DI9: Việt PhúSouth
A10: 7 | B10: VP006202 | C10: Ngô Ngọc Trâm | D10: Buy now pay later | E10: BNPL - Product | F10: Senior Associate | G10: Senior UX/UI Designer | H10: South | I10: Việt Phú | J10: Full-time | K10: Permanent | L10: 44455 | P10: LC | Q10: LTTP | R10: L | S10: 0 | T10: 10000000 | V10: 10000000 | W10: 0 | X10: 0 | Y10: 0 | Z10: 0 | AA10: 0 | AB10: 0 | AC10: 0 | AD10: TB, CN | AE10: 21 | AF10: 21 | AG10: 0 | AH10: 0 | AI10: 0 | AJ10: 21 | AK10: 0 | AL10: 0 | AM10: 0 | AN10: 0 | AO10: 0 | AP10: 0 | AQ10: 10000000 | AR10: 0 | AS10: 0 | AT10: 10000000 | AU10: 0 | AV10: 0 | AW10: 0 | AX10: 0 | AY10: 0 | AZ10: 0 | BA10: 0 | BB10: 0 | BC10: 0 | BD10: 0 | BE10: 0 | BF10: 0 | BG10: 0 | BH10: 0 | BI10: 0 | BJ10: 0 | BK10: 0 | BL10: 0 | BM10: 0 | BN10: 0 | BO10: 0 | BP10: 0 | BQ10: 0 | BR10: 0 | BS10: 0 | BT10: 10000000 | BU10: 0 | BV10: 0 | BW10: 0 | BX10: 11000000 | BY10: 0 | BZ10: 0 | CA10: 800000 | CB10: 100000 | CC10: 150000 | CD10: 0 | CE10: 1050000 | CF10: 12050000 | CG10: 0 | CH10: 0 | CI10: 0 | CJ10: 0 | CK10: 0 | CL10: 0 | CM10: 0 | CN10: 0 | CO10: 0 | CP10: 0 | CQ10: 0 | CR10: 8950000 | CS10: 0 | CT10: 8950000 | CU10: 1700000 | CV10: 0 | CW10: 300000 | CY10: 0 | CZ10: 2000000 | DA10: 3050000 | DB10: 200000 | DC10: 12200000 | DE10: Việt PhúSouthBuy now pay later | DF10: 833333.33 | DG10: HO | DI10: Việt PhúSouth
A11: 8 | B11: VP006206 | C11: Nguyễn Đình Khánh Nguyên | D11: Buy now pay later | E11: BNPL - Tech Dev | F11: Assistant Manager | G11: Assistant Manager, Full -Stack | H11: South | I11: Việt Phú | J11: Full-time | K11: Permanent | L11: 44495 | Q11: 10% | R11: L | S11: 0 | T11: 30000000 | V11: 30000000 | W11: 0 | X11: 0 | Y11: 0 | Z11: 0 | AA11: 0 | AB11: 0 | AC11: 0 | AD11: TB, CN | AE11: 21 | AF11: 21 | AG11: 0 | AH11: 0 | AI11: 0 | AJ11: 21 | AK11: 0 | AL11: 0 | AM11: 0 | AN11: 0 | AO11: 0 | AP11: 0 | AQ11: 30000000 | AR11: 0 | AS11: 0 | AT11: 30000000 | AU11: 0 | AV11: 0 | AW11: 0 | AX11: 0 | AY11: 0 | AZ11: 0 | BA11: 0 | BB11: 0 | BC11: 0 | BD11: 0 | BE11: 0 | BF11: 0 | BG11: 0 | BH11: 0 | BI11: 0 | BJ11: 0 | BK11: 0 | BL11: 0 | BM11: 0 | BN11: 0 | BO11: 0 | BP11: 0 | BQ11: 0 | BR11: 0 | BS11: 0 | BT11: 30000000 | BU11: 0 | BV11: 0 | BW11: 0 | BX11: 0 | BY11: 0 | BZ11: 0 | CA11: 0 | CB11: 0 | CC11: 0 | CD11: 0 | CE11: 0 | CF11: 0 | CG11: 30000000 | CH11: 3000000 | CI11: 0 | CJ11: 3000000 | CK11: 0 | CL11: 0 | CM11: 0 | CN11: 0 | CO11: 0 | CP11: 0 | CQ11: 0 | CR11: 27000000 | CS11: 0 | CT11: 27000000 | CU11: 0 | CV11: 0 | CW11: 0 | CY11: 0 | CZ11: 0 | DA11: 0 | DB11: 0 | DC11: 30000000 | DE11: Việt PhúSouthBuy now pay later | DF11: 2500000 | DG11: HO | DI11: Việt PhúSouth
A12: 9 | B12: VP006178 | C12: Lâm Thị Phượng | D12: Buy now pay later | E12: BNPL - Tech Dev | F12: Team leader | G12: QA Team Leader | H12: South | I12: Việt Phú | J12: Full-time | K12: Leaving | L12: 44491 | O12: 44541 | P12: JO | Q12: 10% | R12: L | S12: 0 | T12: 15000000 | V12: 15000000 | W12: 0 | X12: 0 | Y12: 0 | Z12: 0 | AA12: 0 | AB12: 0 | AC12: 0 | AD12: TB, CN | AE12: 21 | AF12: 11 | AG12: 0 | AH12: 0 | AI12: 0 | AJ12: 11 | AK12: 0 | AL12: 0 | AM12: 0 | AN12: 0 | AO12: 0 | AP12: 0 | AQ12: 7857142.9 | AR12: 0 | AS12: 0 | AT12: 7857142.9 | AU12: 0 | AV12: 0 | AW12: 0 | AX12: 0 | AY12: 0 | AZ12: 0 | BA12: 0 | BB12: 0 | BC12: 0 | BD12: 0 | BE12: 0 | BF12: 0 | BG12: 0 | BH12: 0 | BI12: 0 | BJ12: 0 | BK12: 0 | BL12: 0 | BM12: 0 | BN12: 0 | BO12: 0 | BP12: 0 | BQ12: 0 | BR12: 0 | BS12: 0 | BT12: 7857142.9 | BU12: 0 | BV12: 0 | BW12: 0 | BX12: 0 | BY12: 0 | BZ12: 0 | CA12: 0 | CB12: 0 | CC12: 0 | CD12: 0 | CE12: 0 | CF12: 0 | CG12: 7857142.9 | CH12: 785714.29 | CI12: 0 | CJ12: 785714.29 | CK12: 0 | CL12: 0 | CM12: 0 | CN12: 0 | CO12: 0 | CP12: 0 | CQ12: 0 | CR12: 7071429 | CS12: 0 | CT12: 7071429 | CU12: 0 | CV12: 0 | CW12: 0 | CY12: 0 | CZ12: 0 | DA12: 0 | DB12: 0 | DC12: 7857143 | DE12: Việt PhúSouthBuy now pay later | DF12: 1250000 | DG12: HO | DI12: Việt PhúSouth
A13: 10 | B13: VP006204 | C13: Tô Thành Thương | D13: Buy now pay later | E13: BNPL - Tech Dev | F13: Team leader | G13: Front - end Team Leader | H13: South | I13: Việt Phú | J13: Full-time | K13: Permanent | L13: 44473 | P13: LC | Q13: LTTP | R13: L | S13: 0 | T13: 15000000 | V13: 15000000 | W13: 0 | X13: 0 | Y13: 0 | Z13: 0 | AA13: 0 | AB13: 0 | AC13: 0 | AD13: TB, CN | AE13: 21 | AF13: 21 | AG13: 0 | AH13: 0 | AI13: 0 | AJ13: 21 | AK13: 0 | AL13: 0 | AM13: 0 | AN13: 0 | AO13: 0 | AP13: 0 | AQ13: 15000000 | AR13: 0 | AS13: 0 | AT13: 15000000 | AU13: 0 | AV13: 0 | AW13: 0 | AX13: 0 | AY13: 0 | AZ13: 0 | BA13: 0 | BB13: 0 | BC13: 0 | BD13: 0 | BE13: 0 | BF13: 0 | BG13: 0 | BH13: 0 | BI13: 0 | BJ13: 0 | BK13: 0 | BL13: 0 | BM13: 0 | BN13: 0 | BO13: 0 | BP13: 0 | BQ13: 0 | BR13: 0 | BS13: 0 | BT13: 15000000 | BU13: 0 | BV13: 0 | BW13: 0 | BX13: 11000000 | BY13: 0 | BZ13: 0 | CA13: 1200000 | CB13: 150000 | CC13: 225000 | CD13: 0 | CE13: 1575000 | CF13: 12575000 | CG13: 2425000 | CH13: 121250 | CI13: 0 | CJ13: 121250 | CK13: 0 | CL13: 0 | CM13: 0 | CN13: 0 | CO13: 0 | CP13: 0 | CQ13: 0 | CR13: 13303750 | CS13: 0 | CT13: 13303750 | CU13: 2550000 | CV13: 0 | CW13: 450000 | CY13: 0 | CZ13: 3000000 | DA13: 4575000 | DB13: 300000 | DC13: 18300000 | DE13: Việt PhúSouthBuy now pay later | DF13: 1250000 | DG13: HO | DI13: Việt PhúSouth
A14: 11 | B14: VP006179 | C14: Đặng Hoàng Nguyên | D14: Buy now pay later | E14: BNPL - Tech Dev | F14: Senior Associate | G14: Senior Wordpress Development Executive | H14: South | I14: Việt Phú | J14: Full-time | K14: Leaving | L14: 44455 | O14: 44544 | P14: LC | Q14: LTTP | R14: L | S14: 0 | T14: 10000000 | V14: 10000000 | W14: 0 | X14: 0 | Y14: 0 | Z14: 0 | AA14: 0 | AB14: 0 | AC14: 0 | AD14: TB, CN | AE14: 21 | AF14: 12 | AG14: 0 | AH14: 0 | AI14: 0 | AJ14: 12 | AK14: 0 | AL14: 0 | AM14: 0 | AN14: 0 | AO14: 0 | AP14: 0 | AQ14: 5714285.7 | AR14: 2553905 | AS14: 0 | AT14: 8268190.7 | AU14: 0 | AV14: 0 | AW14: 0 | AX14: 0 | AY14: 0 | AZ14: 0 | BA14: 0 | BB14: 0 | BC14: 0 | BD14: 0 | BE14: 0 | BF14: 0 | BG14: 0 | BH14: 0 | BI14: 0 | BJ14: 0 | BK14: 0 | BL14: 0 | BM14: 0 | BN14: 0 | BO14: 0 | BP14: 0 | BQ14: 0 | BR14: 0 | BS14: 0 | BT14: 8268190.7 | BU14: 0 | BV14: 0 | BW14: 0 | BX14: 11000000 | BY14: 0 | BZ14: 0 | CA14: 0 | CB14: 0 | CC14: 0 | CD14: 1206720 | CE14: 1206720 | CF14: 12206720 | CG14: 0 | CH14: 0 | CI14: 0 | CJ14: 0 | CK14: 0 | CL14: 0 | CM14: 0 | CN14: 0 | CO14: 0 | CP14: 0 | CQ14: 0 | CR14: 7061471 | CS14: 0 | CT14: 7061471 | CU14: 0 | CV14: 0 | CW14: 0 | CY14: 0 | CZ14: 0 | DA14: 1206720 | DB14: 0 | DC14: 8268191 | DE14: Việt PhúSouthBuy now pay later | DF14: 833333.33 | DG14: HO | DI14: Việt PhúSouth
A15: 12 | B15: VP001464 | C15: Lê Thị Cẩm Nhung | D15: Finance | E15: Funding | F15: Senior Associate | G15: Funding - Banking Relationship | H15: South | I15: Việt Phú | J15: Full-time | K15: Permanent | L15: 41680 | P15: LC | Q15: LTTP | R15: L | S15: 0 | T15: 10000000 | V15: 10000000 | W15: 0 | X15: 0 | Y15: 0 | Z15: 0 | AA15: 0 | AB15: 0 | AC15: 0 | AD15: TB, CN | AE15: 21 | AF15: 21 | AG15: 0 | AH15: 0 | AI15: 0 | AJ15: 21 | AK15: 0 | AL15: 0 | AM15: 0 | AN15: 0 | AO15: 0 | AP15: 0 | AQ15: 10000000 | AR15: 0 | AS15: 0 | AT15: 10000000 | AU15: 0 | AV15: 0 | AW15: 0 | AX15: 0 | AY15: 0 | AZ15: 0 | BA15: 0 | BB15: 0 | BC15: 0 | BD15: 0 | BE15: 0 | BF15: 0 | BG15: 0 | BH15: 0 | BI15: 0 | BJ15: 0 | BK15: 0 | BL15: 0 | BM15: 0 | BN15: 0 | BO15: 0 | BP15: 0 | BQ15: 0 | BR15: 0 | BS15: 0 | BT15: 10000000 | BU15: 0 | BV15: 0 | BW15: 0 | BX15: 11000000 | BY15: 1 | BZ15: 4400000 | CA15: 800000 | CB15: 100000 | CC15: 150000 | CD15: 0 | CE15: 1050000 | CF15: 16450000 | CG15: 0 | CH15: 0 | CI15: 0 | CJ15: 0 | CK15: 0 | CL15: 100000 | CM15: 0 | CN15: 0 | CO15: 174000 | CP15: 0 | CQ15: 274000 | CR15: 8676000 | CS15: 0 | CT15: 8676000 | CU15: 1700000 | CV15: 0 | CW15: 300000 | CY15: 0 | CZ15: 2000000 | DA15: 3050000 | DB15: 200000 | DC15: 12200000 | DE15: Việt PhúSouthFinance | DF15: 833333.33 | DG15: HO | DI15: Việt PhúSouth
A16: 13 | B16: VP006176 | C16: Nguyễn Hải Hà | D16: Finance | E16: Planning & Analysis | F16: Associate | G16: Finance Analyst | H16: South | I16: Việt Phú | J16: Full-time | K16: Permanent | L16: 44382 | P16: LC | Q16: LTTP | R16: L | S16: 0 | T16: 5000000 | V16: 5000000 | W16: 0 | X16: 0 | Y16: 0 | Z16: 0 | AA16: 0 | AB16: 0 | AC16: 0 | AD16: TB, CN | AE16: 21 | AF16: 21 | AG16: 0 | AH16: 0 | AI16: 0 | AJ16: 21 | AK16: 0 | AL16: 0 | AM16: 0 | AN16: 0 | AO16: 0 | AP16: 0 | AQ16: 5000000 | AR16: 0 | AS16: 0 | AT16: 5000000 | AU16: 0 | AV16: 0 | AW16: 0 | AX16: 0 | AY16: 0 | AZ16: 0 | BA16: 0 | BB16: 0 | BC16: 0 | BD16: 0 | BE16: 0 | BF16: 0 | BG16: 0 | BH16: 0 | BI16: 0 | BJ16: 0 | BK16: 0 | BL16: 0 | BM16: 0 | BN16: 0 | BO16: 0 | BP16: 0 | BQ16: 0 | BR16: 0 | BS16: 0 | BT16: 5000000 | BU16: 0 | BV16: 0 | BW16: 0 | BX16: 11000000 | BY16: 0 | BZ16: 0 | CA16: 400000 | CB16: 50000 | CC16: 75000 | CD16: 0 | CE16: 525000 | CF16: 11525000 | CG16: 0 | CH16: 0 | CI16: 0 | CJ16: 0 | CK16: 0 | CL16: 0 | CM16: 0 | CN16: 0 | CO16: 0 | CP16: 0 | CQ16: 0 | CR16: 4475000 | CS16: 0 | CT16: 4475000 | CU16: 850000 | CV16: 0 | CW16: 150000 | CY16: 0 | CZ16: 1000000 | DA16: 1525000 | DB16: 100000 | DC16: 6100000 | DE16: Việt PhúSouthFinance | DF16: 416666.67 | DG16: HO | DI16: Việt PhúSouth
A17: 14 | B17: VP004767 | C17: Hoàng Thị Minh Châu | D17: Finance | E17: Planning & Analysis | F17: HOD | G17: Head of Finance | H17: South | I17: Việt Phú | J17: Full-time | K17: Maternity | L17: 43314 | M17: 15/09/2021 - 14/03/2022 | P17: LC | Q17: LTTP | R17: L | S17: 0 | T17: 80000000 | V17: 80000000 | W17: 0 | X17: 0 | Y17: 0 | Z17: 0 | AA17: 0 | AB17: 0 | AC17: 0 | AD17: TB, CN | AE17: 21 | AF17: 0 | AG17: 0 | AH17: 0 | AI17: 0 | AJ17: 0 | AK17: 0 | AL17: 0 | AM17: 0 | AN17: 0 | AO17: 0 | AP17: 0 | AQ17: 0 | AR17: 0 | AS17: 0 | AT17: 0 | AU17: 0 | AV17: 0 | AW17: 0 | AX17: 0 | AY17: 0 | AZ17: 0 | BA17: 0 | BB17: 0 | BC17: 0 | BD17: 0 | BE17: 0 | BF17: 0 | BG17: 0 | BH17: 0 | BI17: 0 | BJ17: 0 | BK17: 0 | BL17: 0 | BM17: 0 | BN17: 0 | BO17: 0 | BP17: 0 | BQ17: 0 | BR17: 0 | BS17: 0 | BT17: 0 | BU17: 0 | BV17: 0 | BW17: 0 | BX17: 11000000 | BY17: 0 | BZ17: 0 | CA17: 0 | CB17: 0 | CC17: 0 | CD17: 0 | CE17: 0 | CF17: 11000000 | CG17: 0 | CH17: 0 | CI17: 0 | CJ17: 0 | CK17: 0 | CL17: 0 | CM17: 0 | CN17: 0 | CO17: 0 | CP17: 0 | CQ17: 0 | CR17: 0 | CS17: 0 | CT17: 0 | CU17: 0 | CV17: 0 | CW17: 0 | CY17: 0 | CZ17: 0 | DA17: 0 | DB17: 0 | DC17: 0 | DE17: Việt PhúSouthFinance | DF17: 6666666.7 | DG17: HO | DI17: Việt PhúSouth
A18: 15 | B18: VP005456 | C18: Nguyễn Thị Hồng Đào | D18: Finance | E18: Accounting & Tax | F18: Associate | G18: Accounting Officer | H18: South | I18: Việt Phú | J18: Full-time | K18: Permanent | L18: 43759 | P18: LC | Q18: LTTP | R18: L | S18: 0 | T18: 5000000 | V18: 5000000 | W18: 0 | X18: 0 | Y18: 0 | Z18: 0 | AA18: 0 | AB18: 0 | AC18: 0 | AD18: TB, CN | AE18: 21 | AF18: 21 | AG18: 0 | AH18: 0 | AI18: 0 | AJ18: 21 | AK18: 0 | AL18: 0 | AM18: 0 | AN18: 0 | AO18: 0 | AP18: 0 | AQ18: 5000000 | AR18: 0 | AS18: 0 | AT18: 5000000 | AU18: 0 | AV18: 0 | AW18: 0 | AX18: 0 | AY18: 0 | AZ18: 0 | BA18: 0 | BB18: 0 | BC18: 0 | BD18: 0 | BE18: 0 | BF18: 0 | BG18: 0 | BH18: 0 | BI18: 0 | BJ18: 0 | BK18: 0 | BL18: 0 | BM18: 0 | BN18: 0 | BO18: 0 | BP18: 0 | BQ18: 0 | BR18: 0 | BS18: 0 | BT18: 5000000 | BU18: 0 | BV18: 0 | BW18: 0 | BX18: 11000000 | BY18: 0 | BZ18: 0 | CA18: 400000 | CB18: 50000 | CC18: 75000 | CD18: 0 | CE18: 525000 | CF18: 11525000 | CG18: 0 | CH18: 0 | CI18: 0 | CJ18: 0 | CK18: 0 | CL18: 0 | CM18: 0 | CN18: 0 | CO18: 0 | CP18: 0 | CQ18: 0 | CR18: 4475000 | CS18: 0 | CT18: 4475000 | CU18: 850000 | CV18: 0 | CW18: 150000 | CY18: 0 | CZ18: 1000000 | DA18: 1525000 | DB18: 100000 | DC18: 6100000 | DE18: Việt PhúSouthFinance | DF18: 416666.67 | DG18: HO | DI18: Việt PhúSouth
A19: 16 | B19: VP005031 | C19: Trần Quốc Huy | D19: Finance | E19: Accounting & Tax | F19: Manager | G19: Chief Accountant | H19: South | I19: Việt Phú | J19: Full-time | K19: Permanent | L19: 43591 | P19: LC | Q19: LTTP | R19: L | S19: 0 | T19: 40000000 | V19: 40000000 | W19: 0 | X19: 0 | Y19: 0 | Z19: 0 | AA19: 0 | AB19: 0 | AC19: 0 | AD19: TB, CN | AE19: 21 | AF19: 21 | AG19: 0 | AH19: 0 | AI19: 0 | AJ19: 21 | AK19: 0 | AL19: 0 | AM19: 0 | AN19: 0 | AO19: 0 | AP19: 0 | AQ19: 40000000 | AR19: 0 | AS19: 0 | AT19: 40000000 | AU19: 0 | AV19: 0 | AW19: 0 | AX19: 0 | AY19: 0 | AZ19: 0 | BA19: 0 | BB19: 0 | BC19: 0 | BD19: 0 | BE19: 0 | BF19: 0 | BG19: 0 | BH19: 0 | BI19: 0 | BJ19: 0 | BK19: 0 | BL19: 0 | BM19: 0 | BN19: 0 | BO19: 0 | BP19: 0 | BQ19: 0 | BR19: 0 | BS19: 0 | BT19: 40000000 | BU19: 0 | BV19: 0 | BW19: 0 | BX19: 11000000 | BY19: 2 | BZ19: 8800000 | CA19: 2384000 | CB19: 400000 | CC19: 447000 | CD19: 0 | CE19: 3231000 | CF19: 23031000 | CG19: 16969000 | CH19: 1795350 | CI19: 0 | CJ19: 1795350 | CK19: 0 | CL19: 0 | CM19: 0 | CN19: 0 | CO19: 0 | CP19: 0 | CQ19: 0 | CR19: 34973650 | CS19: 0 | CT19: 34973650 | CU19: 5066000 | CV19: 0 | CW19: 894000 | CY19: 0 | CZ19: 5960000 | DA19: 9191000 | DB19: 596000 | DC19: 46556000 | DE19: Việt PhúSouthFinance | DF19: 3333333.3 | DG19: HO | DI19: Việt PhúSouth
A20: 17 | B20: VP002210 | C20: Dương Thị Kim Phố | D20: Finance | E20: Accounting & Tax | F20: Senior Associate | G20: General Accountant | H20: South | I20: Việt Phú | J20: Full-time | K20: Permanent | L20: 41939 | P20: LC | Q20: LTTP | R20: L | S20: 0 | T20: 10000000 | V20: 10000000 | W20: 0 | X20: 0 | Y20: 0 | Z20: 0 | AA20: 0 | AB20: 0 | AC20: 0 | AD20: TB, CN | AE20: 21 | AF20: 21 | AG20: 0 | AH20: 0 | AI20: 0 | AJ20: 21 | AK20: 0 | AL20: 0 | AM20: 0 | AN20: 0 | AO20: 0 | AP20: 0 | AQ20: 10000000 | AR20: 0 | AS20: 0 | AT20: 10000000 | AU20: 0 | AV20: 0 | AW20: 0 | AX20: 0 | AY20: 0 | AZ20: 0 | BA20: 0 | BB20: 0 | BC20: 0 | BD20: 0 | BE20: 0 | BF20: 0 | BG20: 0 | BH20: 0 | BI20: 0 | BJ20: 0 | BK20: 0 | BL20: 0 | BM20: 0 | BN20: 0 | BO20: 0 | BP20: 0 | BQ20: 0 | BR20: 0 | BS20: 0 | BT20: 10000000 | BU20: 0 | BV20: 0 | BW20: 0 | BX20: 11000000 | BY20: 2 | BZ20: 8800000 | CA20: 800000 | CB20: 100000 | CC20: 150000 | CD20: 0 | CE20: 1050000 | CF20: 20850000 | CG20: 0 | CH20: 0 | CI20: 0 | CJ20: 0 | CK20: 0 | CL20: 100000 | CM20: 0 | CN20: 0 | CO20: 310000 | CP20: 0 | CQ20: 410000 | CR20: 8540000 | CS20: 0 | CT20: 8540000 | CU20: 1700000 | CV20: 0 | CW20: 300000 | CY20: 0 | CZ20: 2000000 | DA20: 3050000 | DB20: 200000 | DC20: 12200000 | DE20: Việt PhúSouthFinance | DF20: 833333.33 | DG20: HO | DI20: Việt PhúSouth
A21: 18 | B21: VP005162 | C21: Lưu Nguyễn Phương Uyên | D21: Finance | E21: Accounting & Tax | F21: Senior Associate | G21: General Accountant | H21: South | I21: Việt Phú | J21: Full-time | K21: Permanent | L21: 43668 | P21: LC | Q21: LTTP | R21: L | S21: 0 | T21: 10000000 | V21: 10000000 | W21: 0 | X21: 0 | Y21: 0 | Z21: 0 | AA21: 0 | AB21: 0 | AC21: 0 | AD21: TB, CN | AE21: 21 | AF21: 21 | AG21: 0 | AH21: 0 | AI21: 0 | AJ21: 21 | AK21: 0 | AL21: 0 | AM21: 0 | AN21: 0 | AO21: 0 | AP21: 0 | AQ21: 10000000 | AR21: 0 | AS21: 0 | AT21: 10000000 | AU21: 0 | AV21: 0 | AW21: 0 | AX21: 0 | AY21: 0 | AZ21: 0 | BA21: 0 | BB21: 0 | BC21: 0 | BD21: 0 | BE21: 0 | BF21: 0 | BG21: 0 | BH21: 0 | BI21: 0 | BJ21: 0 | BK21: 0 | BL21: 0 | BM21: 0 | BN21: 0 | BO21: 0 | BP21: 0 | BQ21: 0 | BR21: 0 | BS21: 0 | BT21: 10000000 | BU21: 0 | BV21: 0 | BW21: 0 | BX21: 11000000 | BY21: 0 | BZ21: 0 | CA21: 800000 | CB21: 100000 | CC21: 150000 | CD21: 0 | CE21: 1050000 | CF21: 12050000 | CG21: 0 | CH21: 0 | CI21: 0 | CJ21: 0 | CK21: 0 | CL21: 0 | CM21: 0 | CN21: 0 | CO21: 5500 | CP21: 0 | CQ21: 5500 | CR21: 8944500 | CS21: 0 | CT21: 8944500 | CU21: 1700000 | CV21: 0 | CW21: 300000 | CY21: 0 | CZ21: 2000000 | DA21: 3050000 | DB21: 200000 | DC21: 12200000 | DE21: Việt PhúSouthFinance | DF21: 833333.33 | DG21: HO | DI21: Việt PhúSouth
A22: 19 | B22: VP005368 | C22: Phan Thị Hải | D22: Finance | E22: Accounting & Tax | F22: Senior Associate | G22: General Accountant | H22: South | I22: Việt Phú | J22: Full-time | K22: Permanent | L22: 43739 | P22: LC | Q22: LTTP | R22: L | S22: 0 | T22: 10000000 | V22: 10000000 | W22: 0 | X22: 0 | Y22: 0 | Z22: 0 | AA22: 0 | AB22: 0 | AC22: 0 | AD22: TB, CN | AE22: 21 | AF22: 21 | AG22: 0 | AH22: 0 | AI22: 0 | AJ22: 21 | AK22: 0 | AL22: 0 | AM22: 0 | AN22: 0 | AO22: 0 | AP22: 0 | AQ22: 10000000 | AR22: 0 | AS22: 0 | AT22: 10000000 | AU22: 0 | AV22: 0 | AW22: 0 | AX22: 0 | AY22: 0 | AZ22: 0 | BA22: 0 | BB22: 0 | BC22: 0 | BD22: 0 | BE22: 0 | BF22: 0 | BG22: 0 | BH22: 0 | BI22: 0 | BJ22: 0 | BK22: 0 | BL22: 0 | BM22: 0 | BN22: 0 | BO22: 0 | BP22: 0 | BQ22: 0 | BR22: 0 | BS22: 0 | BT22: 10000000 | BU22: 0 | BV22: 0 | BW22: 0 | BX22: 11000000 | BY22: 1 | BZ22: 4400000 | CA22: 800000 | CB22: 100000 | CC22: 150000 | CD22: 0 | CE22: 1050000 | CF22: 16450000 | CG22: 0 | CH22: 0 | CI22: 0 | CJ22: 0 | CK22: 0 | CL22: 100000 | CM22: 0 | CN22: 0 | CO22: 0 | CP22: 0 | CQ22: 100000 | CR22: 8850000 | CS22: 0 | CT22: 8850000 | CU22: 1700000 | CV22: 0 | CW22: 300000 | CY22: 0 | CZ22: 2000000 | DA22: 3050000 | DB22: 200000 | DC22: 12200000 | DE22: Việt PhúSouthFinance | DF22: 833333.33 | DG22: HO | DI22: Việt PhúSouth
A23: 20 | B23: VP006197 | C23: Trần Minh Tâm | D23: Finance | E23: Bank Partnership | F23: Manager | G23: Bank Partnership Manager | H23: South | I23: Việt Phú | J23: Full-time | K23: Permanent | L23: 44445 | P23: LC | Q23: LTTP | R23: L | S23: 0 | T23: 40000000 | V23: 40000000 | W23: 0 | X23: 0 | Y23: 0 | Z23: 0 | AA23: 0 | AB23: 0 | AC23: 0 | AD23: TB, CN | AE23: 21 | AF23: 19 | AG23: 2 | AH23: 0 | AI23: 0 | AJ23: 21 | AK23: 0 | AL23: 0 | AM23: 0 | AN23: 0 | AO23: 0 | AP23: 0 | AQ23: 40000000 | AR23: 0 | AS23: 0 | AT23: 40000000 | AU23: 0 | AV23: 0 | AW23: 0 | AX23: 0 | AY23: 0 | AZ23: 0 | BA23: 0 | BB23: 0 | BC23: 0 | BD23: 0 | BE23: 0 | BF23: 0 | BG23: 0 | BH23: 0 | BI23: 0 | BJ23: 0 | BK23: 0 | BL23: 0 | BM23: 0 | BN23: 0 | BO23: 0 | BP23: 0 | BQ23: 0 | BR23: 0 | BS23: 0 | BT23: 40000000 | BU23: 0 | BV23: 0 | BW23: 0 | BX23: 11000000 | BY23: 0 | BZ23: 0 | CA23: 2384000 | CB23: 400000 | CC23: 447000 | CD23: 0 | CE23: 3231000 | CF23: 14231000 | CG23: 25769000 | CH23: 3503800 | CI23: 0 | CJ23: 3503800 | CK23: 0 | CL23: 149000 | CM23: 0 | CN23: 0 | CO23: 0 | CP23: 0 | CQ23: 149000 | CR23: 33116200 | CS23: 0 | CT23: 33116200 | CU23: 5066000 | CV23: 0 | CW23: 894000 | CY23: 0 | CZ23: 5960000 | DA23: 9191000 | DB23: 596000 | DC23: 46556000 | DE23: Việt PhúSouthFinance | DF23: 3333333.3 | DG23: HO | DI23: Việt PhúSouth
A24: 21 | B24: VP004962 | C24: Lê Thị Bạch Kim | D24: Finance | E24: Facilities & Workplace support | F24: Associate | G24: Personal Assistant cum Admin | H24: South | I24: Việt Phú | J24: Full-time | K24: Permanent | L24: 43530 | P24: LC | Q24: LTTP | R24: L | S24: 0 | T24: 5000000 | V24: 5000000 | W24: 0 | X24: 0 | Y24: 0 | Z24: 0 | AA24: 0 | AB24: 0 | AC24: 0 | AD24: TB, CN | AE24: 21 | AF24: 16 | AG24: 5 | AH24: 0 | AI24: 0 | AJ24: 21 | AK24: 0 | AL24: 0 | AM24: 0 | AN24: 0 | AO24: 0 | AP24: 0 | AQ24: 5000000 | AR24: 0 | AS24: 0 | AT24: 5000000 | AU24: 0 | AV24: 0 | AW24: 0 | AX24: 0 | AY24: 0 | AZ24: 0 | BA24: 0 | BB24: 0 | BC24: 0 | BD24: 0 | BE24: 0 | BF24: 0 | BG24: 0 | BH24: 0 | BI24: 0 | BJ24: 0 | BK24: 0 | BL24: 0 | BM24: 0 | BN24: 0 | BO24: 0 | BP24: 0 | BQ24: 0 | BR24: 0 | BS24: 0 | BT24: 5000000 | BU24: 0 | BV24: 0 | BW24: 0 | BX24: 11000000 | BY24: 0 | BZ24: 0 | CA24: 400000 | CB24: 50000 | CC24: 75000 | CD24: 0 | CE24: 525000 | CF24: 11525000 | CG24: 0 | CH24: 0 | CI24: 0 | CJ24: 0 | CK24: 0 | CL24: 50000 | CM24: 0 | CN24: 0 | CO24: 137000 | CP24: 0 | CQ24: 187000 | CR24: 4288000 | CS24: 0 | CT24: 4288000 | CU24: 850000 | CV24: 0 | CW24: 150000 | CY24: 0 | CZ24: 1000000 | DA24: 1525000 | DB24: 100000 | DC24: 6100000 | DE24: Việt PhúSouthFinance | DF24: 416666.67 | DG24: HO | DI24: Việt PhúSouth
